Workbook

Sheet Human Development Index 2022
A1: Region | B1: Human Development Index 2022
A2: Somalia | B2: 0.38
A3: South Sudan | B3: 0.381
A4: Central African Republic | B4: 0.387
A5: Niger | B5: 0.394
A6: Chad | B6: 0.394
A7: Mali | B7: 0.41
A8: Burundi | B8: 0.42
A9: Yemen | B9: 0.424
A10: Burkina Faso | B10: 0.438
A11: Sierra Leone | B11: 0.458
A12: Mozambique | B12: 0.461
A13: Afghanistan | B13: 0.462
... A194: Switzerland | B194: 0.967

Sheet 202503421 Tourism Ireland - Dis
A1: Household disposable income
A2: US dollars/capita, 2023
A3: Category | B3: Gross disposable income per capita of households and NPISH
A4: United States | B4: 63084.019
A5: Luxembourg | B5: 50501.349
A6: Switzerland | B6: 47123.85
A7: Germany | B7: 42417.404
A8: Australia | B8: 41199.647
A9: Austria | B9: 40933.733
A10: Belgium | B10: 37365.363
A11: Netherlands | B11: 36367.868
A12: United Kingdom | B12: 36196.55
A13: Canada | B13: 35560.624
A14: France | B14: 35000.876
A15: Italy | B15: 34673.924
... A20: Denmark | B20: 30101.188
A23: https://www.oecd.org/en/data/indicators/household-disposable-income.html?oecdcontrol-3fafbcc227-var1=USA%7CGBR%7CDEU%7CFRA%7CESP%7CITA%7CCAN%7CAUS%7CNZL%7CBEL%7CLUX%7CNLD%7CDNK%7CFIN%7CIRL%7CNOR%7CSWE%7CCHE%7CAUT

Sheet Country Decoder - Final 2503205
X1: Outputs | Z1: 350000000 | AG1: Change Y1 to allocate budget across markets
A2: Audience Ratio to Departure | B2: Audience(m) | C2: SV -AD | D2: SV - Flights to AD | E2: SV - AD 23 | F2: SV - Flights to AD 23 | G2: Population | H2: Tourist Departures | I2: Trips(000s) | J2: Spend(m-euro) | L2: Country | M2: Spends Per Trip | N2: Tourist Departures / Population | O2: Search Volume - 'Flight to Abu Dhabi' | P2: =GDP!D1 -> GDP - Growth | Q2: =DPI!B1 -> Disposable Personal Income (USD) | R2: ='Cost of Media'!B1 -> Media Cost | S2: Global Explorers (Audience M) | T2: Budget Split | U2: Market Tiering | V2: Audience Ratio vs. Total Population | X2: Weighted Score | Y2: % Split | Z2: Budget Split | AG2: if you want to change the allocation of a market, simply change it's Market Tiering in U column and paste the new values from W36
A3: =B3/G3 -> 0.40366969 | B3: 4581651 | C3: 18791890 | D3: 69430 | E3: 9975490 | F3: 85740 | G3: 11350000 | H3: 18906000 | I3: 2000 | J3: 230 | L3: UAE | M3: 5.8321579 | N3: =H3/G3 -> 1.6657269 | O3: =C3+D3+E3+F3 -> 28922550 | P3: =VLOOKUP(L3,GDP!$A$2:$D$27,4,FALSE) -> 0.021447497 | Q3: =VLOOKUP(L3,DPI!$A$1:$B$27,2,FALSE) -> 36020 | R3: 7.8 | S3: =B3/1000000 -> 4.581651 | T3: 10 | U3: 2 | V3: =A3 -> 0.40366969 | X3: =SUMPRODUCT($M$32:$V$32,M37:V37) -> 106.74562 | Y3: =X3/SUM($X$3:$X$28) -> 0.034670708 | Z3: =Y3*$Z$1 -> 12134748 | AG3: (green markets are Tier 1, Yellows are Tier 2)
A4: =B4/G4 -> 0.035599178 | B4: 12367235 | C4: 3036780 | D4: 70340 | E4: 2947460 | F4: 48810 | G4: 347402264 | H4: 1.7093009e+08 | I4: 704.9 | J4: 21540 | L4: USA | M4: 10 | N4: =H4/G4 -> 0.49202355 | O4: =C4+D4+E4+F4 -> 6103390 | P4: =VLOOKUP(L4,GDP!$A$2:$D$27,4,FALSE) -> 0.045333059 | Q4: =VLOOKUP(L4,DPI!$A$1:$B$27,2,FALSE) -> 60944 | R4: 12 | S4: =B4/1000000 -> 12.367235 | T4: 2.5 | U4: 10 | V4: =A4 -> 0.035599178 | X4: =SUMPRODUCT($M$32:$V$32,M38:V38) -> 223.84196 | Y4: =X4/SUM($X$3:$X$28) -> 0.072703305 | Z4: =Y4*$Z$1 -> 25446157
A5: =B5/G5 -> 0.086109479 | B5: 5991450 | C5: 2248410 | D5: 169080 | E5: 1782130 | F5: 136400 | G5: 69579448 | H5: 93086000 | I5: 1245.1 | J5: 7400 | L5: UK | M5: 6.0043325 | N5: =H5/G5 -> 1.3378376 | O5: =C5+D5+E5+F5 -> 4336020 | P5: =VLOOKUP(L5,GDP!$A$2:$D$27,4,FALSE) -> 0.053512623 | Q5: =VLOOKUP(L5,DPI!$A$1:$B$27,2,FALSE) -> 36077 | R5: 9.5 | S5: =B5/1000000 -> 5.99145 | T5: 2.6 | U5: 10 | V5: =A5 -> 0.086109479 | X5: =SUMPRODUCT($M$32:$V$32,M39:V39) -> 220.45948 | Y5: =X5/SUM($X$3:$X$28) -> 0.071604685 | Z5: =Y5*$Z$1 -> 25061640
A6: =B6/G6 -> 0.062525275 | B6: 5227113 | C6: 1384090 | D6: 5530 | E6: 1351080 | F6: 3820 | G6: 83600000 | H6: 99533000 | I6: 504.2 | J6: 11200 | L6: Germany | M6: 4.4833256 | N6: =H6/G6 -> 1.1905861 | O6: =C6+D6+E6+F6 -> 2744520 | P6: =VLOOKUP(L6,GDP!$A$2:$D$27,4,FALSE) -> 0.01846286 | Q6: =VLOOKUP(L6,DPI!$A$1:$B$27,2,FALSE) -> 42417 | R6: 7.5 | S6: =B6/1000000 -> 5.227113 | T6: 1.6 | U6: 10 | V6: =A6 -> 0.062525275 | X6: =SUMPRODUCT($M$32:$V$32,M40:V40) -> 211.90058 | Y6: =X6/SUM($X$3:$X$28) -> 0.068824776 | Z6: =Y6*$Z$1 -> 24088672
A7: =B7/G7 -> 0.065790013 | B7: 4385431 | C7: 1319680 | D7: 4240 | E7: 1175450 | F7: 2830 | G7: 66658005 | H7: 49276000 | I7: 433.9 | J7: 3600 | L7: France | M7: 5.8127874 | N7: =H7/G7 -> 0.73923605 | O7: =C7+D7+E7+F7 -> 2502200 | P7: =VLOOKUP(L7,GDP!$A$2:$D$27,4,FALSE) -> 0.015496521 | Q7: =VLOOKUP(L7,DPI!$A$1:$B$27,2,FALSE) -> 35001 | R7: 7 | S7: =B7/1000000 -> 4.385431 | T7: 1.6 | U7: 10 | V7: =A7 -> 0.065790013 | X7: =SUMPRODUCT($M$32:$V$32,M41:V41) -> 210.75121 | Y7: =X7/SUM($X$3:$X$28) -> 0.068451464 | Z7: =Y7*$Z$1 -> 23958012
A8: =B8/G8 -> 0.051211681 | B8: 5954662 | C8: 172870 | D8: 14650 | E8: 149110 | F8: 8400 | G8: 116275465 | H8: 43066000 | I8: 170 | J8: 490 | L8: Egypt | M8: 1.0681261 | N8: =H8/G8 -> 0.37037908 | O8: =C8+D8+E8+F8 -> 345030 | P8: =VLOOKUP(L8,GDP!$A$2:$D$27,4,FALSE) -> -0.093359853 | Q8: =VLOOKUP(L8,DPI!$A$1:$B$27,2,FALSE) -> 2072 | R8: 3.2 | S8: =B8/1000000 -> 5.954662 | T8: 1 | U8: 1 | V8: =A8 -> 0.051211681 | X8: =SUMPRODUCT($M$32:$V$32,M42:V42) -> 59.364733 | Y8: =X8/SUM($X$3:$X$28) -> 0.019281516 | Z8: =Y8*$Z$1 -> 6748530.5
A9: =B9/G9 -> 0.074306582 | B9: 1513675 | C9: 71900 | D9: 290 | E9: 47810 | F9: 190 | G9: 20370672 | H9: 10707000 | I9: 74 | J9: 180 | L9: Khazakstan | M9: 2.0806578 | N9: =H9/G9 -> 0.52560858 | O9: =C9+D9+E9+F9 -> 120190 | P9: =VLOOKUP(L9,GDP!$A$2:$D$27,4,FALSE) -> 0.05522278 | Q9: =VLOOKUP(L9,DPI!$A$1:$B$27,2,FALSE) -> 9660 | R9: 2.8 | S9: =B9/1000000 -> 1.513675 | T9: 3 | U9: 1 | V9: =A9 -> 0.074306582 | X9: =SUMPRODUCT($M$32:$V$32,M43:V43) -> 66.696784 | Y9: =X9/SUM($X$3:$X$28) -> 0.021662948 | Z9: =Y9*$Z$1 -> 7582031.7
A10: =B10/G10 -> 0.73347706 | B10: 1165253 | C10: 94410 | D10: 12270 | E10: 87090 | F10: 12260 | G10: 1588670 | H10: 1950000 | I10: 52.4 | J10: 260 | L10: Bahrain | M10: 4.2309976 | N10: =H10/G10 -> 1.2274418 | O10: =C10+D10+E10+F10 -> 206030 | P10: =VLOOKUP(L10,GDP!$A$2:$D$27,4,FALSE) -> 0.018873954 | Q10: =VLOOKUP(L10,DPI!$A$1:$B$27,2,FALSE) -> 25947 | R10: 4.4 | S10: =B10/1000000 -> 1.165253 | T10: 1 | U10: 0.05 | V10: =A10 -> 0.73347706 | X10: =SUMPRODUCT($M$32:$V$32,M44:V44) -> 54.617531 | Y10: =X10/SUM($X$3:$X$28) -> 0.017739637 | Z10: =Y10*$Z$1 -> 6208872.8 | AE10: <-- | AF10: aim for 4m
A11: =B11/G11 -> 0.94645448 | B11: 2744718 | C11: 139980 | D11: 16220 | E11: 98020 | F11: 14480 | G11: 2900000 | H11: 3550000 | I11: 1000 | J11: 1350 | L11: Qatar | M11: 4.1472032 | N11: =H11/G11 -> 1.2241379 | O11: =C11+D11+E11+F11 -> 268700 | P11: =VLOOKUP(L11,GDP!$A$2:$D$27,4,FALSE) -> 0.0059787223 | Q11: =VLOOKUP(L11,DPI!$A$1:$B$27,2,FALSE) -> 17459 | R11: 5.5 | S11: =B11/1000000 -> 2.744718 | T11: 4 | U11: 0.05 | V11: =A11 -> 0.94645448 | X11: =SUMPRODUCT($M$32:$V$32,M45:V45) -> 65.091672 | Y11: =X11/SUM($X$3:$X$28) -> 0.021141611 | Z11: =Y11*$Z$1 -> 7399563.9
A12: =B12/G12 -> 0.037670506 | B12: 1563326 | C12: 604940 | D12: 9120 | E12: 575590 | F12: 6950 | G12: 41500000 | H12: 37845898 | I12: 59 | J12: 2500 | L12: Canada | M12: 4.0831246 | N12: =H12/G12 -> 0.91194936 | O12: =C12+D12+E12+F12 -> 1196600 | P12: =VLOOKUP(L12,GDP!$A$2:$D$27,4,FALSE) -> -0.0071396698 | Q12: =VLOOKUP(L12,DPI!$A$1:$B$27,2,FALSE) -> 35561 | R12: 9 | S12: =B12/1000000 -> 1.563326 | T12: 1.2 | U12: 1 | V12: =A12 -> 0.037670506 | X12: =SUMPRODUCT($M$32:$V$32,M46:V46) -> 80.443355 | Y12: =X12/SUM($X$3:$X$28) -> 0.026127799 | Z12: =Y12*$Z$1 -> 9144729.7
A13: =B13/G13 -> 0.077463605 | B13: 1504678 | C13: 286520 | D13: 760 | E13: 244350 | F13: 570 | G13: 19424322 | H13: 23066000 | I13: 35.1 | J13: 930 | L13: Romania | M13: 2.2604101 | N13: =H13/G13 -> 1.1874803 | O13: =C13+D13+E13+F13 -> 532200 | P13: =VLOOKUP(L13,GDP!$A$2:$D$27,4,FALSE) -> 0.012562814 | Q13: =VLOOKUP(L13,DPI!$A$1:$B$27,2,FALSE) -> 7532 | R13: 3.5 | S13: =B13/1000000 -> 1.504678 | T13: 3 | U13: 1 | V13: =A13 -> 0.077463605 | X13: =SUMPRODUCT($M$32:$V$32,M47:V47) -> 67.726059 | Y13: =X13/SUM($X$3:$X$28) -> 0.021997253 | Z13: =Y13*$Z$1 -> 7699038.7
A14: =B14/G14 -> 0.094624099 | B14: 452370 | C14: 139390 | D14: 1260 | E14: 98490 | F14: 1000 | G14: 4780706 | H14: 6633000 | I14: 1565.8 | J14: 470 | L14: Oman | M14: 1.6150578 | N14: =H14/G14 -> 1.387452 | O14: =C14+D14+E14+F14 -> 240140 | P14: =VLOOKUP(L14,GDP!$A$2:$D$27,4,FALSE) -> -0.02423721 | Q14: =VLOOKUP(L14,DPI!$A$1:$B$27,2,FALSE) -> 16800 | R14: 3.8 | S14: =B14/1000000 -> 0.45237 | T14: 3.5 | U14: 0.05 | V14: =A14 -> 0.094624099 | X14: =SUMPRODUCT($M$32:$V$32,M48:V48) -> 57.374399 | Y14: =X14/SUM($X$3:$X$28) -> 0.01863506 | Z14: =Y14*$Z$1 -> 6522271.1
A15: =B15/G15 -> 0.036562023 | B15: 1733772 | C15: 641800 | D15: 2170 | E15: 609940 | F15: 1750 | G15: 47420024 | H15: 22816000 | I15: 52.8 | J15: 5700 | L15: Spain | M15: 3.6563048 | N15: =H15/G15 -> 0.48114695 | O15: =C15+D15+E15+F15 -> 1255660 | P15: =VLOOKUP(L15,GDP!$A$2:$D$27,4,FALSE) -> 0.044715447 | Q15: =VLOOKUP(L15,DPI!$A$1:$B$27,2,FALSE) -> 31193 | R15: 6.5 | S15: =B15/1000000 -> 1.733772 | T15: 1.2 | U15: 1 | V15: =A15 -> 0.036562023 | X15: =SUMPRODUCT($M$32:$V$32,M49:V49) -> 73.745254 | Y15: =X15/SUM($X$3:$X$28) -> 0.023952273 | Z15: =Y15*$Z$1 -> 8383295.5
A16: =B16/G16 -> 0.13368511 | B16: 2369212 | C16: 442290 | D16: 4160 | E16: 431370 | F16: 3130 | G16: 17722333 | H16: 22045000 | I16: 61.4 | J16: 2670 | L16: Netherlands | M16: 5.6280836 | N16: =H16/G16 -> 1.2439107 | O16: =C16+D16+E16+F16 -> 880950 | P16: =VLOOKUP(L16,GDP!$A$2:$D$27,4,FALSE) -> 0.036674817 | Q16: =VLOOKUP(L16,DPI!$A$1:$B$27,2,FALSE) -> 40722 | R16: 7.2 | S16: =B16/1000000 -> 2.369212 | T16: 1.2 | U16: 1 | V16: =A16 -> 0.13368511 | X16: =SUMPRODUCT($M$32:$V$32,M50:V50) -> 78.538496 | Y16: =X16/SUM($X$3:$X$28) -> 0.025509106 | Z16: =Y16*$Z$1 -> 8928187
A17: =B17/G17 -> 0.0058892883 | B17: 718260 | C17: 161240 | D17: 72490 | E17: 520 | F17: 360 | G17: 121960408 | H17: 20081000 | I17: 27 | J17: 1140 | L17: Japan | M17: 6.3468851 | N17: =H17/G17 -> 0.16465179 | O17: =C17+D17+E17+F17 -> 234610 | P17: =VLOOKUP(L17,GDP!$A$2:$D$27,4,FALSE) -> 0.039741679 | Q17: =VLOOKUP(L17,DPI!$A$1:$B$27,2,FALSE) -> 28040 | R17: 8.5 | S17: =B17/1000000 -> 0.71826 | T17: 1.3 | U17: 1 | V17: =A17 -> 0.0058892883 | X17: =SUMPRODUCT($M$32:$V$32,M51:V51) -> 80.714099 | Y17: =X17/SUM($X$3:$X$28) -> 0.026215736 | Z17: =Y17*$Z$1 -> 9175507.6
A18: =B18/G18 -> 0.036384716 | B18: 1349855 | C18: 62390 | D18: 370 | E18: 54330 | F18: 290 | G18: 37099506 | H18: 8437000 | I18: 104.6 | J18: 110 | L18: Uzbekistan | M18: 3.9248221 | N18: =H18/G18 -> 0.22741543 | O18: =C18+D18+E18+F18 -> 117380 | P18: =VLOOKUP(L18,GDP!$A$2:$D$27,4,FALSE) -> 0.15241558 | Q18: =VLOOKUP(L18,DPI!$A$1:$B$27,2,FALSE) -> 1706 | R18: 2.2 | S18: =B18/1000000 -> 1.349855 | T18: 2.5 | U18: 1 | V18: =A18 -> 0.036384716 | X18: =SUMPRODUCT($M$32:$V$32,M52:V52) -> 65.584656 | Y18: =X18/SUM($X$3:$X$28) -> 0.021301731 | Z18: =Y18*$Z$1 -> 7455605.9
A19: =B19/G19 -> 0.11301397 | B19: 4477244 | C19: 663510 | D19: 1550 | E19: 585130 | F19: 1550 | G19: 39616730 | H19: 50600000 | I19: 40.7 | J19: 1570 | L19: Poland | M19: 2.6190282 | N19: =H19/G19 -> 1.2772382 | O19: =C19+D19+E19+F19 -> 1251740 | P19: =VLOOKUP(L19,GDP!$A$2:$D$27,4,FALSE) -> 0.078193833 | Q19: =VLOOKUP(L19,DPI!$A$1:$B$27,2,FALSE) -> 10080 | R19: 4.5 | S19: =B19/1000000 -> 4.477244 | T19: 1 | U19: 1 | V19: =A19 -> 0.11301397 | X19: =SUMPRODUCT($M$32:$V$32,M53:V53) -> 64.776156 | Y19: =X19/SUM($X$3:$X$28) -> 0.021039132 | Z19: =Y19*$Z$1 -> 7363696.3 | AG19: =200/350 -> 0.57142857
A20: =B20/G20 -> 0.0043850772 | B20: 227147 | C20: 59540 | D20: 330 | E20: 44400 | F20: 330 | G20: 51800000 | H20: 28714000 | I20: 37.7 | J20: 2280 | L20: South Korea | M20: 4.0416603 | N20: =H20/G20 -> 0.55432432 | O20: =C20+D20+E20+F20 -> 104600 | P20: =VLOOKUP(L20,GDP!$A$2:$D$27,4,FALSE) -> -0.042268593 | Q20: =VLOOKUP(L20,DPI!$A$1:$B$27,2,FALSE) -> 36230 | R20: 8 | S20: =B20/1000000 -> 0.227147 | T20: 1.1 | U20: 1 | V20: =A20 -> 0.0043850772 | X20: =SUMPRODUCT($M$32:$V$32,M54:V54) -> 77.624376 | Y20: =X20/SUM($X$3:$X$28) -> 0.025212202 | Z20: =Y20*$Z$1 -> 8824270.7
A21: =B21/G21 -> 0.12419864 | B21: 344900 | C21: 136500 | D21: 570 | E21: 69270 | F21: 570 | G21: 2777003 | H21: 1868000 | I21: 12 | J21: 30 | L21: Armenia | M21: 2.0528138 | N21: =H21/G21 -> 0.67266762 | O21: =C21+D21+E21+F21 -> 206910 | P21: =VLOOKUP(L21,GDP!$A$2:$D$27,4,FALSE) -> 0.028394627 | Q21: =VLOOKUP(L21,DPI!$A$1:$B$27,2,FALSE) -> 2555 | R21: 2.8 | S21: =B21/1000000 -> 0.3449 | T21: 2 | U21: 1 | V21: =A21 -> 0.12419864 | X21: =SUMPRODUCT($M$32:$V$32,M55:V55) -> 62.828597 | Y21: =X21/SUM($X$3:$X$28) -> 0.02040657 | Z21: =Y21*$Z$1 -> 7142299.5
A22: =B22/G22 -> 0.097492624 | B22: 1152904 | C22: 285990 | D22: 990 | E22: 221500 | F22: 740 | G22: 11825551 | H22: 14191000 | I22: 36.6 | J22: 2700 | L22: Belgium | M22: 6.8996981 | N22: =H22/G22 -> 1.2000286 | O22: =C22+D22+E22+F22 -> 509220 | P22: =VLOOKUP(L22,GDP!$A$2:$D$27,4,FALSE) -> 0.037650602 | Q22: =VLOOKUP(L22,DPI!$A$1:$B$27,2,FALSE) -> 37365 | R22: 6.5 | S22: =B22/1000000 -> 1.152904 | T22: 1.1 | U22: 1 | V22: =A22 -> 0.097492624 | X22: =SUMPRODUCT($M$32:$V$32,M56:V56) -> 76.550766 | Y22: =X22/SUM($X$3:$X$28) -> 0.024863496 | Z22: =Y22*$Z$1 -> 8702223.6
A23: =B23/G23 -> 0.021331154 | B23: 1257134 | C23: 1076490 | D23: 3370 | E23: 1109260 | F23: 3220 | G23: 58934177 | H23: 62207000 | I23: 247 | J23: 5600 | L23: Italy | M23: 4.996738 | N23: =H23/G23 -> 1.0555335 | O23: =C23+D23+E23+F23 -> 2192340 | P23: =VLOOKUP(L23,GDP!$A$2:$D$27,4,FALSE) -> 0.021079258 | Q23: =VLOOKUP(L23,DPI!$A$1:$B$27,2,FALSE) -> 34703 | R23: 7.5 | S23: =B23/1000000 -> 1.257134 | T23: 1.3 | U23: 10 | V23: =A23 -> 0.021331154 | X23: =SUMPRODUCT($M$32:$V$32,M57:V57) -> 210.60139 | Y23: =X23/SUM($X$3:$X$28) -> 0.068402801 | Z23: =Y23*$Z$1 -> 23940980
A24: =B24/G24 -> 0.036996134 | B24: 52696625 | C24: 32530 | D24: 160 | E24: 21260 | F24: 160 | G24: 1424381924 | H24: 154632000 | I24: 177 | J24: 19650 | L24: China | M24: 1 | N24: =H24/G24 -> 0.10856077 | O24: =C24+D24+E24+F24 -> 54110 | P24: =VLOOKUP(L24,GDP!$A$2:$D$27,4,FALSE) -> 0.025762748 | Q24: =VLOOKUP(L24,DPI!$A$1:$B$27,2,FALSE) -> 5738 | R24: 11.5 | S24: =B24/1000000 -> 52.696625 | T24: 1.7 | U24: 10 | V24: =A24 -> 0.036996134 | X24: =SUMPRODUCT($M$32:$V$32,M58:V58) -> 211.99148 | Y24: =X24/SUM($X$3:$X$28) -> 0.068854299 | Z24: =Y24*$Z$1 -> 24099005
A25: =B25/G25 -> 0.23580106 | B25: 8958075 | C25: 390390 | D25: 17520 | E25: 243830 | F25: 13820 | G25: 37989969 | H25: 27196000 | I25: 1452.6 | J25: 600 | L25: Saudi Arabia | M25: 2.0912532 | N25: =H25/G25 -> 0.71587318 | O25: =C25+D25+E25+F25 -> 665560 | P25: =VLOOKUP(L25,GDP!$A$2:$D$27,4,FALSE) -> -0.0014824602 | Q25: =VLOOKUP(L25,DPI!$A$1:$B$27,2,FALSE) -> 10224 | R25: 6.5 | S25: =B25/1000000 -> 8.958075 | T25: 1.3 | U25: 10 | V25: =A25 -> 0.23580106 | X25: =SUMPRODUCT($M$32:$V$32,M59:V59) -> 202.2057 | Y25: =X25/SUM($X$3:$X$28) -> 0.065675902 | Z25: =Y25*$Z$1 -> 22986566
A26: =B26/G26 -> 0.038245221 | B26: 5504874 | C26: 1447698 | D26: 27896 | E26: 994422 | F26: 18822 | G26: 143936258 | H26: 45330000 | I26: 905.5 | J26: 500 | L26: Russia | M26: 1.9591423 | N26: =H26/G26 -> 0.31493107 | O26: =C26+D26+E26+F26 -> 2488838 | P26: =VLOOKUP(L26,GDP!$A$2:$D$27,4,FALSE) -> -0.039333642 | Q26: =VLOOKUP(L26,DPI!$A$1:$B$27,2,FALSE) -> 9053 | R26: 3.8 | S26: =B26/1000000 -> 5.504874 | T26: 1.1 | U26: 10 | V26: =A26 -> 0.038245221 | X26: =SUMPRODUCT($M$32:$V$32,M60:V60) -> 193.9838 | Y26: =X26/SUM($X$3:$X$28) -> 0.063005449 | Z26: =Y26*$Z$1 -> 22051907
A27: =B27/G27 -> 0.64767527 | B27: 2841422 | C27: 156750 | D27: 14530 | E27: 136790 | F27: 11620 | G27: 4387109 | H27: 2950000 | I27: 84 | J27: 50 | L27: Kuwait | M27: 2.6880376 | N27: =H27/G27 -> 0.6724246 | O27: =C27+D27+E27+F27 -> 319690 | P27: =VLOOKUP(L27,GDP!$A$2:$D$27,4,FALSE) -> -0.034477322 | Q27: =VLOOKUP(L27,DPI!$A$1:$B$27,2,FALSE) -> 26600 | R27: 5.2 | S27: =B27/1000000 -> 2.841422 | T27: 1.1 | U27: 0.05 | V27: =A27 -> 0.64767527 | X27: =SUMPRODUCT($M$32:$V$32,M61:V61) -> 55.155708 | Y27: =X27/SUM($X$3:$X$28) -> 0.017914435 | Z27: =Y27*$Z$1 -> 6270052.3
A28: =B28/G28 -> 0.081823974 | B28: 119021703 | C28: 3792180 | D28: 206010 | E28: 2800880 | F28: 111580 | G28: 1454606724 | H28: 26915000 | I28: 2200.3 | J28: 1340 | L28: India | M28: 3.3116351 | N28: =H28/G28 -> 0.018503283 | O28: =C28+D28+E28+F28 -> 6910650 | P28: =VLOOKUP(L28,GDP!$A$2:$D$27,4,FALSE) -> 0.071117933 | Q28: =VLOOKUP(L28,DPI!$A$1:$B$27,2,FALSE) -> 2531 | R28: 3.5 | S28: =B28/1000000 -> 119.0217 | T28: 2.1 | U28: 10 | V28: =A28 -> 0.081823974 | X28: =SUMPRODUCT($M$32:$V$32,M62:V62) -> 199.52774 | Y28: =X28/SUM($X$3:$X$28) -> 0.064806106 | Z28: =Y28*$Z$1 -> 22682137
L29: Avg | M29: =AVERAGE(M3:M28) -> 3.9551647 | N29: =AVERAGE(N3:N28) -> 0.80642574 | O29: =AVERAGE(O3:O28) -> 2488839.5 | P29: =AVERAGE(P3:P28) -> 0.020782254 | Q29: =AVERAGE(Q3:Q28) -> 23162.692 | R29: =AVERAGE(R3:R28) -> 6.1615385 | S29: =AVERAGE(S3:S28) -> 9.6194111 | T29: =AVERAGE(T3:T28) -> 2.1153846 | ... V29: =AVERAGE(V3:V28) -> 0.16470715 | Z29: =+SUM(Z3:Z28)=Z1 -> TRUE
L30: St Dv | M30: =STDEV(M3:M28) -> 2.1005276 | N30: =STDEV(N3:N28) -> 0.46157889 | O30: =STDEV(O3:O28) -> 5695386.2 | P30: =STDEV(P3:P28) -> 0.046847441 | Q30: =STDEV(Q3:Q28) -> 16052.908 | R30: =STDEV(R3:R28) -> 2.673137 | S30: =STDEV(S3:S28) -> 24.493177 | T30: =STDEV(T3:T28) -> 1.8200423 | ... V30: =STDEV(V3:V28) -> 0.24299524
U31: Edited for Pan Arab TV impact
L32: Model Weight | M32: 5 | N32: 0.5 | O32: 2 | P32: 1 | Q32: 5 | R32: 20 | S32: 2 | T32: 15 | U32: 200 | V32: 0.01
K35: Index Table
K36: Tier | L36: Country | M36: =_xlfn.CONCAT(M2," Index") -> Spends Per Trip Index | N36: =_xlfn.CONCAT(N2," Index") -> Tourist Departures / Population Index | O36: =_xlfn.CONCAT(O2," Index") -> Search Volume - 'Flight to Abu Dhabi' Index | P36: =_xlfn.CONCAT(P2," Index") -> GDP - Growth Index | Q36: =_xlfn.CONCAT(Q2," Index") -> Disposable Personal Income (USD) Index | R36: =_xlfn.CONCAT(R2," Index") -> Media Cost Index | S36: =_xlfn.CONCAT(S2," Index") -> Global Explorers (Audience M) Index | T36: =_xlfn.CONCAT(T2," Index") -> Budget Split Index | ... V36: =_xlfn.CONCAT(V2," Index") -> Audience Ratio vs. Total Population Index
K37: Tier 1 | L37: UAE | M37: =_xlfn.NORM.DIST(M3,M$29,M$30,TRUE) -> 0.81422715 | N37: =_xlfn.NORM.DIST(N3,N$29,N$30,TRUE) -> 0.9686742 | O37: =_xlfn.NORM.DIST(O3,O$29,O$30,TRUE) -> 0.99999827 | P37: =_xlfn.NORM.DIST(P3,P$29,P$30,TRUE) -> 0.50566487 | Q37: =_xlfn.NORM.DIST(Q3,Q$29,Q$30,TRUE) -> 0.78841486 | R37: =_xlfn.NORM.DIST(R3,R$29,R$30,TRUE) -> 0.73004062 | S37: =_xlfn.NORM.DIST(S3,S$29,S$30,TRUE) -> 0.41852039 | T37: =_xlfn.NORM.DIST(T3,T$29,T$30,TRUE) -> 0.99999262 | ... V37: =_xlfn.NORM.DIST(V3,V$29,V$30,TRUE) -> 0.83729573 | AH37: 7.8
K38: Tier 1 | L38: USA | M38: =_xlfn.NORM.DIST(M4,M$29,M$30,TRUE) -> 0.99799751 | N38: =_xlfn.NORM.DIST(N4,N$29,N$30,TRUE) -> 0.24788984 | O38: =_xlfn.NORM.DIST(O4,O$29,O$30,TRUE) -> 0.73717013 | P38: =_xlfn.NORM.DIST(P4,P$29,P$30,TRUE) -> 0.69988112 | Q38: =_xlfn.NORM.DIST(Q4,Q$29,Q$30,TRUE) -> 0.99070243 | R38: =_xlfn.NORM.DIST(R4,R$29,R$30,TRUE) -> 0.98552341 | S38: =_xlfn.NORM.DIST(S4,S$29,S$30,TRUE) -> 0.54466256 | T38: =_xlfn.NORM.DIST(T4,T$29,T$30,TRUE) -> 0.58368208 | ... V38: =_xlfn.NORM.DIST(V4,V$29,V$30,TRUE) -> 0.2975989 | AH38: 12
K39: Tier 1 | L39: UK | M39: =_xlfn.NORM.DIST(M5,M$29,M$30,TRUE) -> 0.83535601 | N39: =_xlfn.NORM.DIST(N5,N$29,N$30,TRUE) -> 0.87519382 | O39: =_xlfn.NORM.DIST(O5,O$29,O$30,TRUE) -> 0.62715562 | P39: =_xlfn.NORM.DIST(P5,P$29,P$30,TRUE) -> 0.75761731 | Q39: =_xlfn.NORM.DIST(Q5,Q$29,Q$30,TRUE) -> 0.78944125 | R39: =_xlfn.NORM.DIST(R5,R$29,R$30,TRUE) -> 0.89414785 | S39: =_xlfn.NORM.DIST(S5,S$29,S$30,TRUE) -> 0.44112352 | T39: =_xlfn.NORM.DIST(T5,T$29,T$30,TRUE) -> 0.60498282 | ... V39: =_xlfn.NORM.DIST(V5,V$29,V$30,TRUE) -> 0.37317589 | AH39: 9.5
K40: Tier 1 | L40: Germany | M40: =_xlfn.NORM.DIST(M6,M$29,M$30,TRUE) -> 0.59926381 | N40: =_xlfn.NORM.DIST(N6,N$29,N$30,TRUE) -> 0.79737301 | O40: =_xlfn.NORM.DIST(O6,O$29,O$30,TRUE) -> 0.51790353 | P40: =_xlfn.NORM.DIST(P6,P$29,P$30,TRUE) -> 0.48025662 | Q40: =_xlfn.NORM.DIST(Q6,Q$29,Q$30,TRUE) -> 0.88481923 | R40: =_xlfn.NORM.DIST(R6,R$29,R$30,TRUE) -> 0.69171174 | S40: =_xlfn.NORM.DIST(S6,S$29,S$30,TRUE) -> 0.42884031 | T40: =_xlfn.NORM.DIST(T6,T$29,T$30,TRUE) -> 0.38852258 | ... V40: =_xlfn.NORM.DIST(V6,V$29,V$30,TRUE) -> 0.33705654 | AH40: 7.5
K41: Tier 1 | L41: France | M41: =_xlfn.NORM.DIST(M7,M$29,M$30,TRUE) -> 0.81174906 | N41: =_xlfn.NORM.DIST(N7,N$29,N$30,TRUE) -> 0.44213243 | O41: =_xlfn.NORM.DIST(O7,O$29,O$30,TRUE) -> 0.50093585 | P41: =_xlfn.NORM.DIST(P7,P$29,P$30,TRUE) -> 0.45508321 | Q41: =_xlfn.NORM.DIST(Q7,Q$29,Q$30,TRUE) -> 0.76957735 | R41: =_xlfn.NORM.DIST(R7,R$29,R$30,TRUE) -> 0.62311112 | S41: =_xlfn.NORM.DIST(S7,S$29,S$30,TRUE) -> 0.41539388 | T41: =_xlfn.NORM.DIST(T7,T$29,T$30,TRUE) -> 0.38852258 | ... V41: =_xlfn.NORM.DIST(V7,V$29,V$30,TRUE) -> 0.34197668 | AH41: 7
K42: Tier 2 | L42: Egypt | M42: =_xlfn.NORM.DIST(M8,M$29,M$30,TRUE) -> 0.084653343 | N42: =_xlfn.NORM.DIST(N8,N$29,N$30,TRUE) -> 0.17240986 | O42: =_xlfn.NORM.DIST(O8,O$29,O$30,TRUE) -> 0.35330545 | P42: =_xlfn.NORM.DIST(P8,P$29,P$30,TRUE) -> 0.0074158208 | Q42: =_xlfn.NORM.DIST(Q8,Q$29,Q$30,TRUE) -> 0.094452751 | R42: =_xlfn.NORM.DIST(R8,R$29,R$30,TRUE) -> 0.13395493 | S42: =_xlfn.NORM.DIST(S8,S$29,S$30,TRUE) -> 0.44053093 | T42: =_xlfn.NORM.DIST(T8,T$29,T$30,TRUE) -> 0.2699929 | ... V42: =_xlfn.NORM.DIST(V8,V$29,V$30,TRUE) -> 0.32022537 | AH42: 3.2
K43: Tier 2 | L43: Khazakstan | M43: =_xlfn.NORM.DIST(M9,M$29,M$30,TRUE) -> 0.18608978 | N43: =_xlfn.NORM.DIST(N9,N$29,N$30,TRUE) -> 0.27146645 | O43: =_xlfn.NORM.DIST(O9,O$29,O$30,TRUE) -> 0.33874554 | P43: =_xlfn.NORM.DIST(P9,P$29,P$30,TRUE) -> 0.76888002 | Q43: =_xlfn.NORM.DIST(Q9,Q$29,Q$30,TRUE) -> 0.20013563 | R43: =_xlfn.NORM.DIST(R9,R$29,R$30,TRUE) -> 0.10428167 | S43: =_xlfn.NORM.DIST(S9,S$29,S$30,TRUE) -> 0.37034546 | T43: =_xlfn.NORM.DIST(T9,T$29,T$30,TRUE) -> 0.68653099 | ... V43: =_xlfn.NORM.DIST(V9,V$29,V$30,TRUE) -> 0.35493671 | AH43: 2.8
K44: Tier 2 | L44: Bahrain | M44: =_xlfn.NORM.DIST(M10,M$29,M$30,TRUE) -> 0.55223733 | N44: =_xlfn.NORM.DIST(N10,N$29,N$30,TRUE) -> 0.81914765 | O44: =_xlfn.NORM.DIST(O10,O$29,O$30,TRUE) -> 0.34427731 | P44: =_xlfn.NORM.DIST(P10,P$29,P$30,TRUE) -> 0.48375383 | Q44: =_xlfn.NORM.DIST(Q10,Q$29,Q$30,TRUE) -> 0.56884944 | R44: =_xlfn.NORM.DIST(R10,R$29,R$30,TRUE) -> 0.25495495 | S44: =_xlfn.NORM.DIST(S10,S$29,S$30,TRUE) -> 0.36498562 | T44: =_xlfn.NORM.DIST(T10,T$29,T$30,TRUE) -> 0.2699929 | ... V44: =_xlfn.NORM.DIST(V10,V$29,V$30,TRUE) -> 0.99037523 | AH44: 4.4
K45: Tier 2 | L45: Qatar | M45: =_xlfn.NORM.DIST(M11,M$29,M$30,TRUE) -> 0.53642212 | N45: =_xlfn.NORM.DIST(N11,N$29,N$30,TRUE) -> 0.81725772 | O45: =_xlfn.NORM.DIST(O11,O$29,O$30,TRUE) -> 0.34833716 | P45: =_xlfn.NORM.DIST(P11,P$29,P$30,TRUE) -> 0.37600336 | Q45: =_xlfn.NORM.DIST(Q11,Q$29,Q$30,TRUE) -> 0.36118023 | R45: =_xlfn.NORM.DIST(R11,R$29,R$30,TRUE) -> 0.40226976 | S45: =_xlfn.NORM.DIST(S11,S$29,S$30,TRUE) -> 0.38947874 | T45: =_xlfn.NORM.DIST(T11,T$29,T$30,TRUE) -> 0.84977735 | ... V45: =_xlfn.NORM.DIST(V11,V$29,V$30,TRUE) -> 0.9993526 | AH45: 5.5
K46: Tier 2 | L46: Canada | M46: =_xlfn.NORM.DIST(M12,M$29,M$30,TRUE) -> 0.52428772 | N46: =_xlfn.NORM.DIST(N12,N$29,N$30,TRUE) -> 0.59041571 | O46: =_xlfn.NORM.DIST(O12,O$29,O$30,TRUE) -> 0.41025373 | P46: =_xlfn.NORM.DIST(P12,P$29,P$30,TRUE) -> 0.27558156 | Q46: =_xlfn.NORM.DIST(Q12,Q$29,Q$30,TRUE) -> 0.78004355 | R46: =_xlfn.NORM.DIST(R12,R$29,R$30,TRUE) -> 0.85584734 | S46: =_xlfn.NORM.DIST(S12,S$29,S$30,TRUE) -> 0.37111133 | T46: =_xlfn.NORM.DIST(T12,T$29,T$30,TRUE) -> 0.3075008 | ... V46: =_xlfn.NORM.DIST(V12,V$29,V$30,TRUE) -> 0.30055854 | AH46: 9
K47: Tier 2 | L47: Romania | M47: =_xlfn.NORM.DIST(M13,M$29,M$30,TRUE) -> 0.20988415 | N47: =_xlfn.NORM.DIST(N13,N$29,N$30,TRUE) -> 0.79546914 | O47: =_xlfn.NORM.DIST(O13,O$29,O$30,TRUE) -> 0.36559305 | P47: =_xlfn.NORM.DIST(P13,P$29,P$30,TRUE) -> 0.43036255 | Q47: =_xlfn.NORM.DIST(Q13,Q$29,Q$30,TRUE) -> 0.16510313 | R47: =_xlfn.NORM.DIST(R13,R$29,R$30,TRUE) -> 0.15970743 | S47: =_xlfn.NORM.DIST(S13,S$29,S$30,TRUE) -> 0.37020673 | T47: =_xlfn.NORM.DIST(T13,T$29,T$30,TRUE) -> 0.68653099 | ... V47: =_xlfn.NORM.DIST(V13,V$29,V$30,TRUE) -> 0.35978484 | AH47: 3.5
K48: Tier 2 | L48: Oman | M48: =_xlfn.NORM.DIST(M14,M$29,M$30,TRUE) -> 0.13262743 | N48: =_xlfn.NORM.DIST(N14,N$29,N$30,TRUE) -> 0.89594508 | O48: =_xlfn.NORM.DIST(O14,O$29,O$30,TRUE) -> 0.34648481 | P48: =_xlfn.NORM.DIST(P14,P$29,P$30,TRUE) -> 0.16828105 | Q48: =_xlfn.NORM.DIST(Q14,Q$29,Q$30,TRUE) -> 0.34592061 | R48: =_xlfn.NORM.DIST(R14,R$29,R$30,TRUE) -> 0.18850108 | S48: =_xlfn.NORM.DIST(S14,S$29,S$30,TRUE) -> 0.35410203 | T48: =_xlfn.NORM.DIST(T14,T$29,T$30,TRUE) -> 0.77659979 | ... V48: =_xlfn.NORM.DIST(V14,V$29,V$30,TRUE) -> 0.38651521 | AH48: 3.8
... K62: Tier 1 | L62: India | M62: =_xlfn.NORM.DIST(M28,M$29,M$30,TRUE) -> 0.37966311 | N62: =_xlfn.NORM.DIST(N28,N$29,N$30,TRUE) -> 0.043909558 | O62: =_xlfn.NORM.DIST(O28,O$29,O$30,TRUE) -> 0.78123905 | P62: =_xlfn.NORM.DIST(P28,P$29,P$30,TRUE) -> 0.85869161 | Q62: =_xlfn.NORM.DIST(Q28,Q$29,Q$30,TRUE) -> 0.099355811 | R62: =_xlfn.NORM.DIST(R28,R$29,R$30,TRUE) -> 0.15970743 | S62: =_xlfn.NORM.DIST(S28,S$29,S$30,TRUE) -> 0.99999603 | T62: =_xlfn.NORM.DIST(T28,T$29,T$30,TRUE) -> 0.49662783 | ... V62: =_xlfn.NORM.DIST(V28,V$29,V$30,TRUE) -> 0.36651803 | AH62: 3.5
L70: UAE | M70: 4581651 | O70: UAE | P70: {=VLOOKUP(O70:O95,L70:M95,2,FALSE)} -> 4581651
L71: India | M71: 119021703 | O71: USA | P71: 12367235
L72: China | M72: 52696625 | O72: UK | P72: 5991450
L73: Russia | M73: 5504874 | O73: Germany | P73: 5227113
L74: USA | M74: 12367235 | O74: France | P74: 4385431
L75: UK | M75: 5991450 | O75: Egypt | P75: 5954662
L76: Saudi Arabia | M76: 8958075 | O76: Khazakstan | P76: 1513675
L77: Kuwait | M77: 2841422 | O77: Bahrain | P77: 1165253
L78: France | M78: 4385431 | O78: Qatar | P78: 2744718
L79: Italy | M79: 1257134 | O79: Canada | P79: 1563326
L80: Germany | M80: 5227113 | O80: Romania | P80: 1504678
L81: Egypt | M81: 5954662 | O81: Oman | P81: 452370
L82: Qatar | M82: 2744718 | O82: Spain | P82: 1733772
... L95: Belgium | M95: 1152904 | O95: India | P95: 119021703
AB98: Market | AD98: Current Budget | AE98: Recommended Budget
AB99: USA | AD99: 7100000 | AE99: 5530422
AB100: UK | AD100: €6,800,00 | AE100: 5125428
L101: Country | M101: Tourist Departures / Population | N101: Search Volume - 'Abu Dhabi' | O101: Media Cost | P101: Weighted Score | Q101: % Split | AB101: Switzerland | AD101: 100000 | AE101: 732419
L102: UAE | M102: 1.6657269 | N102: 28922550 | O102: 7.8 | P102: 106.74562 | Q102: 0.034670708 | S102: Country | AB102: Australia/New Zealand | AD102: 550000 | AE102: 995027
L103: USA | M103: 0.49202355 | N103: 6103390 | O103: 12 | P103: 223.84196 | Q103: 0.072703305 | S103: USA | T103: 25446157 | AB103: BeNe | AD103: 700000 | AE103: 1123999
L104: UK | M104: 1.3378376 | N104: 4336020 | O104: 9.5 | P104: 220.45948 | Q104: 0.071604685 | S104: UK | T104: 25061640 | AB104: Austria | AD104: 7100000 | AE104: 5530422
L105: Germany | M105: 1.1905861 | N105: 2744520 | O105: 7.5 | P105: 211.90058 | Q105: 0.068824776 | S105: China | T105: 24099005 | AB105: Canada | AD105: €6,800,00 | AE105: 5125428
L106: France | M106: 0.73923605 | N106: 2502200 | O106: 7 | P106: 210.75121 | Q106: 0.068451464 | S106: Germany | T106: 24088672 | AB106: Germany | AD106: 100000 | AE106: 732419
L107: Egypt | M107: 0.37037908 | N107: 345030 | O107: 3.2 | P107: 59.364733 | Q107: 0.019281516 | S107: France | T107: 23958012 | AB107: Spain | AD107: 550000 | AE107: 995027
L108: Khazakstan | M108: 0.52560858 | N108: 120190 | O108: 2.8 | P108: 66.696784 | Q108: 0.021662948 | S108: Italy | T108: 23940980 | AB108: Italy | AD108: 700000 | AE108: 1123999
L109: Bahrain | M109: 1.2274418 | N109: 206030 | O109: 4.4 | P109: 54.617531 | Q109: 0.017739637 | S109: Saudi Arabia | T109: 22986566 | AB109: France | AD109: 2100000 | AE109: 2072729
L110: Qatar | M110: 1.2241379 | N110: 268700 | O110: 5.5 | P110: 65.091672 | Q110: 0.021141611 | S110: India | T110: 22682137 | AB110: Nordics | AD110: 400000 | AE110: 1009352
L111: Canada | M111: 0.91194936 | N111: 1196600 | O111: 9 | P111: 80.443355 | Q111: 0.026127799 | S111: Russia | T111: 22051907
L112: Romania | M112: 1.1874803 | N112: 532200 | O112: 3.5 | P112: 67.726059 | Q112: 0.021997253 | S112: UAE | T112: 12134748
L113: Oman | M113: 1.387452 | N113: 240140 | O113: 3.8 | P113: 57.374399 | Q113: 0.01863506 | S113: Japan | T113: 9175507.6
L114: Spain | M114: 0.48114695 | N114: 1255660 | O114: 6.5 | P114: 73.745254 | Q114: 0.023952273 | S114: Canada | T114: 9144729.7
L115: Netherlands | M115: 1.2439107 | N115: 880950 | O115: 7.2 | P115: 78.538496 | Q115: 0.025509106 | S115: Netherlands | T115: 8928187
L116: Japan | M116: 0.16465179 | N116: 234610 | O116: 8.5 | P116: 80.714099 | Q116: 0.026215736 | S116: South Korea | T116: 8824270.7
L117: Uzbekistan | M117: 0.22741543 | N117: 117380 | O117: 2.2 | P117: 65.584656 | Q117: 0.021301731 | S117: Belgium | T117: 8702223.6
L118: Poland | M118: 1.2772382 | N118: 1251740 | O118: 4.5 | P118: 64.776156 | Q118: 0.021039132 | S118: Spain | T118: 8383295.5
L119: South Korea | M119: 0.55432432 | N119: 104600 | O119: 8 | P119: 77.624376 | Q119: 0.025212202 | S119: Romania | T119: 7699038.7
L120: Armenia | M120: 0.67266762 | N120: 206910 | O120: 2.8 | P120: 62.828597 | Q120: 0.02040657 | S120: Khazakstan | T120: 7582031.7
L121: Belgium | M121: 1.2000286 | N121: 509220 | O121: 6.5 | P121: 76.550766 | Q121: 0.024863496 | S121: Uzbekistan | T121: 7455605.9
L122: Italy | M122: 1.0555335 | N122: 2192340 | O122: 7.5 | P122: 210.60139 | Q122: 0.068402801 | S122: Qatar | T122: 7399563.9
... L127: India | M127: 0.018503283 | N127: 6910650 | O127: 3.5 | P127: 199.52774 | Q127: 0.064806106 | S127: Kuwait | T127: 6270052.3
S128: Bahrain | T128: 6208872.8

Sheet dataviz
C4: ='Country Decoder - Final 2503205'!K36 -> Tier | D4: ='Country Decoder - Final 2503205'!L36 -> Country | E4: ='Country Decoder - Final 2503205'!M36 -> Spends Per Trip Index | F4: ='Country Decoder - Final 2503205'!N36 -> Tourist Departures / Population Index | G4: ='Country Decoder - Final 2503205'!O36 -> Search Volume - 'Flight to Abu Dhabi' Index | H4: ='Country Decoder - Final 2503205'!P36 -> GDP - Growth Index | I4: ='Country Decoder - Final 2503205'!Q36 -> Disposable Personal Income (USD) Index | J4: ='Country Decoder - Final 2503205'!R36 -> Media Cost Index | ... N4: ='Country Decoder - Final 2503205'!V36 -> Audience Ratio vs. Total Population Index | O4: ='Country Decoder - Final 2503205'!X2 -> Weighted Score | P4: ='Country Decoder - Final 2503205'!Y2 -> % Split | Q4: ='Country Decoder - Final 2503205'!Z2 -> Budget Split | S4: Values for dropdowns:
C5: ='Country Decoder - Final 2503205'!K37 -> Tier 1 | D5: ='Country Decoder - Final 2503205'!L37 -> UAE | E5: ='Country Decoder - Final 2503205'!M37 -> 0.81422715 | F5: ='Country Decoder - Final 2503205'!N37 -> 0.9686742 | G5: ='Country Decoder - Final 2503205'!O37 -> 0.99999827 | H5: ='Country Decoder - Final 2503205'!P37 -> 0.50566487 | I5: ='Country Decoder - Final 2503205'!Q37 -> 0.78841486 | J5: ='Country Decoder - Final 2503205'!R37 -> 0.73004062 | ... N5: ='Country Decoder - Final 2503205'!V37 -> 0.83729573 | O5: ='Country Decoder - Final 2503205'!X3 -> 106.74562 | P5: ='Country Decoder - Final 2503205'!Y3 -> 0.034670708 | Q5: ='Country Decoder - Final 2503205'!Z3 -> 12134748 | S5: {=TRANSPOSE(D4:Q4)} -> Country
C6: ='Country Decoder - Final 2503205'!K38 -> Tier 1 | D6: ='Country Decoder - Final 2503205'!L38 -> USA | E6: ='Country Decoder - Final 2503205'!M38 -> 0.99799751 | F6: ='Country Decoder - Final 2503205'!N38 -> 0.24788984 | G6: ='Country Decoder - Final 2503205'!O38 -> 0.73717013 | H6: ='Country Decoder - Final 2503205'!P38 -> 0.69988112 | I6: ='Country Decoder - Final 2503205'!Q38 -> 0.99070243 | J6: ='Country Decoder - Final 2503205'!R38 -> 0.98552341 | ... N6: ='Country Decoder - Final 2503205'!V38 -> 0.2975989 | O6: ='Country Decoder - Final 2503205'!X4 -> 223.84196 | P6: ='Country Decoder - Final 2503205'!Y4 -> 0.072703305 | Q6: ='Country Decoder - Final 2503205'!Z4 -> 25446157 | S6: Spends Per Trip Index
C7: ='Country Decoder - Final 2503205'!K39 -> Tier 1 | D7: ='Country Decoder - Final 2503205'!L39 -> UK | E7: ='Country Decoder - Final 2503205'!M39 -> 0.83535601 | F7: ='Country Decoder - Final 2503205'!N39 -> 0.87519382 | G7: ='Country Decoder - Final 2503205'!O39 -> 0.62715562 | H7: ='Country Decoder - Final 2503205'!P39 -> 0.75761731 | I7: ='Country Decoder - Final 2503205'!Q39 -> 0.78944125 | J7: ='Country Decoder - Final 2503205'!R39 -> 0.89414785 | ... N7: ='Country Decoder - Final 2503205'!V39 -> 0.37317589 | O7: ='Country Decoder - Final 2503205'!X5 -> 220.45948 | P7: ='Country Decoder - Final 2503205'!Y5 -> 0.071604685 | Q7: ='Country Decoder - Final 2503205'!Z5 -> 25061640 | S7: Tourist Departures / Population Index
C8: ='Country Decoder - Final 2503205'!K40 -> Tier 1 | D8: ='Country Decoder - Final 2503205'!L40 -> Germany | E8: ='Country Decoder - Final 2503205'!M40 -> 0.59926381 | F8: ='Country Decoder - Final 2503205'!N40 -> 0.79737301 | G8: ='Country Decoder - Final 2503205'!O40 -> 0.51790353 | H8: ='Country Decoder - Final 2503205'!P40 -> 0.48025662 | I8: ='Country Decoder - Final 2503205'!Q40 -> 0.88481923 | J8: ='Country Decoder - Final 2503205'!R40 -> 0.69171174 | ... N8: ='Country Decoder - Final 2503205'!V40 -> 0.33705654 | O8: ='Country Decoder - Final 2503205'!X6 -> 211.90058 | P8: ='Country Decoder - Final 2503205'!Y6 -> 0.068824776 | Q8: ='Country Decoder - Final 2503205'!Z6 -> 24088672 | S8: Search Volume - 'Flight to Abu Dhabi' Index
C9: ='Country Decoder - Final 2503205'!K41 -> Tier 1 | D9: ='Country Decoder - Final 2503205'!L41 -> France | E9: ='Country Decoder - Final 2503205'!M41 -> 0.81174906 | F9: ='Country Decoder - Final 2503205'!N41 -> 0.44213243 | G9: ='Country Decoder - Final 2503205'!O41 -> 0.50093585 | H9: ='Country Decoder - Final 2503205'!P41 -> 0.45508321 | I9: ='Country Decoder - Final 2503205'!Q41 -> 0.76957735 | J9: ='Country Decoder - Final 2503205'!R41 -> 0.62311112 | ... N9: ='Country Decoder - Final 2503205'!V41 -> 0.34197668 | O9: ='Country Decoder - Final 2503205'!X7 -> 210.75121 | P9: ='Country Decoder - Final 2503205'!Y7 -> 0.068451464 | Q9: ='Country Decoder - Final 2503205'!Z7 -> 23958012 | S9: GDP - Growth Index
C10: ='Country Decoder - Final 2503205'!K42 -> Tier 2 | D10: ='Country Decoder - Final 2503205'!L42 -> Egypt | E10: ='Country Decoder - Final 2503205'!M42 -> 0.084653343 | F10: ='Country Decoder - Final 2503205'!N42 -> 0.17240986 | G10: ='Country Decoder - Final 2503205'!O42 -> 0.35330545 | H10: ='Country Decoder - Final 2503205'!P42 -> 0.0074158208 | I10: ='Country Decoder - Final 2503205'!Q42 -> 0.094452751 | J10: ='Country Decoder - Final 2503205'!R42 -> 0.13395493 | ... N10: ='Country Decoder - Final 2503205'!V42 -> 0.32022537 | O10: ='Country Decoder - Final 2503205'!X8 -> 59.364733 | P10: ='Country Decoder - Final 2503205'!Y8 -> 0.019281516 | Q10: ='Country Decoder - Final 2503205'!Z8 -> 6748530.5 | S10: Disposable Personal Income (USD) Index
C11: ='Country Decoder - Final 2503205'!K43 -> Tier 2 | D11: ='Country Decoder - Final 2503205'!L43 -> Khazakstan | E11: ='Country Decoder - Final 2503205'!M43 -> 0.18608978 | F11: ='Country Decoder - Final 2503205'!N43 -> 0.27146645 | G11: ='Country Decoder - Final 2503205'!O43 -> 0.33874554 | H11: ='Country Decoder - Final 2503205'!P43 -> 0.76888002 | I11: ='Country Decoder - Final 2503205'!Q43 -> 0.20013563 | J11: ='Country Decoder - Final 2503205'!R43 -> 0.10428167 | ... N11: ='Country Decoder - Final 2503205'!V43 -> 0.35493671 | O11: ='Country Decoder - Final 2503205'!X9 -> 66.696784 | P11: ='Country Decoder - Final 2503205'!Y9 -> 0.021662948 | Q11: ='Country Decoder - Final 2503205'!Z9 -> 7582031.7 | S11: Media Cost Index
C12: ='Country Decoder - Final 2503205'!K44 -> Tier 2 | D12: ='Country Decoder - Final 2503205'!L44 -> Bahrain | E12: ='Country Decoder - Final 2503205'!M44 -> 0.55223733 | F12: ='Country Decoder - Final 2503205'!N44 -> 0.81914765 | G12: ='Country Decoder - Final 2503205'!O44 -> 0.34427731 | H12: ='Country Decoder - Final 2503205'!P44 -> 0.48375383 | I12: ='Country Decoder - Final 2503205'!Q44 -> 0.56884944 | J12: ='Country Decoder - Final 2503205'!R44 -> 0.25495495 | ... N12: ='Country Decoder - Final 2503205'!V44 -> 0.99037523 | O12: ='Country Decoder - Final 2503205'!X10 -> 54.617531 | P12: ='Country Decoder - Final 2503205'!Y10 -> 0.017739637 | Q12: ='Country Decoder - Final 2503205'!Z10 -> 6208872.8 | S12: Global Explorers (Audience M) Index
C13: ='Country Decoder - Final 2503205'!K45 -> Tier 2 | D13: ='Country Decoder - Final 2503205'!L45 -> Qatar | E13: ='Country Decoder - Final 2503205'!M45 -> 0.53642212 | F13: ='Country Decoder - Final 2503205'!N45 -> 0.81725772 | G13: ='Country Decoder - Final 2503205'!O45 -> 0.34833716 | H13: ='Country Decoder - Final 2503205'!P45 -> 0.37600336 | I13: ='Country Decoder - Final 2503205'!Q45 -> 0.36118023 | J13: ='Country Decoder - Final 2503205'!R45 -> 0.40226976 | ... N13: ='Country Decoder - Final 2503205'!V45 -> 0.9993526 | O13: ='Country Decoder - Final 2503205'!X11 -> 65.091672 | P13: ='Country Decoder - Final 2503205'!Y11 -> 0.021141611 | Q13: ='Country Decoder - Final 2503205'!Z11 -> 7399563.9 | S13: Budget Split Index
C14: ='Country Decoder - Final 2503205'!K46 -> Tier 2 | D14: ='Country Decoder - Final 2503205'!L46 -> Canada | E14: ='Country Decoder - Final 2503205'!M46 -> 0.52428772 | F14: ='Country Decoder - Final 2503205'!N46 -> 0.59041571 | G14: ='Country Decoder - Final 2503205'!O46 -> 0.41025373 | H14: ='Country Decoder - Final 2503205'!P46 -> 0.27558156 | I14: ='Country Decoder - Final 2503205'!Q46 -> 0.78004355 | J14: ='Country Decoder - Final 2503205'!R46 -> 0.85584734 | ... N14: ='Country Decoder - Final 2503205'!V46 -> 0.30055854 | O14: ='Country Decoder - Final 2503205'!X12 -> 80.443355 | P14: ='Country Decoder - Final 2503205'!Y12 -> 0.026127799 | Q14: ='Country Decoder - Final 2503205'!Z12 -> 9144729.7 | S14: Market Tiering Index
C15: ='Country Decoder - Final 2503205'!K47 -> Tier 2 | D15: ='Country Decoder - Final 2503205'!L47 -> Romania | E15: ='Country Decoder - Final 2503205'!M47 -> 0.20988415 | F15: ='Country Decoder - Final 2503205'!N47 -> 0.79546914 | G15: ='Country Decoder - Final 2503205'!O47 -> 0.36559305 | H15: ='Country Decoder - Final 2503205'!P47 -> 0.43036255 | I15: ='Country Decoder - Final 2503205'!Q47 -> 0.16510313 | J15: ='Country Decoder - Final 2503205'!R47 -> 0.15970743 | ... N15: ='Country Decoder - Final 2503205'!V47 -> 0.35978484 | O15: ='Country Decoder - Final 2503205'!X13 -> 67.726059 | P15: ='Country Decoder - Final 2503205'!Y13 -> 0.021997253 | Q15: ='Country Decoder - Final 2503205'!Z13 -> 7699038.7 | S15: Audience Ratio vs. Total Population Index
C16: ='Country Decoder - Final 2503205'!K48 -> Tier 2 | D16: ='Country Decoder - Final 2503205'!L48 -> Oman | E16: ='Country Decoder - Final 2503205'!M48 -> 0.13262743 | F16: ='Country Decoder - Final 2503205'!N48 -> 0.89594508 | G16: ='Country Decoder - Final 2503205'!O48 -> 0.34648481 | H16: ='Country Decoder - Final 2503205'!P48 -> 0.16828105 | I16: ='Country Decoder - Final 2503205'!Q48 -> 0.34592061 | J16: ='Country Decoder - Final 2503205'!R48 -> 0.18850108 | ... N16: ='Country Decoder - Final 2503205'!V48 -> 0.38651521 | O16: ='Country Decoder - Final 2503205'!X14 -> 57.374399 | P16: ='Country Decoder - Final 2503205'!Y14 -> 0.01863506 | Q16: ='Country Decoder - Final 2503205'!Z14 -> 6522271.1 | S16: Weighted Score
C17: ='Country Decoder - Final 2503205'!K49 -> Tier 2 | D17: ='Country Decoder - Final 2503205'!L49 -> Spain | E17: ='Country Decoder - Final 2503205'!M49 -> 0.44343002 | F17: ='Country Decoder - Final 2503205'!N49 -> 0.24049568 | G17: ='Country Decoder - Final 2503205'!O49 -> 0.41429022 | H17: ='Country Decoder - Final 2503205'!P49 -> 0.69528076 | I17: ='Country Decoder - Final 2503205'!Q49 -> 0.69154698 | J17: ='Country Decoder - Final 2503205'!R49 -> 0.55037778 | ... N17: ='Country Decoder - Final 2503205'!V49 -> 0.29897301 | O17: ='Country Decoder - Final 2503205'!X15 -> 73.745254 | P17: ='Country Decoder - Final 2503205'!Y15 -> 0.023952273 | Q17: ='Country Decoder - Final 2503205'!Z15 -> 8383295.5 | S17: % Split
C18: ='Country Decoder - Final 2503205'!K50 -> Tier 2 | D18: ='Country Decoder - Final 2503205'!L50 -> Netherlands | E18: ='Country Decoder - Final 2503205'!M50 -> 0.78710832 | F18: ='Country Decoder - Final 2503205'!N50 -> 0.82838464 | G18: ='Country Decoder - Final 2503205'!O50 -> 0.38885122 | H18: ='Country Decoder - Final 2503205'!P50 -> 0.63278583 | I18: ='Country Decoder - Final 2503205'!Q50 -> 0.86298736 | J18: ='Country Decoder - Final 2503205'!R50 -> 0.65116975 | ... N18: ='Country Decoder - Final 2503205'!V50 -> 0.44920696 | O18: ='Country Decoder - Final 2503205'!X16 -> 78.538496 | P18: ='Country Decoder - Final 2503205'!Y16 -> 0.025509106 | Q18: ='Country Decoder - Final 2503205'!Z16 -> 8928187 | S18: Budget Split
C19: ='Country Decoder - Final 2503205'!K51 -> Tier 2 | D19: ='Country Decoder - Final 2503205'!L51 -> Japan | E19: ='Country Decoder - Final 2503205'!M51 -> 0.87257091 | F19: ='Country Decoder - Final 2503205'!N51 -> 0.08220548 | G19: ='Country Decoder - Final 2503205'!O51 -> 0.34612657 | H19: ='Country Decoder - Final 2503205'!P51 -> 0.65715307 | I19: ='Country Decoder - Final 2503205'!Q51 -> 0.61937017 | J19: ='Country Decoder - Final 2503205'!R51 -> 0.80915876 | ... N19: ='Country Decoder - Final 2503205'!V51 -> 0.25668985 | O19: ='Country Decoder - Final 2503205'!X17 -> 80.714099 | P19: ='Country Decoder - Final 2503205'!Y17 -> 0.026215736 | Q19: ='Country Decoder - Final 2503205'!Z17 -> 9175507.6
C20: ='Country Decoder - Final 2503205'!K52 -> Tier 2 | D20: ='Country Decoder - Final 2503205'!L52 -> Uzbekistan | E20: ='Country Decoder - Final 2503205'!M52 -> 0.49423737 | F20: ='Country Decoder - Final 2503205'!N52 -> 0.10484606 | G20: ='Country Decoder - Final 2503205'!O52 -> 0.33856504 | H20: ='Country Decoder - Final 2503205'!P52 -> 0.99752161 | I20: ='Country Decoder - Final 2503205'!Q52 -> 0.090672795 | J20: ='Country Decoder - Final 2503205'!R52 -> 0.069172666 | ... N20: ='Country Decoder - Final 2503205'!V52 -> 0.29871976 | O20: ='Country Decoder - Final 2503205'!X18 -> 65.584656 | P20: ='Country Decoder - Final 2503205'!Y18 -> 0.021301731 | Q20: ='Country Decoder - Final 2503205'!Z18 -> 7455605.9
C21: ='Country Decoder - Final 2503205'!K53 -> Tier 2 | D21: ='Country Decoder - Final 2503205'!L53 -> Poland | E21: ='Country Decoder - Final 2503205'!M53 -> 0.26235704 | F21: ='Country Decoder - Final 2503205'!N53 -> 0.84613678 | G21: ='Country Decoder - Final 2503205'!O53 -> 0.41402202 | H21: ='Country Decoder - Final 2503205'!P53 -> 0.88980672 | I21: ='Country Decoder - Final 2503205'!Q53 -> 0.20754378 | J21: ='Country Decoder - Final 2503205'!R53 -> 0.26711273 | ... N21: ='Country Decoder - Final 2503205'!V53 -> 0.4157675 | O21: ='Country Decoder - Final 2503205'!X19 -> 64.776156 | P21: ='Country Decoder - Final 2503205'!Y19 -> 0.021039132 | Q21: ='Country Decoder - Final 2503205'!Z19 -> 7363696.3
C22: ='Country Decoder - Final 2503205'!K54 -> Tier 2 | D22: ='Country Decoder - Final 2503205'!L54 -> South Korea | E22: ='Country Decoder - Final 2503205'!M54 -> 0.51642302 | F22: ='Country Decoder - Final 2503205'!N54 -> 0.29247389 | G22: ='Country Decoder - Final 2503205'!O54 -> 0.33774456 | H22: ='Country Decoder - Final 2503205'!P54 -> 0.089171252 | I22: ='Country Decoder - Final 2503205'!Q54 -> 0.79218182 | J22: ='Country Decoder - Final 2503205'!R54 -> 0.75419625 | ... N22: ='Country Decoder - Final 2503205'!V54 -> 0.25469926 | O22: ='Country Decoder - Final 2503205'!X20 -> 77.624376 | P22: ='Country Decoder - Final 2503205'!Y20 -> 0.025212202 | Q22: ='Country Decoder - Final 2503205'!Z20 -> 8824270.7
C23: ='Country Decoder - Final 2503205'!K55 -> Tier 2 | D23: ='Country Decoder - Final 2503205'!L55 -> Armenia | E23: ='Country Decoder - Final 2503205'!M55 -> 0.18255955 | F23: ='Country Decoder - Final 2503205'!N55 -> 0.38599079 | G23: ='Country Decoder - Final 2503205'!O55 -> 0.34433419 | H23: ='Country Decoder - Final 2503205'!P55 -> 0.56454111 | I23: ='Country Decoder - Final 2503205'!Q55 -> 0.099617206 | J23: ='Country Decoder - Final 2503205'!R55 -> 0.10428167 | ... N23: ='Country Decoder - Final 2503205'!V55 -> 0.43380111 | O23: ='Country Decoder - Final 2503205'!X21 -> 62.828597 | P23: ='Country Decoder - Final 2503205'!Y21 -> 0.02040657 | Q23: ='Country Decoder - Final 2503205'!Z21 -> 7142299.5
C24: ='Country Decoder - Final 2503205'!K56 -> Tier 2 | D24: ='Country Decoder - Final 2503205'!L56 -> Belgium | E24: ='Country Decoder - Final 2503205'!M56 -> 0.91951349 | F24: ='Country Decoder - Final 2503205'!N56 -> 0.80309592 | G24: ='Country Decoder - Final 2503205'!O56 -> 0.36407668 | H24: ='Country Decoder - Final 2503205'!P56 -> 0.64060253 | I24: ='Country Decoder - Final 2503205'!Q56 -> 0.81184582 | J24: ='Country Decoder - Final 2503205'!R56 -> 0.55037778 | ... N24: ='Country Decoder - Final 2503205'!V56 -> 0.39104041 | O24: ='Country Decoder - Final 2503205'!X22 -> 76.550766 | P24: ='Country Decoder - Final 2503205'!Y22 -> 0.024863496 | Q24: ='Country Decoder - Final 2503205'!Z22 -> 8702223.6
C25: ='Country Decoder - Final 2503205'!K57 -> Tier 1 | D25: ='Country Decoder - Final 2503205'!L57 -> Italy | E25: ='Country Decoder - Final 2503205'!M57 -> 0.69000436 | F25: ='Country Decoder - Final 2503205'!N57 -> 0.70529329 | G25: ='Country Decoder - Final 2503205'!O57 -> 0.4792406 | H25: ='Country Decoder - Final 2503205'!P57 -> 0.5025292 | I25: ='Country Decoder - Final 2503205'!Q57 -> 0.76389628 | J25: ='Country Decoder - Final 2503205'!R57 -> 0.69171174 | ... N25: ='Country Decoder - Final 2503205'!V57 -> 0.27758318 | O25: ='Country Decoder - Final 2503205'!X23 -> 210.60139 | P25: ='Country Decoder - Final 2503205'!Y23 -> 0.068402801 | Q25: ='Country Decoder - Final 2503205'!Z23 -> 23940980
C26: ='Country Decoder - Final 2503205'!K58 -> Tier 1 | D26: ='Country Decoder - Final 2503205'!L58 -> China | E26: ='Country Decoder - Final 2503205'!M58 -> 0.079733292 | F26: ='Country Decoder - Final 2503205'!N58 -> 0.065278592 | G26: ='Country Decoder - Final 2503205'!O58 -> 0.33451066 | H26: ='Country Decoder - Final 2503205'!P58 -> 0.54233301 | I26: ='Country Decoder - Final 2503205'!Q58 -> 0.13886032 | J26: ='Country Decoder - Final 2503205'!R58 -> 0.97709161 | ... N26: ='Country Decoder - Final 2503205'!V58 -> 0.29959349 | O26: ='Country Decoder - Final 2503205'!X24 -> 211.99148 | P26: ='Country Decoder - Final 2503205'!Y24 -> 0.068854299 | Q26: ='Country Decoder - Final 2503205'!Z24 -> 24099005
C27: ='Country Decoder - Final 2503205'!K59 -> Tier 1 | D27: ='Country Decoder - Final 2503205'!L59 -> Saudi Arabia | E27: ='Country Decoder - Final 2503205'!M59 -> 0.18744418 | F27: ='Country Decoder - Final 2503205'!N59 -> 0.42223463 | G27: ='Country Decoder - Final 2503205'!O59 -> 0.37443386 | H27: ='Country Decoder - Final 2503205'!P59 -> 0.31730084 | I27: ='Country Decoder - Final 2503205'!Q59 -> 0.21012055 | J27: ='Country Decoder - Final 2503205'!R59 -> 0.55037778 | ... N27: ='Country Decoder - Final 2503205'!V59 -> 0.61507582 | O27: ='Country Decoder - Final 2503205'!X25 -> 202.2057 | P27: ='Country Decoder - Final 2503205'!Y25 -> 0.065675902 | Q27: ='Country Decoder - Final 2503205'!Z25 -> 22986566
C28: ='Country Decoder - Final 2503205'!K60 -> Tier 1 | D28: ='Country Decoder - Final 2503205'!L60 -> Russia | E28: ='Country Decoder - Final 2503205'!M60 -> 0.17099309 | F28: ='Country Decoder - Final 2503205'!N60 -> 0.14348054 | G28: ='Country Decoder - Final 2503205'!O60 -> 0.49999989 | H28: ='Country Decoder - Final 2503205'!P60 -> 0.099706298 | I28: ='Country Decoder - Final 2503205'!Q60 -> 0.18971438 | J28: ='Country Decoder - Final 2503205'!R60 -> 0.18850108 | ... N28: ='Country Decoder - Final 2503205'!V60 -> 0.30138207 | O28: ='Country Decoder - Final 2503205'!X26 -> 193.9838 | P28: ='Country Decoder - Final 2503205'!Y26 -> 0.063005449 | Q28: ='Country Decoder - Final 2503205'!Z26 -> 22051907
C29: ='Country Decoder - Final 2503205'!K61 -> Tier 1 | D29: ='Country Decoder - Final 2503205'!L61 -> Kuwait | E29: ='Country Decoder - Final 2503205'!M61 -> 0.27317375 | F29: ='Country Decoder - Final 2503205'!N61 -> 0.3857894 | G29: ='Country Decoder - Final 2503205'!O61 -> 0.35165326 | H29: ='Country Decoder - Final 2503205'!P61 -> 0.11908674 | I29: ='Country Decoder - Final 2503205'!Q61 -> 0.5847747 | J29: ='Country Decoder - Final 2503205'!R61 -> 0.3595342 | ... N29: ='Country Decoder - Final 2503205'!V61 -> 0.97656992 | O29: ='Country Decoder - Final 2503205'!X27 -> 55.155708 | P29: ='Country Decoder - Final 2503205'!Y27 -> 0.017914435 | Q29: ='Country Decoder - Final 2503205'!Z27 -> 6270052.3
C30: ='Country Decoder - Final 2503205'!K62 -> Tier 1 | D30: ='Country Decoder - Final 2503205'!L62 -> India | E30: ='Country Decoder - Final 2503205'!M62 -> 0.37966311 | F30: ='Country Decoder - Final 2503205'!N62 -> 0.043909558 | G30: ='Country Decoder - Final 2503205'!O62 -> 0.78123905 | H30: ='Country Decoder - Final 2503205'!P62 -> 0.85869161 | I30: ='Country Decoder - Final 2503205'!Q62 -> 0.099355811 | J30: ='Country Decoder - Final 2503205'!R62 -> 0.15970743 | ... N30: ='Country Decoder - Final 2503205'!V62 -> 0.36651803 | O30: ='Country Decoder - Final 2503205'!X28 -> 199.52774 | P30: ='Country Decoder - Final 2503205'!Y28 -> 0.064806106 | Q30: ='Country Decoder - Final 2503205'!Z28 -> 22682137
D34: =_xlfn.CONCAT("Bubble Chart: ",D38," x ",E38," (Size: ",F38,")") -> Bubble Chart: Media Cost Index x Weighted Score (Size: Budget Split)
D36: Col A | E36: Col B | F36: Col C
D37: x-axis | E37: y-axis | F37: size
C38: Country | D38: Media Cost Index | E38: Weighted Score | F38: Budget Split
C39: =D5 -> UAE | D39: {=_xlfn._xlws.FILTER($D$5:$Q$30,$D$4:$Q$4=D38)} -> 0.73004062 | E39: {=_xlfn._xlws.FILTER($D$5:$Q$30,$D$4:$Q$4=E38)} -> 106.74562 | F39: {=_xlfn._xlws.FILTER($D$5:$Q$30,$D$4:$Q$4=F38)} -> 12134748
C40: =D6 -> USA | D40: 0.98552341 | E40: 223.84196 | F40: 25446157
C41: =D7 -> UK | D41: 0.89414785 | E41: 220.45948 | F41: 25061640
C42: =D8 -> Germany | D42: 0.69171174 | E42: 211.90058 | F42: 24088672
C43: =D9 -> France | D43: 0.62311112 | E43: 210.75121 | F43: 23958012
C44: =D10 -> Egypt | D44: 0.13395493 | E44: 59.364733 | F44: 6748530.5
C45: =D11 -> Khazakstan | D45: 0.10428167 | E45: 66.696784 | F45: 7582031.7
C46: =D12 -> Bahrain | D46: 0.25495495 | E46: 54.617531 | F46: 6208872.8
C47: =D13 -> Qatar | D47: 0.40226976 | E47: 65.091672 | F47: 7399563.9
C48: =D14 -> Canada | D48: 0.85584734 | E48: 80.443355 | F48: 9144729.7
C49: =D15 -> Romania | D49: 0.15970743 | E49: 67.726059 | F49: 7699038.7
C50: =D16 -> Oman | D50: 0.18850108 | E50: 57.374399 | F50: 6522271.1
C51: =D17 -> Spain | D51: 0.55037778 | E51: 73.745254 | F51: 8383295.5
... C64: =D30 -> India | D64: 0.15970743 | E64: 199.52774 | F64: 22682137

Sheet Country Decoder - All Factors
V1: Outputs | W1: % | X1: 23760000
B2: Country | C2: =Trips!B1 -> Trips(000s) | D2: =Spend!B1 -> Spend(m-euro) | E2: ='Tourist Departures'!B1 -> Tourist Departures | F2: ='Minimum Wage'!B1 -> Hourly Minimum Wage | G2: =NoofMillionaires!B1 -> NoofMillionaires | H2: ='Inflation Rate'!B1 -> Inflation Rate | I2: =Population!B1 -> Population(m) | J2: ='Search Volume'!B2 -> SV -Abu Dhabi | K2: ='Search Volume'!C2 -> SV - Flights to Abu Dhabi | L2: ='Search Volume'!D2 -> 23SV -Abu Dhabi | M2: ='Search Volume'!E2 -> 23SV - Flights to Abu Dhabi | N2: ='Search Volume'!#REF! -> #REF! | O2: ='GDP Per Capita'!B1 -> GDP Per Capita | P2: =StandardofLiving!B1 -> HDI | Q2: =MAS!B1 -> Median Annual Salary (USD) | R2: =GDP!C1 -> GDP - 2025 | S2: =GDP!D1 -> GDP - Growth | T2: =DPI!B1 -> Disposable Personal Income (USD) | U2: ='Cost of Media'!B1 -> Media Cost | V2: Weighted Score | X2: Budget Split
B3: UAE | C3: =VLOOKUP(B3,Trips!$A$1:$B$27,2,FALSE) -> 0 | D3: =VLOOKUP(B3,Spend!$A$1:$B$27,2,FALSE) -> #N/A | E3: =VLOOKUP(B3,'Tourist Departures'!$A$1:$B$27,2,FALSE) -> 18906000 | F3: =VLOOKUP(B3,'Minimum Wage'!$A$1:$B$27,2,FALSE) -> 6 | G3: =VLOOKUP(B3,NoofMillionaires!$A$1:$B$27,2,FALSE) -> 116500 | H3: =VLOOKUP(B3,'Inflation Rate'!$A$1:$B$27,2,FALSE) -> 0.026 | I3: =VLOOKUP(B3,Population!$A$1:$B$27,2,FALSE) -> 11350000 | J3: =VLOOKUP(B3,'Search Volume'!$A$2:$C$28,2,FALSE) -> 18791890 | K3: =VLOOKUP(B3,'Search Volume'!$A$2:$C$28,3,FALSE) -> 69430 | L3: =VLOOKUP(B3,'Search Volume'!$A$2:$E$28,4,FALSE) -> 9975490 | M3: =VLOOKUP(B3,'Search Volume'!$A$2:$E$28,5,FALSE) -> 85740 | N3: =VLOOKUP(B3,'Search Volume'!$A$2:$C$14,6,FALSE) -> #REF! | O3: =VLOOKUP(B3,'GDP Per Capita'!$A$1:$B$27,2,FALSE) -> 49377.564 | P3: =VLOOKUP(B3,StandardofLiving!$A$1:$B$27,2,FALSE) -> 0.94 | Q3: =VLOOKUP(B3,MAS!$A$1:$B$27,2,FALSE) -> 22037 | R3: =VLOOKUP(B3,GDP!$A$2:$D$28,3,FALSE) -> 548.598 | S3: =VLOOKUP(B3,GDP!$A$2:$D$28,4,FALSE) -> 0.021447497 | T3: =VLOOKUP(B3,DPI!$A$1:$B$27,2,FALSE) -> 36020 | U3: =VLOOKUP(B3,'Cost of Media'!$A$1:$B$27,2,FALSE) -> #N/A | V3: 17.325899 | W3: =V3/SUM($V$4:$V$27) -> 0.054768484 | X3: =W3*$X$1 -> 1301299.2
B4: USA | C4: =VLOOKUP(B4,Trips!$A$1:$B$27,2,FALSE) -> 704.9 | D4: =VLOOKUP(B4,Spend!$A$1:$B$27,2,FALSE) -> #N/A | E4: =VLOOKUP(B4,'Tourist Departures'!$A$1:$B$27,2,FALSE) -> 1.7093009e+08 | F4: =VLOOKUP(B4,'Minimum Wage'!$A$1:$B$27,2,FALSE) -> 7.25 | G4: =VLOOKUP(B4,NoofMillionaires!$A$1:$B$27,2,FALSE) -> 24480000 | H4: =VLOOKUP(B4,'Inflation Rate'!$A$1:$B$27,2,FALSE) -> 0.031 | I4: =VLOOKUP(B4,Population!$A$1:$B$27,2,FALSE) -> 347402264 | J4: =VLOOKUP(B4,'Search Volume'!$A$2:$C$28,2,FALSE) -> 3036780 | K4: =VLOOKUP(B4,'Search Volume'!$A$2:$C$28,3,FALSE) -> 70340 | L4: =VLOOKUP(B4,'Search Volume'!$A$2:$E$28,4,FALSE) -> 2947460 | M4: =VLOOKUP(B4,'Search Volume'!$A$2:$E$28,5,FALSE) -> 48810 | N4: =VLOOKUP(B4,'Search Volume'!$A$2:$C$14,6,FALSE) -> #REF! | O4: =VLOOKUP(B4,'GDP Per Capita'!$A$1:$B$27,2,FALSE) -> 85809.9 | P4: =VLOOKUP(B4,StandardofLiving!$A$1:$B$27,2,FALSE) -> 0.938 | Q4: =VLOOKUP(B4,MAS!$A$1:$B$27,2,FALSE) -> 67468 | R4: =VLOOKUP(B4,GDP!$A$2:$D$28,3,FALSE) -> 30507 | S4: =VLOOKUP(B4,GDP!$A$2:$D$28,4,FALSE) -> 0.045333059 | T4: =VLOOKUP(B4,DPI!$A$1:$B$27,2,FALSE) -> 60944 | U4: =VLOOKUP(B4,'Cost of Media'!$A$1:$B$27,2,FALSE) -> #N/A | V4: 18.325899 | W4: =V4/SUM($V$4:$V$27) -> 0.05792956 | X4: =W4*$X$1 -> 1376406.3
A5: Great Britain | B5: UK | C5: =VLOOKUP(B5,Trips!$A$1:$B$27,2,FALSE) -> 1245.1 | D5: =VLOOKUP(B5,Spend!$A$1:$B$27,2,FALSE) -> #N/A | E5: =VLOOKUP(B5,'Tourist Departures'!$A$1:$B$27,2,FALSE) -> 93086000 | F5: =VLOOKUP(B5,'Minimum Wage'!$A$1:$B$27,2,FALSE) -> 14.3 | G5: =VLOOKUP(B5,NoofMillionaires!$A$1:$B$27,2,FALSE) -> 2849000 | H5: =VLOOKUP(B5,'Inflation Rate'!$A$1:$B$27,2,FALSE) -> 0.029 | I5: =VLOOKUP(B5,Population!$A$1:$B$27,2,FALSE) -> 69579448 | J5: =VLOOKUP(B5,'Search Volume'!$A$2:$C$28,2,FALSE) -> 2248410 | K5: =VLOOKUP(B5,'Search Volume'!$A$2:$C$28,3,FALSE) -> 169080 | L5: =VLOOKUP(B5,'Search Volume'!$A$2:$E$28,4,FALSE) -> 1782130 | M5: =VLOOKUP(B5,'Search Volume'!$A$2:$E$28,5,FALSE) -> 136400 | N5: =VLOOKUP(B5,'Search Volume'!$A$2:$C$14,6,FALSE) -> #REF! | O5: =VLOOKUP(B5,'GDP Per Capita'!$A$1:$B$27,2,FALSE) -> 52636.787 | P5: =VLOOKUP(B5,StandardofLiving!$A$1:$B$27,2,FALSE) -> 0.946 | Q5: =VLOOKUP(B5,MAS!$A$1:$B$27,2,FALSE) -> 45486 | R5: =VLOOKUP(B5,GDP!$A$2:$D$28,3,FALSE) -> 3839 | S5: =VLOOKUP(B5,GDP!$A$2:$D$28,4,FALSE) -> 0.053512623 | T5: =VLOOKUP(B5,DPI!$A$1:$B$27,2,FALSE) -> 36077 | U5: =VLOOKUP(B5,'Cost of Media'!$A$1:$B$27,2,FALSE) -> #N/A | V5: 16.61223 | W5: =V5/SUM($V$4:$V$27) -> 0.052512523 | X5: =W5*$X$1 -> 1247697.6
B6: Germany | C6: =VLOOKUP(B6,Trips!$A$1:$B$27,2,FALSE) -> 504.2 | D6: =VLOOKUP(B6,Spend!$A$1:$B$27,2,FALSE) -> 430 | E6: =VLOOKUP(B6,'Tourist Departures'!$A$1:$B$27,2,FALSE) -> 99533000 | F6: =VLOOKUP(B6,'Minimum Wage'!$A$1:$B$27,2,FALSE) -> 13.85 | G6: =VLOOKUP(B6,NoofMillionaires!$A$1:$B$27,2,FALSE) -> 2683000 | H6: =VLOOKUP(B6,'Inflation Rate'!$A$1:$B$27,2,FALSE) -> 0.026 | I6: =VLOOKUP(B6,Population!$A$1:$B$27,2,FALSE) -> 83600000 | J6: =VLOOKUP(B6,'Search Volume'!$A$2:$C$28,2,FALSE) -> 1384090 | K6: =VLOOKUP(B6,'Search Volume'!$A$2:$C$28,3,FALSE) -> 5530 | L6: =VLOOKUP(B6,'Search Volume'!$A$2:$E$28,4,FALSE) -> 1351080 | M6: =VLOOKUP(B6,'Search Volume'!$A$2:$E$28,5,FALSE) -> 3820 | N6: =VLOOKUP(B6,'Search Volume'!$A$2:$C$14,6,FALSE) -> #REF! | O6: =VLOOKUP(B6,'GDP Per Capita'!$A$1:$B$27,2,FALSE) -> 55800.219 | P6: =VLOOKUP(B6,StandardofLiving!$A$1:$B$27,2,FALSE) -> 0.959 | Q6: =VLOOKUP(B6,MAS!$A$1:$B$27,2,FALSE) -> 55055 | R6: =VLOOKUP(B6,GDP!$A$2:$D$28,3,FALSE) -> 4744 | S6: =VLOOKUP(B6,GDP!$A$2:$D$28,4,FALSE) -> 0.01846286 | T6: =VLOOKUP(B6,DPI!$A$1:$B$27,2,FALSE) -> 42417 | U6: =VLOOKUP(B6,'Cost of Media'!$A$1:$B$27,2,FALSE) -> #N/A | V6: 12.163844 | W6: =V6/SUM($V$4:$V$27) -> 0.038450836 | X6: =W6*$X$1 -> 913591.87
B7: France | C7: =VLOOKUP(B7,Trips!$A$1:$B$27,2,FALSE) -> 433.9 | D7: =VLOOKUP(B7,Spend!$A$1:$B$27,2,FALSE) -> 362 | E7: =VLOOKUP(B7,'Tourist Departures'!$A$1:$B$27,2,FALSE) -> 49276000 | F7: =VLOOKUP(B7,'Minimum Wage'!$A$1:$B$27,2,FALSE) -> 12.96 | G7: =VLOOKUP(B7,NoofMillionaires!$A$1:$B$27,2,FALSE) -> 2796000 | H7: =VLOOKUP(B7,'Inflation Rate'!$A$1:$B$27,2,FALSE) -> 0.028 | I7: =VLOOKUP(B7,Population!$A$1:$B$27,2,FALSE) -> 66658005 | J7: =VLOOKUP(B7,'Search Volume'!$A$2:$C$28,2,FALSE) -> 1319680 | K7: =VLOOKUP(B7,'Search Volume'!$A$2:$C$28,3,FALSE) -> 4240 | L7: =VLOOKUP(B7,'Search Volume'!$A$2:$E$28,4,FALSE) -> 1175450 | M7: =VLOOKUP(B7,'Search Volume'!$A$2:$E$28,5,FALSE) -> 2830 | N7: =VLOOKUP(B7,'Search Volume'!$A$2:$C$14,6,FALSE) -> #REF! | O7: =VLOOKUP(B7,'GDP Per Capita'!$A$1:$B$27,2,FALSE) -> 46150.488 | P7: =VLOOKUP(B7,StandardofLiving!$A$1:$B$27,2,FALSE) -> 0.92 | Q7: =VLOOKUP(B7,MAS!$A$1:$B$27,2,FALSE) -> 48072 | R7: =VLOOKUP(B7,GDP!$A$2:$D$28,3,FALSE) -> 3211 | S7: =VLOOKUP(B7,GDP!$A$2:$D$28,4,FALSE) -> 0.015496521 | T7: =VLOOKUP(B7,DPI!$A$1:$B$27,2,FALSE) -> 35001 | U7: =VLOOKUP(B7,'Cost of Media'!$A$1:$B$27,2,FALSE) -> 0.042772724 | V7: 8.9095183 | W7: =V7/SUM($V$4:$V$27) -> 0.028163665 | X7: =W7*$X$1 -> 669168.69
B8: Egypt | C8: =VLOOKUP(B8,Trips!$A$1:$B$27,2,FALSE) -> 170 | D8: =VLOOKUP(B8,Spend!$A$1:$B$27,2,FALSE) -> #N/A | E8: =VLOOKUP(B8,'Tourist Departures'!$A$1:$B$27,2,FALSE) -> 43066000 | F8: =VLOOKUP(B8,'Minimum Wage'!$A$1:$B$27,2,FALSE) -> 0.73 | G8: =VLOOKUP(B8,NoofMillionaires!$A$1:$B$27,2,FALSE) -> 87000 | H8: =VLOOKUP(B8,'Inflation Rate'!$A$1:$B$27,2,FALSE) -> 0.282 | I8: =VLOOKUP(B8,Population!$A$1:$B$27,2,FALSE) -> 116275465 | J8: =VLOOKUP(B8,'Search Volume'!$A$2:$C$28,2,FALSE) -> 172870 | K8: =VLOOKUP(B8,'Search Volume'!$A$2:$C$28,3,FALSE) -> 14650 | L8: =VLOOKUP(B8,'Search Volume'!$A$2:$E$28,4,FALSE) -> 149110 | M8: =VLOOKUP(B8,'Search Volume'!$A$2:$E$28,5,FALSE) -> 8400 | N8: =VLOOKUP(B8,'Search Volume'!$A$2:$C$14,6,FALSE) -> #REF! | O8: =VLOOKUP(B8,'GDP Per Capita'!$A$1:$B$27,2,FALSE) -> 3338.4737 | P8: =VLOOKUP(B8,StandardofLiving!$A$1:$B$27,2,FALSE) -> 0.754 | Q8: =VLOOKUP(B8,MAS!$A$1:$B$27,2,FALSE) -> 12500 | R8: =VLOOKUP(B8,GDP!$A$2:$D$28,3,FALSE) -> 347.342 | S8: =VLOOKUP(B8,GDP!$A$2:$D$28,4,FALSE) -> -0.093359853 | T8: =VLOOKUP(B8,DPI!$A$1:$B$27,2,FALSE) -> 2072 | U8: =VLOOKUP(B8,'Cost of Media'!$A$1:$B$27,2,FALSE) -> #N/A | V8: 7.4276786 | W8: =V8/SUM($V$4:$V$27) -> 0.023479457 | X8: =W8*$X$1 -> 557871.9
B9: Khazakstan | C9: =VLOOKUP(B9,Trips!$A$1:$B$27,2,FALSE) -> 74 | D9: =VLOOKUP(B9,Spend!$A$1:$B$27,2,FALSE) -> #N/A | E9: =VLOOKUP(B9,'Tourist Departures'!$A$1:$B$27,2,FALSE) -> 10707000 | F9: =VLOOKUP(B9,'Minimum Wage'!$A$1:$B$27,2,FALSE) -> 1.09 | G9: =VLOOKUP(B9,NoofMillionaires!$A$1:$B$27,2,FALSE) -> 44307 | H9: =VLOOKUP(B9,'Inflation Rate'!$A$1:$B$27,2,FALSE) -> 0.087 | I9: =VLOOKUP(B9,Population!$A$1:$B$27,2,FALSE) -> 20370672 | J9: =VLOOKUP(B9,'Search Volume'!$A$2:$C$28,2,FALSE) -> 71900 | K9: =VLOOKUP(B9,'Search Volume'!$A$2:$C$28,3,FALSE) -> 290 | L9: =VLOOKUP(B9,'Search Volume'!$A$2:$E$28,4,FALSE) -> 47810 | M9: =VLOOKUP(B9,'Search Volume'!$A$2:$E$28,5,FALSE) -> 190 | N9: =VLOOKUP(B9,'Search Volume'!$A$2:$C$14,6,FALSE) -> #N/A | O9: =VLOOKUP(B9,'GDP Per Capita'!$A$1:$B$27,2,FALSE) -> 3161.7001 | P9: =VLOOKUP(B9,StandardofLiving!$A$1:$B$27,2,FALSE) -> 0.74 | Q9: =VLOOKUP(B9,MAS!$A$1:$B$27,2,FALSE) -> 13348 | R9: =VLOOKUP(B9,GDP!$A$2:$D$28,3,FALSE) -> 300.538 | S9: =VLOOKUP(B9,GDP!$A$2:$D$28,4,FALSE) -> 0.05522278 | T9: =VLOOKUP(B9,DPI!$A$1:$B$27,2,FALSE) -> 9660 | U9: =VLOOKUP(B9,'Cost of Media'!$A$1:$B$27,2,FALSE) -> 0 | V9: 6.8810569 | W9: =V9/SUM($V$4:$V$27) -> 0.021751544 | X9: =W9*$X$1 -> 516816.69
B10: Bahrain | C10: =VLOOKUP(B10,Trips!$A$1:$B$27,2,FALSE) -> 52.4 | D10: =VLOOKUP(B10,Spend!$A$1:$B$27,2,FALSE) -> #N/A | E10: =VLOOKUP(B10,'Tourist Departures'!$A$1:$B$27,2,FALSE) -> 2950000 | F10: =VLOOKUP(B10,'Minimum Wage'!$A$1:$B$27,2,FALSE) -> 7 | G10: =VLOOKUP(B10,NoofMillionaires!$A$1:$B$27,2,FALSE) -> 25000 | H10: =VLOOKUP(B10,'Inflation Rate'!$A$1:$B$27,2,FALSE) -> 0.021 | I10: =VLOOKUP(B10,Population!$A$1:$B$27,2,FALSE) -> 1588670 | J10: =VLOOKUP(B10,'Search Volume'!$A$2:$C$28,2,FALSE) -> 94410 | K10: =VLOOKUP(B10,'Search Volume'!$A$2:$C$28,3,FALSE) -> 12270 | L10: =VLOOKUP(B10,'Search Volume'!$A$2:$E$28,4,FALSE) -> 87090 | M10: =VLOOKUP(B10,'Search Volume'!$A$2:$E$28,5,FALSE) -> 12260 | N10: =VLOOKUP(B10,'Search Volume'!$A$2:$C$14,6,FALSE) -> #N/A | O10: =VLOOKUP(B10,'GDP Per Capita'!$A$1:$B$27,2,FALSE) -> 30048.218 | P10: =VLOOKUP(B10,StandardofLiving!$A$1:$B$27,2,FALSE) -> 0.899 | Q10: =VLOOKUP(B10,MAS!$A$1:$B$27,2,FALSE) -> 56393 | R10: =VLOOKUP(B10,GDP!$A$2:$D$28,3,FALSE) -> 47.829 | S10: =VLOOKUP(B10,GDP!$A$2:$D$28,4,FALSE) -> 0.018873954 | T10: =VLOOKUP(B10,DPI!$A$1:$B$27,2,FALSE) -> 25947 | U10: =VLOOKUP(B10,'Cost of Media'!$A$1:$B$27,2,FALSE) -> 0 | V10: 9.2950082 | W10: =V10/SUM($V$4:$V$27) -> 0.029382228 | X10: =W10*$X$1 -> 698121.74
B11: Qatar | C11: =VLOOKUP(B11,Trips!$A$1:$B$27,2,FALSE) -> 0 | D11: =VLOOKUP(B11,Spend!$A$1:$B$27,2,FALSE) -> #N/A | E11: =VLOOKUP(B11,'Tourist Departures'!$A$1:$B$27,2,FALSE) -> 3550000 | F11: =VLOOKUP(B11,'Minimum Wage'!$A$1:$B$27,2,FALSE) -> 1.59 | G11: =VLOOKUP(B11,NoofMillionaires!$A$1:$B$27,2,FALSE) -> 36000 | H11: =VLOOKUP(B11,'Inflation Rate'!$A$1:$B$27,2,FALSE) -> 0.024 | I11: =VLOOKUP(B11,Population!$A$1:$B$27,2,FALSE) -> 2757220 | J11: =VLOOKUP(B11,'Search Volume'!$A$2:$C$28,2,FALSE) -> 139980 | K11: =VLOOKUP(B11,'Search Volume'!$A$2:$C$28,3,FALSE) -> 16220 | L11: =VLOOKUP(B11,'Search Volume'!$A$2:$E$28,4,FALSE) -> 98020 | M11: =VLOOKUP(B11,'Search Volume'!$A$2:$E$28,5,FALSE) -> 14480 | N11: =VLOOKUP(B11,'Search Volume'!$A$2:$C$14,6,FALSE) -> #N/A | O11: =VLOOKUP(B11,'GDP Per Capita'!$A$1:$B$27,2,FALSE) -> 76275.908 | P11: =VLOOKUP(B11,StandardofLiving!$A$1:$B$27,2,FALSE) -> 0.886 | Q11: =VLOOKUP(B11,MAS!$A$1:$B$27,2,FALSE) -> 45560 | R11: =VLOOKUP(B11,GDP!$A$2:$D$28,3,FALSE) -> 222.776 | S11: =VLOOKUP(B11,GDP!$A$2:$D$28,4,FALSE) -> 0.0059787223 | T11: =VLOOKUP(B11,DPI!$A$1:$B$27,2,FALSE) -> 17459 | U11: =VLOOKUP(B11,'Cost of Media'!$A$1:$B$27,2,FALSE) -> #N/A | V11: 10.295008 | W11: =V11/SUM($V$4:$V$27) -> 0.032543304 | X11: =W11*$X$1 -> 773228.91
B12: Canada | C12: =VLOOKUP(B12,Trips!$A$1:$B$27,2,FALSE) -> 59 | D12: =VLOOKUP(B12,Spend!$A$1:$B$27,2,FALSE) -> 255 | E12: =VLOOKUP(B12,'Tourist Departures'!$A$1:$B$27,2,FALSE) -> 37845898 | F12: =VLOOKUP(B12,'Minimum Wage'!$A$1:$B$27,2,FALSE) -> 12.63 | G12: =VLOOKUP(B12,NoofMillionaires!$A$1:$B$27,2,FALSE) -> 2291000 | H12: =VLOOKUP(B12,'Inflation Rate'!$A$1:$B$27,2,FALSE) -> 0.029 | I12: =VLOOKUP(B12,Population!$A$1:$B$27,2,FALSE) -> 41500000 | J12: =VLOOKUP(B12,'Search Volume'!$A$2:$C$28,2,FALSE) -> 604940 | K12: =VLOOKUP(B12,'Search Volume'!$A$2:$C$28,3,FALSE) -> 9120 | L12: =VLOOKUP(B12,'Search Volume'!$A$2:$E$28,4,FALSE) -> 575590 | M12: =VLOOKUP(B12,'Search Volume'!$A$2:$E$28,5,FALSE) -> 6950 | N12: =VLOOKUP(B12,'Search Volume'!$A$2:$C$14,6,FALSE) -> #N/A | O12: =VLOOKUP(B12,'GDP Per Capita'!$A$1:$B$27,2,FALSE) -> 54282.618 | P12: =VLOOKUP(B12,StandardofLiving!$A$1:$B$27,2,FALSE) -> 0.939 | Q12: =VLOOKUP(B12,MAS!$A$1:$B$27,2,FALSE) -> 45345 | R12: =VLOOKUP(B12,GDP!$A$2:$D$28,3,FALSE) -> 2225 | S12: =VLOOKUP(B12,GDP!$A$2:$D$28,4,FALSE) -> -0.0071396698 | T12: =VLOOKUP(B12,DPI!$A$1:$B$27,2,FALSE) -> 35561 | U12: =VLOOKUP(B12,'Cost of Media'!$A$1:$B$27,2,FALSE) -> 0.031657955 | V12: 11.295008 | W12: =V12/SUM($V$4:$V$27) -> 0.03570438 | X12: =W12*$X$1 -> 848336.07
B13: Romania | C13: =VLOOKUP(B13,Trips!$A$1:$B$27,2,FALSE) -> 35.1 | D13: =VLOOKUP(B13,Spend!$A$1:$B$27,2,FALSE) -> #N/A | E13: =VLOOKUP(B13,'Tourist Departures'!$A$1:$B$27,2,FALSE) -> 23066000 | F13: =VLOOKUP(B13,'Minimum Wage'!$A$1:$B$27,2,FALSE) -> 4.14 | G13: =VLOOKUP(B13,NoofMillionaires!$A$1:$B$27,2,FALSE) -> 37000 | H13: =VLOOKUP(B13,'Inflation Rate'!$A$1:$B$27,2,FALSE) -> 0.072 | I13: =VLOOKUP(B13,Population!$A$1:$B$27,2,FALSE) -> 19424322 | J13: =VLOOKUP(B13,'Search Volume'!$A$2:$C$28,2,FALSE) -> 286520 | K13: =VLOOKUP(B13,'Search Volume'!$A$2:$C$28,3,FALSE) -> 760 | L13: =VLOOKUP(B13,'Search Volume'!$A$2:$E$28,4,FALSE) -> 244350 | M13: =VLOOKUP(B13,'Search Volume'!$A$2:$E$28,5,FALSE) -> 570 | N13: =VLOOKUP(B13,'Search Volume'!$A$2:$C$14,6,FALSE) -> #N/A | O13: =VLOOKUP(B13,'GDP Per Capita'!$A$1:$B$27,2,FALSE) -> 20072.408 | P13: =VLOOKUP(B13,StandardofLiving!$A$1:$B$27,2,FALSE) -> 0.845 | Q13: =VLOOKUP(B13,MAS!$A$1:$B$27,2,FALSE) -> 16660 | R13: =VLOOKUP(B13,GDP!$A$2:$D$28,3,FALSE) -> 403 | S13: =VLOOKUP(B13,GDP!$A$2:$D$28,4,FALSE) -> 0.012562814 | T13: =VLOOKUP(B13,DPI!$A$1:$B$27,2,FALSE) -> 7532 | U13: =VLOOKUP(B13,'Cost of Media'!$A$1:$B$27,2,FALSE) -> 0 | V13: 12.295008 | W13: =V13/SUM($V$4:$V$27) -> 0.038865456 | X13: =W13*$X$1 -> 923443.24
B14: Oman | C14: =VLOOKUP(B14,Trips!$A$1:$B$27,2,FALSE) -> 1565.8 | D14: =VLOOKUP(B14,Spend!$A$1:$B$27,2,FALSE) -> #N/A | E14: =VLOOKUP(B14,'Tourist Departures'!$A$1:$B$27,2,FALSE) -> 6633000 | F14: =VLOOKUP(B14,'Minimum Wage'!$A$1:$B$27,2,FALSE) -> 4.88 | G14: =VLOOKUP(B14,NoofMillionaires!$A$1:$B$27,2,FALSE) -> 30000 | H14: =VLOOKUP(B14,'Inflation Rate'!$A$1:$B$27,2,FALSE) -> 0.018 | I14: =VLOOKUP(B14,Population!$A$1:$B$27,2,FALSE) -> 4780706 | J14: =VLOOKUP(B14,'Search Volume'!$A$2:$C$28,2,FALSE) -> 139390 | K14: =VLOOKUP(B14,'Search Volume'!$A$2:$C$28,3,FALSE) -> 1260 | L14: =VLOOKUP(B14,'Search Volume'!$A$2:$E$28,4,FALSE) -> 98490 | M14: =VLOOKUP(B14,'Search Volume'!$A$2:$E$28,5,FALSE) -> 1000 | N14: =VLOOKUP(B14,'Search Volume'!$A$2:$C$14,6,FALSE) -> #N/A | O14: =VLOOKUP(B14,'GDP Per Capita'!$A$1:$B$27,2,FALSE) -> 20248.417 | P14: =VLOOKUP(B14,StandardofLiving!$A$1:$B$27,2,FALSE) -> 0.858 | Q14: =VLOOKUP(B14,MAS!$A$1:$B$27,2,FALSE) -> 20470 | R14: =VLOOKUP(B14,GDP!$A$2:$D$28,3,FALSE) -> 104.351 | S14: =VLOOKUP(B14,GDP!$A$2:$D$28,4,FALSE) -> -0.02423721 | T14: =VLOOKUP(B14,DPI!$A$1:$B$27,2,FALSE) -> 16800 | U14: =VLOOKUP(B14,'Cost of Media'!$A$1:$B$27,2,FALSE) -> #N/A | V14: 13.295008 | W14: =V14/SUM($V$4:$V$27) -> 0.042026532 | X14: =W14*$X$1 -> 998550.41
B15: Spain | C15: =VLOOKUP(B15,Trips!$A$1:$B$27,2,FALSE) -> 52.8 | D15: =VLOOKUP(B15,Spend!$A$1:$B$27,2,FALSE) -> 264 | E15: =VLOOKUP(B15,'Tourist Departures'!$A$1:$B$27,2,FALSE) -> 22816000 | F15: =VLOOKUP(B15,'Minimum Wage'!$A$1:$B$27,2,FALSE) -> 8.24 | G15: =VLOOKUP(B15,NoofMillionaires!$A$1:$B$27,2,FALSE) -> 1132000 | H15: =VLOOKUP(B15,'Inflation Rate'!$A$1:$B$27,2,FALSE) -> 0.034 | I15: =VLOOKUP(B15,Population!$A$1:$B$27,2,FALSE) -> 47420024 | J15: =VLOOKUP(B15,'Search Volume'!$A$2:$C$28,2,FALSE) -> 641800 | K15: =VLOOKUP(B15,'Search Volume'!$A$2:$C$28,3,FALSE) -> 2170 | L15: =VLOOKUP(B15,'Search Volume'!$A$2:$E$28,4,FALSE) -> 609940 | M15: =VLOOKUP(B15,'Search Volume'!$A$2:$E$28,5,FALSE) -> 1750 | N15: =VLOOKUP(B15,'Search Volume'!$A$2:$C$14,6,FALSE) -> #N/A | O15: =VLOOKUP(B15,'GDP Per Capita'!$A$1:$B$27,2,FALSE) -> 35297.009 | P15: =VLOOKUP(B15,StandardofLiving!$A$1:$B$27,2,FALSE) -> 0.918 | Q15: =VLOOKUP(B15,MAS!$A$1:$B$27,2,FALSE) -> 39965 | R15: =VLOOKUP(B15,GDP!$A$2:$D$28,3,FALSE) -> 1799 | S15: =VLOOKUP(B15,GDP!$A$2:$D$28,4,FALSE) -> 0.044715447 | T15: =VLOOKUP(B15,DPI!$A$1:$B$27,2,FALSE) -> 31193 | U15: =VLOOKUP(B15,'Cost of Media'!$A$1:$B$27,2,FALSE) -> 0.096328877 | V15: 14.295008 | W15: =V15/SUM($V$4:$V$27) -> 0.045187608 | X15: =W15*$X$1 -> 1073657.6
B16: Netherlands | C16: =VLOOKUP(B16,Trips!$A$1:$B$27,2,FALSE) -> 61.4 | D16: =VLOOKUP(B16,Spend!$A$1:$B$27,2,FALSE) -> 132 | E16: =VLOOKUP(B16,'Tourist Departures'!$A$1:$B$27,2,FALSE) -> 22045000 | F16: =VLOOKUP(B16,'Minimum Wage'!$A$1:$B$27,2,FALSE) -> 12.47 | G16: =VLOOKUP(B16,NoofMillionaires!$A$1:$B$27,2,FALSE) -> 1149000 | H16: =VLOOKUP(B16,'Inflation Rate'!$A$1:$B$27,2,FALSE) -> 0.028 | I16: =VLOOKUP(B16,Population!$A$1:$B$27,2,FALSE) -> 17722333 | J16: =VLOOKUP(B16,'Search Volume'!$A$2:$C$28,2,FALSE) -> 442290 | K16: =VLOOKUP(B16,'Search Volume'!$A$2:$C$28,3,FALSE) -> 4160 | L16: =VLOOKUP(B16,'Search Volume'!$A$2:$E$28,4,FALSE) -> 431370 | M16: =VLOOKUP(B16,'Search Volume'!$A$2:$E$28,5,FALSE) -> 3130 | N16: =VLOOKUP(B16,'Search Volume'!$A$2:$C$14,6,FALSE) -> #N/A | O16: =VLOOKUP(B16,'GDP Per Capita'!$A$1:$B$27,2,FALSE) -> 68218.726 | P16: =VLOOKUP(B16,StandardofLiving!$A$1:$B$27,2,FALSE) -> 0.955 | Q16: =VLOOKUP(B16,MAS!$A$1:$B$27,2,FALSE) -> 50920 | R16: =VLOOKUP(B16,GDP!$A$2:$D$28,3,FALSE) -> 1272 | S16: =VLOOKUP(B16,GDP!$A$2:$D$28,4,FALSE) -> 0.036674817 | T16: =VLOOKUP(B16,DPI!$A$1:$B$27,2,FALSE) -> 40722 | U16: =VLOOKUP(B16,'Cost of Media'!$A$1:$B$27,2,FALSE) -> 0 | V16: 15.295008 | W16: =V16/SUM($V$4:$V$27) -> 0.048348685 | X16: =W16*$X$1 -> 1148764.7
B17: Japan | C17: =VLOOKUP(B17,Trips!$A$1:$B$27,2,FALSE) -> 27 | D17: =VLOOKUP(B17,Spend!$A$1:$B$27,2,FALSE) -> #N/A | E17: =VLOOKUP(B17,'Tourist Departures'!$A$1:$B$27,2,FALSE) -> 20081000 | F17: =VLOOKUP(B17,'Minimum Wage'!$A$1:$B$27,2,FALSE) -> 6.69 | G17: =VLOOKUP(B17,NoofMillionaires!$A$1:$B$27,2,FALSE) -> 3366000 | H17: =VLOOKUP(B17,'Inflation Rate'!$A$1:$B$27,2,FALSE) -> 0.022 | I17: =VLOOKUP(B17,Population!$A$1:$B$27,2,FALSE) -> 121960408 | J17: =VLOOKUP(B17,'Search Volume'!$A$2:$C$28,2,FALSE) -> 161240 | K17: =VLOOKUP(B17,'Search Volume'!$A$2:$C$28,3,FALSE) -> 72490 | L17: =VLOOKUP(B17,'Search Volume'!$A$2:$E$28,4,FALSE) -> 520 | M17: =VLOOKUP(B17,'Search Volume'!$A$2:$E$28,5,FALSE) -> 360 | N17: =VLOOKUP(B17,'Search Volume'!$A$2:$C$14,6,FALSE) -> #N/A | O17: =VLOOKUP(B17,'GDP Per Capita'!$A$1:$B$27,2,FALSE) -> 32475.892 | P17: =VLOOKUP(B17,StandardofLiving!$A$1:$B$27,2,FALSE) -> 0.925 | Q17: =VLOOKUP(B17,MAS!$A$1:$B$27,2,FALSE) -> 38010 | R17: =VLOOKUP(B17,GDP!$A$2:$D$28,3,FALSE) -> 4186 | S17: =VLOOKUP(B17,GDP!$A$2:$D$28,4,FALSE) -> 0.039741679 | T17: =VLOOKUP(B17,DPI!$A$1:$B$27,2,FALSE) -> 28040 | U17: =VLOOKUP(B17,'Cost of Media'!$A$1:$B$27,2,FALSE) -> 0.048190819 | V17: 16.295008 | W17: =V17/SUM($V$4:$V$27) -> 0.051509761 | X17: =W17*$X$1 -> 1223871.9
... B28: India | C28: =VLOOKUP(B28,Trips!$A$1:$B$27,2,FALSE) -> 2200.3 | D28: =VLOOKUP(B28,Spend!$A$1:$B$27,2,FALSE) -> #N/A | E28: =VLOOKUP(B28,'Tourist Departures'!$A$1:$B$27,2,FALSE) -> 26915000 | F28: =VLOOKUP(B28,'Minimum Wage'!$A$1:$B$27,2,FALSE) -> 0.6 | G28: =VLOOKUP(B28,NoofMillionaires!$A$1:$B$27,2,FALSE) -> 796000 | H28: =VLOOKUP(B28,'Inflation Rate'!$A$1:$B$27,2,FALSE) -> 0.046 | I28: =VLOOKUP(B28,Population!$A$1:$B$27,2,FALSE) -> 1454606724 | J28: =VLOOKUP(B28,'Search Volume'!$A$2:$C$28,2,FALSE) -> 3792180 | K28: =VLOOKUP(B28,'Search Volume'!$A$2:$C$28,3,FALSE) -> 206010 | L28: =VLOOKUP(B28,'Search Volume'!$A$2:$E$28,4,FALSE) -> 2800880 | M28: =VLOOKUP(B28,'Search Volume'!$A$2:$E$28,5,FALSE) -> 111580 | N28: =VLOOKUP(B28,'Search Volume'!$A$2:$C$14,6,FALSE) -> #REF! | O28: =VLOOKUP(B28,'GDP Per Capita'!$A$1:$B$27,2,FALSE) -> 2696.6639 | P28: =VLOOKUP(B28,StandardofLiving!$A$1:$B$27,2,FALSE) -> 0.685 | Q28: =VLOOKUP(B28,MAS!$A$1:$B$27,2,FALSE) -> 10475 | R28: =VLOOKUP(B28,GDP!$A$2:$D$28,3,FALSE) -> 4187 | S28: =VLOOKUP(B28,GDP!$A$2:$D$28,4,FALSE) -> 0.071117933 | T28: =VLOOKUP(B28,DPI!$A$1:$B$27,2,FALSE) -> 2531 | U28: =VLOOKUP(B28,'Cost of Media'!$A$1:$B$27,2,FALSE) -> 0.21913073 | V28: 9.1481187 | W28: =V28/SUM($V$4:$V$27) -> 0.028917899 | X28: =W28*$X$1 -> 687089.29
B29: Avg | C29: =AVERAGE(C3:C27) -> 323.332 | D29: =AVERAGE(D3:D27) -> #N/A | E29: =AVERAGE(E3:E27) -> 40824640 | F29: =AVERAGE(F3:F27) -> 6.514 | G29: =AVERAGE(G3:G27) -> 2063952.3 | H29: =AVERAGE(H4:H27) -> 0.046708333 | I29: =AVERAGE(I4:I27) -> 1.1557449e+08 | J29: =AVERAGE(J4:J27) -> 627337 | K29: =AVERAGE(K4:K27) -> 18744.417 | L29: =AVERAGE(L4:L27) -> 544941.75 | M29: =AVERAGE(M4:M27) -> 12169.667 | N29: =AVERAGE(N4:N27) -> #REF! | O29: =AVERAGE(O3:O27) -> 35785.784 | P29: =AVERAGE(P3:P27) -> 0.88252 | Q29: =AVERAGE(Q3:Q27) -> 32949.24 | R29: =AVERAGE(R3:R27) -> 3293.601 | S29: =AVERAGE(S4:S27) -> 0.018657216 | T29: =AVERAGE(T3:T27) -> 23987.96 | U29: =AVERAGE(U4:U27) -> #N/A | V29: =AVERAGE(V4:V24) -> 13.712545 | AA29: 29410000
B30: St Dv | C30: =STDEV(C3:C27) -> 475.29728 | D30: =STDEV(D3:D27) -> #N/A | E30: =STDEV(E3:E27) -> 44982303 | F30: =STDEV(F3:F27) -> 4.675639 | G30: =STDEV(G3:G27) -> 4906275 | H30: =STDEV(H4:H27) -> 0.054725782 | I30: =STDEV(I4:I27) -> 2.8818632e+08 | J30: =STDEV(J4:J27) -> 769945.27 | K30: =STDEV(K4:K27) -> 37563.824 | L30: =STDEV(L4:L27) -> 711494.81 | M30: =STDEV(M4:M27) -> 28470.347 | N30: =STDEV(N4:N27) -> #REF! | O30: =STDEV(O3:O27) -> 22799.733 | P30: =STDEV(P3:P27) -> 0.068946912 | Q30: =STDEV(Q3:Q27) -> 18196.655 | R30: =STDEV(R3:R27) -> 6834.2314 | S30: =STDEV(S4:S27) -> 0.047651162 | T30: =STDEV(T3:T27) -> 15810.997 | U30: =STDEV(U4:U27) -> #N/A | AA30: 2300000
B31: Weight | C31: 1 | D31: =VLOOKUP(B31,Spend!$A$1:$B$27,2,FALSE) -> #N/A | E31: 1.5 | F31: 1 | G31: =VLOOKUP(B31,NoofMillionaires!$A$1:$B$13,2,FALSE) -> #N/A | H31: 1 | I31: 1 | J31: 1 | K31: 0.1 | L31: 0.1 | M31: 0.1 | N31: 0.1 | O31: 1 | P31: 1 | Q31: 1 | R31: 1 | S31: 1 | T31: 1.25 | U31: 1 | AA31: 3350000
D32: =VLOOKUP(B32,Spend!$A$1:$B$27,2,FALSE) -> #N/A | E32: x | AA32: =AA29-AA30-AA31 -> 23760000
C33: spends per trip | D33: =VLOOKUP(B33,Spend!$A$1:$B$27,2,FALSE) -> #N/A | E33: 2 | T33: update this
C34: departure / population | D34: =VLOOKUP(B34,Spend!$A$1:$B$27,2,FALSE) -> #N/A
B36: Country | C36: =C2 -> Trips(000s) | D36: =D2 -> Spend(m-euro) | E36: =E2 -> Tourist Departures | F36: =F2 -> Hourly Minimum Wage | G36: =G2 -> NoofMillionaires | H36: =H2 -> Inflation Rate | I36: =I2 -> Population(m) | J36: =J2 -> SV -Abu Dhabi | ... U36: =U2 -> Media Cost | V36: Weighted Score
B37: =B4 -> USA | C37: =_xlfn.NORM.DIST(C4,C$29,C$30,TRUE) -> 0.78895443 | D37: =_xlfn.NORM.DIST(D4,D$29,D$30,TRUE) -> #N/A | E37: =_xlfn.NORM.DIST(E4,E$29,E$30,TRUE) -> 0.99808826 | F37: =_xlfn.NORM.DIST(F4,F$29,F$30,TRUE) -> 0.56253978 | G37: =_xlfn.NORM.DIST(G4,G$29,G$30,TRUE) -> 0.99999755 | H37: =_xlfn.NORM.DIST(H4,H$29,H$30,TRUE) -> 0.38704193 | I37: =_xlfn.NORM.DIST(I4,I$29,I$30,TRUE) -> 0.78942771 | J37: =_xlfn.NORM.DIST(J4,J$29,J$30,TRUE) -> 0.99912409 | ... U37: =_xlfn.NORM.DIST(U4,U$29,U$30,TRUE) -> #N/A | V37: =SUMPRODUCT($C$31:$U$31,C37:U37) -> #N/A
B38: =B5 -> UK | C38: =_xlfn.NORM.DIST(C5,C$29,C$30,TRUE) -> 0.97377066 | D38: =_xlfn.NORM.DIST(D5,D$29,D$30,TRUE) -> #N/A | E38: =_xlfn.NORM.DIST(E5,E$29,E$30,TRUE) -> 0.8773458 | F38: =_xlfn.NORM.DIST(F5,F$29,F$30,TRUE) -> 0.95206626 | G38: =_xlfn.NORM.DIST(G5,G$29,G$30,TRUE) -> 0.56356297 | H38: =_xlfn.NORM.DIST(H5,H$29,H$30,TRUE) -> 0.37312688 | I38: =_xlfn.NORM.DIST(I5,I$29,I$30,TRUE) -> 0.4365974 | J38: =_xlfn.NORM.DIST(J5,J$29,J$30,TRUE) -> 0.98237346 | ... U38: =_xlfn.NORM.DIST(U5,U$29,U$30,TRUE) -> #N/A | V38: =SUMPRODUCT($C$31:$U$31,C38:U38) -> #N/A
B39: =B6 -> Germany | C39: =_xlfn.NORM.DIST(C6,C$29,C$30,TRUE) -> 0.64822643 | D39: =_xlfn.NORM.DIST(D6,D$29,D$30,TRUE) -> #N/A | E39: =_xlfn.NORM.DIST(E6,E$29,E$30,TRUE) -> 0.904078 | F39: =_xlfn.NORM.DIST(F6,F$29,F$30,TRUE) -> 0.9416741 | G39: =_xlfn.NORM.DIST(G6,G$29,G$30,TRUE) -> 0.55020318 | H39: =_xlfn.NORM.DIST(H6,H$29,H$30,TRUE) -> 0.35256607 | I39: =_xlfn.NORM.DIST(I6,I$29,I$30,TRUE) -> 0.4558277 | J39: =_xlfn.NORM.DIST(J6,J$29,J$30,TRUE) -> 0.83716329 | ... U39: =_xlfn.NORM.DIST(U6,U$29,U$30,TRUE) -> #N/A | V39: =SUMPRODUCT($C$31:$U$31,C39:U39) -> #N/A
B40: =B7 -> France | C40: =_xlfn.NORM.DIST(C7,C$29,C$30,TRUE) -> 0.5919753 | D40: =_xlfn.NORM.DIST(D7,D$29,D$30,TRUE) -> #N/A | E40: =_xlfn.NORM.DIST(E7,E$29,E$30,TRUE) -> 0.57451538 | F40: =_xlfn.NORM.DIST(F7,F$29,F$30,TRUE) -> 0.91599635 | G40: =_xlfn.NORM.DIST(G7,G$29,G$30,TRUE) -> 0.55930462 | H40: =_xlfn.NORM.DIST(H7,H$29,H$30,TRUE) -> 0.36622966 | I40: =_xlfn.NORM.DIST(I7,I$29,I$30,TRUE) -> 0.43260766 | J40: =_xlfn.NORM.DIST(J7,J$29,J$30,TRUE) -> 0.81572977 | ... U40: =_xlfn.NORM.DIST(U7,U$29,U$30,TRUE) -> #N/A | V40: =SUMPRODUCT($C$31:$U$31,C40:U40) -> #N/A
B41: =B8 -> Egypt | C41: =_xlfn.NORM.DIST(C8,C$29,C$30,TRUE) -> 0.37349822 | D41: =_xlfn.NORM.DIST(D8,D$29,D$30,TRUE) -> #N/A | E41: =_xlfn.NORM.DIST(E8,E$29,E$30,TRUE) -> 0.51987011 | F41: =_xlfn.NORM.DIST(F8,F$29,F$30,TRUE) -> 0.10803423 | G41: =_xlfn.NORM.DIST(G8,G$29,G$30,TRUE) -> 0.34349485 | H41: =_xlfn.NORM.DIST(H8,H$29,H$30,TRUE) -> 0.99999144 | I41: =_xlfn.NORM.DIST(I8,I$29,I$30,TRUE) -> 0.50097037 | J41: =_xlfn.NORM.DIST(J8,J$29,J$30,TRUE) -> 0.27750857 | ... U41: =_xlfn.NORM.DIST(U8,U$29,U$30,TRUE) -> #N/A | V41: =SUMPRODUCT($C$31:$U$31,C41:U41) -> #N/A
B42: =B9 -> Khazakstan | C42: =_xlfn.NORM.DIST(C9,C$29,C$30,TRUE) -> 0.29993719 | D42: =_xlfn.NORM.DIST(D9,D$29,D$30,TRUE) -> #N/A | E42: =_xlfn.NORM.DIST(E9,E$29,E$30,TRUE) -> 0.2515742 | F42: =_xlfn.NORM.DIST(F9,F$29,F$30,TRUE) -> 0.12301314 | G42: =_xlfn.NORM.DIST(G9,G$29,G$30,TRUE) -> 0.34029969 | H42: =_xlfn.NORM.DIST(H9,H$29,H$30,TRUE) -> 0.76920966 | I42: =_xlfn.NORM.DIST(I9,I$29,I$30,TRUE) -> 0.37056584 | J42: =_xlfn.NORM.DIST(J9,J$29,J$30,TRUE) -> 0.23533233 | ... U42: =_xlfn.NORM.DIST(U9,U$29,U$30,TRUE) -> #N/A | V42: =SUMPRODUCT($C$31:$U$31,C42:U42) -> #N/A
B43: =B10 -> Bahrain | C43: =_xlfn.NORM.DIST(C10,C$29,C$30,TRUE) -> 0.28432989 | D43: =_xlfn.NORM.DIST(D10,D$29,D$30,TRUE) -> #N/A | E43: =_xlfn.NORM.DIST(E10,E$29,E$30,TRUE) -> 0.19989684 | F43: =_xlfn.NORM.DIST(F10,F$29,F$30,TRUE) -> 0.54139271 | G43: =_xlfn.NORM.DIST(G10,G$29,G$30,TRUE) -> 0.33885849 | H43: =_xlfn.NORM.DIST(H10,H$29,H$30,TRUE) -> 0.31926096 | I43: =_xlfn.NORM.DIST(I10,I$29,I$30,TRUE) -> 0.34622655 | J43: =_xlfn.NORM.DIST(J10,J$29,J$30,TRUE) -> 0.24441774 | ... U43: =_xlfn.NORM.DIST(U10,U$29,U$30,TRUE) -> #N/A | V43: =SUMPRODUCT($C$31:$U$31,C43:U43) -> #N/A
B44: =B23 -> Italy | C44: =_xlfn.NORM.DIST(C23,C$29,C$30,TRUE) -> 0.43620484 | D44: =_xlfn.NORM.DIST(D23,D$29,D$30,TRUE) -> #N/A | E44: =_xlfn.NORM.DIST(E23,E$29,E$30,TRUE) -> 0.68273141 | F44: =_xlfn.NORM.DIST(F23,F$29,F$30,TRUE) -> 0.77203535 | G44: =_xlfn.NORM.DIST(G23,G$29,G$30,TRUE) -> 0.44722422 | H44: =_xlfn.NORM.DIST(H23,H$29,H$30,TRUE) -> 0.31926096 | I44: =_xlfn.NORM.DIST(I23,I$29,I$30,TRUE) -> 0.42209353 | J44: =_xlfn.NORM.DIST(J23,J$29,J$30,TRUE) -> 0.72017352 | ... U44: =_xlfn.NORM.DIST(U23,U$29,U$30,TRUE) -> #N/A | V44: =SUMPRODUCT($C$31:$U$31,C44:U44) -> #N/A
B45: =B24 -> China | C45: =_xlfn.NORM.DIST(C24,C$29,C$30,TRUE) -> 0.37908884 | D45: =_xlfn.NORM.DIST(D24,D$29,D$30,TRUE) -> #N/A | E45: =_xlfn.NORM.DIST(E24,E$29,E$30,TRUE) -> 0.99429764 | F45: =_xlfn.NORM.DIST(F24,F$29,F$30,TRUE) -> 0.16985566 | G45: =_xlfn.NORM.DIST(G24,G$29,G$30,TRUE) -> 0.79981864 | H45: =_xlfn.NORM.DIST(H24,H$29,H$30,TRUE) -> 0.25118399 | I45: =_xlfn.NORM.DIST(I24,I$29,I$30,TRUE) -> 0.99999721 | J45: =_xlfn.NORM.DIST(J24,J$29,J$30,TRUE) -> 0.21989984 | ... U45: =_xlfn.NORM.DIST(U24,U$29,U$30,TRUE) -> #N/A | V45: =SUMPRODUCT($C$31:$U$31,C45:U45) -> #N/A
B46: =B25 -> Saudi Arabia | C46: =_xlfn.NORM.DIST(C25,C$29,C$30,TRUE) -> 0.99124736 | D46: =_xlfn.NORM.DIST(D25,D$29,D$30,TRUE) -> #N/A | E46: =_xlfn.NORM.DIST(E25,E$29,E$30,TRUE) -> 0.38095339 | F46: =_xlfn.NORM.DIST(F25,F$29,F$30,TRUE) -> 0.46982428 | G46: =_xlfn.NORM.DIST(G25,G$29,G$30,TRUE) -> 0.36059076 | H46: =_xlfn.NORM.DIST(H25,H$29,H$30,TRUE) -> 0.30631874 | I46: =_xlfn.NORM.DIST(I25,I$29,I$30,TRUE) -> 0.39388153 | J46: =_xlfn.NORM.DIST(J25,J$29,J$30,TRUE) -> 0.37913809 | ... U46: =_xlfn.NORM.DIST(U25,U$29,U$30,TRUE) -> #N/A | V46: =SUMPRODUCT($C$31:$U$31,C46:U46) -> #N/A
B47: =B26 -> Russia | C47: =_xlfn.NORM.DIST(C26,C$29,C$30,TRUE) -> 0.88968418 | D47: =_xlfn.NORM.DIST(D26,D$29,D$30,TRUE) -> #N/A | E47: =_xlfn.NORM.DIST(E26,E$29,E$30,TRUE) -> 0.53989076 | F47: =_xlfn.NORM.DIST(F26,F$29,F$30,TRUE) -> 0.12921432 | G47: =_xlfn.NORM.DIST(G26,G$29,G$30,TRUE) -> 0.363647 | H47: =_xlfn.NORM.DIST(H26,H$29,H$30,TRUE) -> 0.69741195 | I47: =_xlfn.NORM.DIST(I26,I$29,I$30,TRUE) -> 0.53919849 | J47: =_xlfn.NORM.DIST(J26,J$29,J$30,TRUE) -> 0.85667053 | ... U47: =_xlfn.NORM.DIST(U26,U$29,U$30,TRUE) -> #N/A | V47: =SUMPRODUCT($C$31:$U$31,C47:U47) -> #N/A
B48: =B27 -> Kuwait | C48: =_xlfn.NORM.DIST(C27,C$29,C$30,TRUE) -> 0.30729173 | D48: =_xlfn.NORM.DIST(D27,D$29,D$30,TRUE) -> #N/A | E48: =_xlfn.NORM.DIST(E27,E$29,E$30,TRUE) -> 0.19989684 | F48: =_xlfn.NORM.DIST(F27,F$29,F$30,TRUE) -> 0.13750107 | G48: =_xlfn.NORM.DIST(G27,G$29,G$30,TRUE) -> 0.35329232 | H48: =_xlfn.NORM.DIST(H27,H$29,H$30,TRUE) -> 0.39405556 | I48: =_xlfn.NORM.DIST(I27,I$29,I$30,TRUE) -> 0.34981585 | J48: =_xlfn.NORM.DIST(J27,J$29,J$30,TRUE) -> 0.27053512 | ... U48: =_xlfn.NORM.DIST(U27,U$29,U$30,TRUE) -> #N/A | V48: =SUMPRODUCT($C$31:$U$31,C48:U48) -> #N/A
B53: UAE
B54: USA
B55: France
B56: India
B57: UK
B58: Italy
B59: China
B60: Saudi Arabia
B61: Germany
B62: Russia
B63: Kuwait
B64: Egypt
... B78: Belgium

Sheet Country Decoder - Final (2)
O1: Outputs | P1: % | Q1: 23760000
B2: Population | C2: Tourist Departures | D2: Trips(000s) | E2: Spend(m-euro) | G2: Country | H2: Spends Per Trip | I2: Tourist Departures / Population | J2: ='Search Volume'!C2 -> SV - Flights to Abu Dhabi | K2: SV - Flights to | L2: =GDP!D1 -> GDP - Growth | M2: =DPI!B1 -> Disposable Personal Income (USD) | N2: ='Cost of Media'!B1 -> Media Cost | O2: Weighted Score | Q2: Budget Split
B3: 334910000 | C3: 80730000 | D3: 1205000 | E3: 1692000000 | G3: United States | H3: =E3/D3 -> 1404.1494 | I3: =C3/B3 -> 0.24104983 | J3: =VLOOKUP(G3,'Search Volume'!$A$2:$C$14,3,FALSE) -> #N/A | K3: 0.18471166 | L3: =VLOOKUP(G3,GDP!$A$2:$D$13,4,FALSE) -> #N/A | M3: =VLOOKUP(G3,DPI!$A$1:$B$13,2,FALSE) -> #N/A | N3: =VLOOKUP(G3,'Cost of Media'!$A$1:$B$13,2,FALSE) -> #N/A | O3: 7.7159307 | P3: =O3/SUM($O$3:$O$14) -> 0.11660705 | Q3: =P3*$Q$1 -> 2770583.5
B4: 68350000 | C4: 71000000 | D4: 3913000 | E4: 1757000000 | G4: United Kingdom | H4: =E4/D4 -> 449.0161 | I4: =C4/B4 -> 1.038771 | J4: =VLOOKUP(G4,'Search Volume'!$A$2:$C$14,3,FALSE) -> #N/A | K4: 0.74679742 | L4: =VLOOKUP(G4,GDP!$A$2:$D$13,4,FALSE) -> #N/A | M4: =VLOOKUP(G4,DPI!$A$1:$B$13,2,FALSE) -> #N/A | N4: =VLOOKUP(G4,'Cost of Media'!$A$1:$B$13,2,FALSE) -> #N/A | O4: 8.3223866 | P4: =O4/SUM($O$3:$O$14) -> 0.12577212 | Q4: =P4*$Q$1 -> 2988345.6
B5: 84480000 | C5: 86623000 | D5: 463000 | E5: 430000000 | G5: Germany | H5: =E5/D5 -> 928.7257 | I5: =C5/B5 -> 1.025367 | J5: =VLOOKUP(G5,'Search Volume'!$A$2:$C$14,3,FALSE) -> 5530 | K5: 0.0055680614 | L5: =VLOOKUP(G5,GDP!$A$2:$D$13,4,FALSE) -> 0.01846286 | M5: =VLOOKUP(G5,DPI!$A$1:$B$13,2,FALSE) -> 42417 | N5: =VLOOKUP(G5,'Cost of Media'!$A$1:$B$13,2,FALSE) -> #N/A | O5: 5.1151639 | P5: =O5/SUM($O$3:$O$14) -> 0.077302946 | Q5: =P5*$Q$1 -> 1836718
B6: 68170000 | C6: 28085000 | D6: 395000 | E6: 362000000 | G6: France | H6: =E6/D6 -> 916.4557 | I6: =C6/B6 -> 0.41198474 | J6: =VLOOKUP(G6,'Search Volume'!$A$2:$C$14,3,FALSE) -> 4240 | K6: 0.003085007 | L6: =VLOOKUP(G6,GDP!$A$2:$D$13,4,FALSE) -> 0.015496521 | M6: =VLOOKUP(G6,DPI!$A$1:$B$13,2,FALSE) -> 35001 | N6: =VLOOKUP(G6,'Cost of Media'!$A$1:$B$13,2,FALSE) -> 0.042772724 | O6: 4.1742451 | P6: =O6/SUM($O$3:$O$14) -> 0.063083305 | Q6: =P6*$Q$1 -> 1498859.3
B7: 48370000 | C7: 15755000 | D7: 286000 | E7: 264000000 | G7: Spain | H7: =E7/D7 -> 923.07692 | I7: =C7/B7 -> 0.32571842 | J7: =VLOOKUP(G7,'Search Volume'!$A$2:$C$14,3,FALSE) -> #N/A | K7: 0.0056746572 | L7: =VLOOKUP(G7,GDP!$A$2:$D$13,4,FALSE) -> 0.044715447 | M7: =VLOOKUP(G7,DPI!$A$1:$B$13,2,FALSE) -> 31193 | N7: =VLOOKUP(G7,'Cost of Media'!$A$1:$B$13,2,FALSE) -> #N/A | O7: 5.0777711 | P7: =O7/SUM($O$3:$O$14) -> 0.076737847 | Q7: =P7*$Q$1 -> 1823291.2
B8: 58760000 | C8: 24970000 | D8: 229000 | E8: 192000000 | G8: Italy | H8: =E8/D8 -> 838.42795 | I8: =C8/B8 -> 0.42494894 | J8: =VLOOKUP(G8,'Search Volume'!$A$2:$C$14,3,FALSE) -> 3370 | K8: 0.0027087866 | L8: =VLOOKUP(G8,GDP!$A$2:$D$13,4,FALSE) -> 0.021079258 | M8: =VLOOKUP(G8,DPI!$A$1:$B$13,2,FALSE) -> 34703 | N8: =VLOOKUP(G8,'Cost of Media'!$A$1:$B$13,2,FALSE) -> 0.15021632 | O8: 4.394105 | P8: =O8/SUM($O$3:$O$14) -> 0.066405939 | Q8: =P8*$Q$1 -> 1577805.1
B9: 40100000 | C9: 21400000 | D9: 180000 | E9: 255000000 | G9: Canada | H9: =E9/D9 -> 1416.6667 | I9: =C9/B9 -> 0.53366584 | J9: =VLOOKUP(G9,'Search Volume'!$A$2:$C$14,3,FALSE) -> #N/A | K9: 0.024730219 | L9: =VLOOKUP(G9,GDP!$A$2:$D$13,4,FALSE) -> -0.0071396698 | M9: =VLOOKUP(G9,DPI!$A$1:$B$13,2,FALSE) -> 35561 | N9: =VLOOKUP(G9,'Cost of Media'!$A$1:$B$13,2,FALSE) -> #N/A | O9: 5.2559761 | P9: =O9/SUM($O$3:$O$14) -> 0.079430972 | Q9: =P9*$Q$1 -> 1887279.9
B10: 31860000 | C10: 10629000 | D10: 164000 | E10: 239000000 | G10: AUS / NZ | H10: =E10/D10 -> 1457.3171 | I10: =C10/B10 -> 0.33361582 | J10: =VLOOKUP(G10,'Search Volume'!$A$2:$C$14,3,FALSE) -> #N/A | K10: 0.015092707 | L10: =VLOOKUP(G10,GDP!$A$2:$D$13,4,FALSE) -> #N/A | M10: =VLOOKUP(G10,DPI!$A$1:$B$13,2,FALSE) -> #N/A | N10: =VLOOKUP(G10,'Cost of Media'!$A$1:$B$13,2,FALSE) -> #N/A | O10: 5.6258992 | P10: =O10/SUM($O$3:$O$14) -> 0.085021437 | Q10: =P10*$Q$1 -> 2020109.3
B11: 30370000 | C11: 41970000 | D11: 264000 | E11: 192000000 | G11: BeNe | H11: =E11/D11 -> 727.27273 | I11: =C11/B11 -> 1.3819559 | J11: =VLOOKUP(G11,'Search Volume'!$A$2:$C$14,3,FALSE) -> #N/A | K11: 0.0061825547 | L11: =VLOOKUP(G11,GDP!$A$2:$D$13,4,FALSE) -> #N/A | M11: =VLOOKUP(G11,DPI!$A$1:$B$13,2,FALSE) -> #N/A | N11: =VLOOKUP(G11,'Cost of Media'!$A$1:$B$13,2,FALSE) -> #N/A | O11: 5.4917122 | P11: =O11/SUM($O$3:$O$14) -> 0.082993535 | Q11: =P11*$Q$1 -> 1971926.4
B12: 27980000 | C12: 25249000 | D12: 154000 | E12: 107000000 | G12: Nordics | H12: =E12/D12 -> 694.80519 | I12: =C12/B12 -> 0.90239457 | J12: =VLOOKUP(G12,'Search Volume'!$A$2:$C$14,3,FALSE) -> #N/A | K12: 0.003436146 | L12: =VLOOKUP(G12,GDP!$A$2:$D$13,4,FALSE) -> #N/A | M12: =VLOOKUP(G12,DPI!$A$1:$B$13,2,FALSE) -> #N/A | N12: =VLOOKUP(G12,'Cost of Media'!$A$1:$B$13,2,FALSE) -> #N/A | O12: 4.03894 | P12: =O12/SUM($O$3:$O$14) -> 0.061038506 | Q12: =P12*$Q$1 -> 1450274.9
B13: 8850000 | C13: 11275100 | D13: 82000 | E13: 71000000 | G13: Switzerland | H13: =E13/D13 -> 865.85366 | I13: =C13/B13 -> 1.2740226 | J13: =VLOOKUP(G13,'Search Volume'!$A$2:$C$14,3,FALSE) -> #N/A | K13: 0.0013230416 | L13: =VLOOKUP(G13,GDP!$A$2:$D$13,4,FALSE) -> #N/A | M13: =VLOOKUP(G13,DPI!$A$1:$B$13,2,FALSE) -> #N/A | N13: =VLOOKUP(G13,'Cost of Media'!$A$1:$B$13,2,FALSE) -> #N/A | O13: 5.653085 | P13: =O13/SUM($O$3:$O$14) -> 0.085432282 | Q13: =P13*$Q$1 -> 2029871
B14: 9130000 | C14: 11871000 | D14: 37000 | E14: 39000000 | G14: Austria | H14: =E14/D14 -> 1054.0541 | I14: =C14/B14 -> 1.3002191 | J14: =VLOOKUP(G14,'Search Volume'!$A$2:$C$14,3,FALSE) -> #N/A | K14: 0.00068973734 | L14: =VLOOKUP(G14,GDP!$A$2:$D$13,4,FALSE) -> #N/A | M14: =VLOOKUP(G14,DPI!$A$1:$B$13,2,FALSE) -> #N/A | N14: =VLOOKUP(G14,'Cost of Media'!$A$1:$B$13,2,FALSE) -> #N/A | O14: 5.3051466 | P14: =O14/SUM($O$3:$O$14) -> 0.080174061 | Q14: =P14*$Q$1 -> 1904935.7
G16: Avg | H16: =AVERAGE(H3:H14) -> 972.98509 | I16: =AVERAGE(I3:I14) -> 0.76614281 | J16: =AVERAGE(J3:J14) -> #N/A | K16: =AVERAGE(K3:K14) -> 0.083333333 | L16: =AVERAGE(L3:L14) -> #N/A | M16: =AVERAGE(M3:M14) -> #N/A | N16: =AVERAGE(N3:N14) -> #N/A | O16: =AVERAGE(O3:O11) -> 5.68591 | T16: 29410000
G17: St Dv | H17: =STDEV(H3:H14) -> 312.3861 | I17: =STDEV(I3:I14) -> 0.4301327 | J17: =STDEV(J3:J14) -> #N/A | K17: =STDEV(K3:K14) -> 0.21520881 | L17: =STDEV(L3:L14) -> #N/A | M17: =STDEV(M3:M14) -> #N/A | N17: =STDEV(N3:N14) -> #N/A | T17: 2300000
G18: Weight | H18: 2 | I18: 1.2 | J18: 1.5 | K18: 1.2 | L18: 1 | M18: 1.25 | N18: 1 | T18: 3350000
T19: =T16-T17-T18 -> 23760000
G23: Country | H23: =H2 -> Spends Per Trip | I23: =I2 -> Tourist Departures / Population | J23: =J2 -> SV - Flights to Abu Dhabi | K23: SV - Flights to | L23: =L2 -> GDP - Growth | M23: =M2 -> Disposable Personal Income (USD) | N23: =N2 -> Media Cost | O23: Weighted Score
G24: =G3 -> United States | H24: =_xlfn.NORM.DIST(H3,H$16,H$17,TRUE) -> 0.91624189 | I24: =_xlfn.NORM.DIST(I3,I$16,I$17,TRUE) -> 0.11108661 | J24: =_xlfn.NORM.DIST(J3,J$16,J$17,TRUE) -> #N/A | K24: =_xlfn.NORM.DIST(K3,K$16,K$17,TRUE) -> 0.68120448 | L24: =_xlfn.NORM.DIST(L3,L$16,L$17,TRUE) -> #N/A | M24: =_xlfn.NORM.DIST(M3,M$16,M$17,TRUE) -> #N/A | N24: =_xlfn.NORM.DIST(N3,N$16,N$17,TRUE) -> #N/A | O24: =SUMPRODUCT($H$18:$N$18,H24:N24) -> #N/A
G25: =G4 -> United Kingdom | H25: =_xlfn.NORM.DIST(H4,H$16,H$17,TRUE) -> 0.04674073 | I25: =_xlfn.NORM.DIST(I4,I$16,I$17,TRUE) -> 0.736902 | J25: =_xlfn.NORM.DIST(J4,J$16,J$17,TRUE) -> #N/A | K25: =_xlfn.NORM.DIST(K4,K$16,K$17,TRUE) -> 0.99897498 | L25: =_xlfn.NORM.DIST(L4,L$16,L$17,TRUE) -> #N/A | M25: =_xlfn.NORM.DIST(M4,M$16,M$17,TRUE) -> #N/A | N25: =_xlfn.NORM.DIST(N4,N$16,N$17,TRUE) -> #N/A | O25: =SUMPRODUCT($H$18:$N$18,H25:N25) -> #N/A
G26: =G5 -> Germany | H26: =_xlfn.NORM.DIST(H5,H$16,H$17,TRUE) -> 0.44366572 | I26: =_xlfn.NORM.DIST(I5,I$16,I$17,TRUE) -> 0.72663284 | J26: =_xlfn.NORM.DIST(J5,J$16,J$17,TRUE) -> #N/A | K26: =_xlfn.NORM.DIST(K5,K$16,K$17,TRUE) -> 0.35891966 | L26: =_xlfn.NORM.DIST(L5,L$16,L$17,TRUE) -> #N/A | M26: =_xlfn.NORM.DIST(M5,M$16,M$17,TRUE) -> #N/A | N26: =_xlfn.NORM.DIST(N5,N$16,N$17,TRUE) -> #N/A | O26: =SUMPRODUCT($H$18:$N$18,H26:N26) -> #N/A
G27: =G6 -> France | H27: =_xlfn.NORM.DIST(H6,H$16,H$17,TRUE) -> 0.42819948 | I27: =_xlfn.NORM.DIST(I6,I$16,I$17,TRUE) -> 0.205149 | J27: =_xlfn.NORM.DIST(J6,J$16,J$17,TRUE) -> #N/A | K27: =_xlfn.NORM.DIST(K6,K$16,K$17,TRUE) -> 0.35461669 | L27: =_xlfn.NORM.DIST(L6,L$16,L$17,TRUE) -> #N/A | M27: =_xlfn.NORM.DIST(M6,M$16,M$17,TRUE) -> #N/A | N27: =_xlfn.NORM.DIST(N6,N$16,N$17,TRUE) -> #N/A | O27: =SUMPRODUCT($H$18:$N$18,H27:N27) -> #N/A
G28: =G7 -> Spain | H28: =_xlfn.NORM.DIST(H7,H$16,H$17,TRUE) -> 0.43653334 | I28: =_xlfn.NORM.DIST(I7,I$16,I$17,TRUE) -> 0.15293493 | J28: =_xlfn.NORM.DIST(J7,J$16,J$17,TRUE) -> #N/A | K28: =_xlfn.NORM.DIST(K7,K$16,K$17,TRUE) -> 0.35910479 | L28: =_xlfn.NORM.DIST(L7,L$16,L$17,TRUE) -> #N/A | M28: =_xlfn.NORM.DIST(M7,M$16,M$17,TRUE) -> #N/A | N28: =_xlfn.NORM.DIST(N7,N$16,N$17,TRUE) -> #N/A | O28: =SUMPRODUCT($H$18:$N$18,H28:N28) -> #N/A
G29: =G8 -> Italy | H29: =_xlfn.NORM.DIST(H8,H$16,H$17,TRUE) -> 0.33332876 | I29: =_xlfn.NORM.DIST(I8,I$16,I$17,TRUE) -> 0.21382212 | J29: =_xlfn.NORM.DIST(J8,J$16,J$17,TRUE) -> #N/A | K29: =_xlfn.NORM.DIST(K8,K$16,K$17,TRUE) -> 0.35396632 | L29: =_xlfn.NORM.DIST(L8,L$16,L$17,TRUE) -> #N/A | M29: =_xlfn.NORM.DIST(M8,M$16,M$17,TRUE) -> #N/A | N29: =_xlfn.NORM.DIST(N8,N$16,N$17,TRUE) -> #N/A | O29: =SUMPRODUCT($H$18:$N$18,H29:N29) -> #N/A
G30: =G9 -> Canada | H30: =_xlfn.NORM.DIST(H9,H$16,H$17,TRUE) -> 0.92223963 | I30: =_xlfn.NORM.DIST(I9,I$16,I$17,TRUE) -> 0.29443395 | J30: =_xlfn.NORM.DIST(J9,J$16,J$17,TRUE) -> #N/A | K30: =_xlfn.NORM.DIST(K9,K$16,K$17,TRUE) -> 0.39269254 | L30: =_xlfn.NORM.DIST(L9,L$16,L$17,TRUE) -> #N/A | M30: =_xlfn.NORM.DIST(M9,M$16,M$17,TRUE) -> #N/A | N30: =_xlfn.NORM.DIST(N9,N$16,N$17,TRUE) -> #N/A | O30: =SUMPRODUCT($H$18:$N$18,H30:N30) -> #N/A
G31: =G10 -> AUS / NZ | H31: =_xlfn.NORM.DIST(H10,H$16,H$17,TRUE) -> 0.93948052 | I31: =_xlfn.NORM.DIST(I10,I$16,I$17,TRUE) -> 0.1573121 | J31: =_xlfn.NORM.DIST(J10,J$16,J$17,TRUE) -> #N/A | K31: =_xlfn.NORM.DIST(K10,K$16,K$17,TRUE) -> 0.37558754 | L31: =_xlfn.NORM.DIST(L10,L$16,L$17,TRUE) -> #N/A | M31: =_xlfn.NORM.DIST(M10,M$16,M$17,TRUE) -> #N/A | N31: =_xlfn.NORM.DIST(N10,N$16,N$17,TRUE) -> #N/A | O31: =SUMPRODUCT($H$18:$N$18,H31:N31) -> #N/A
G32: =G11 -> BeNe | H32: =_xlfn.NORM.DIST(H11,H$16,H$17,TRUE) -> 0.21576791 | I32: =_xlfn.NORM.DIST(I11,I$16,I$17,TRUE) -> 0.92388252 | J32: =_xlfn.NORM.DIST(J11,J$16,J$17,TRUE) -> #N/A | K32: =_xlfn.NORM.DIST(K11,K$16,K$17,TRUE) -> 0.35998733 | L32: =_xlfn.NORM.DIST(L11,L$16,L$17,TRUE) -> #N/A | M32: =_xlfn.NORM.DIST(M11,M$16,M$17,TRUE) -> #N/A | N32: =_xlfn.NORM.DIST(N11,N$16,N$17,TRUE) -> #N/A | O32: =SUMPRODUCT($H$18:$N$18,H32:N32) -> #N/A
G33: =G12 -> Nordics | H33: =_xlfn.NORM.DIST(H12,H$16,H$17,TRUE) -> 0.18659867 | I33: =_xlfn.NORM.DIST(I12,I$16,I$17,TRUE) -> 0.62428972 | J33: =_xlfn.NORM.DIST(J12,J$16,J$17,TRUE) -> #N/A | K33: =_xlfn.NORM.DIST(K12,K$16,K$17,TRUE) -> 0.35522408 | L33: =_xlfn.NORM.DIST(L12,L$16,L$17,TRUE) -> #N/A | M33: =_xlfn.NORM.DIST(M12,M$16,M$17,TRUE) -> #N/A | N33: =_xlfn.NORM.DIST(N12,N$16,N$17,TRUE) -> #N/A | O33: =SUMPRODUCT($H$18:$N$18,H33:N33) -> #N/A
G34: =G13 -> Switzerland | H34: =_xlfn.NORM.DIST(H13,H$16,H$17,TRUE) -> 0.3658197 | I34: =_xlfn.NORM.DIST(I13,I$16,I$17,TRUE) -> 0.88114926 | J34: =_xlfn.NORM.DIST(J13,J$16,J$17,TRUE) -> #N/A | K34: =_xlfn.NORM.DIST(K13,K$16,K$17,TRUE) -> 0.3515745 | L34: =_xlfn.NORM.DIST(L13,L$16,L$17,TRUE) -> #N/A | M34: =_xlfn.NORM.DIST(M13,M$16,M$17,TRUE) -> #N/A | N34: =_xlfn.NORM.DIST(N13,N$16,N$17,TRUE) -> #N/A | O34: =SUMPRODUCT($H$18:$N$18,H34:N34) -> #N/A
G35: =G14 -> Austria | H35: =_xlfn.NORM.DIST(H14,H$16,H$17,TRUE) -> 0.60238115 | I35: =_xlfn.NORM.DIST(I14,I$16,I$17,TRUE) -> 0.89281799 | J35: =_xlfn.NORM.DIST(J14,J$16,J$17,TRUE) -> #N/A | K35: =_xlfn.NORM.DIST(K14,K$16,K$17,TRUE) -> 0.35048335 | L35: =_xlfn.NORM.DIST(L14,L$16,L$17,TRUE) -> #N/A | M35: =_xlfn.NORM.DIST(M14,M$16,M$17,TRUE) -> #N/A | N35: =_xlfn.NORM.DIST(N14,N$16,N$17,TRUE) -> #N/A | O35: =SUMPRODUCT($H$18:$N$18,H35:N35) -> #N/A

Sheet Country Decoder - Final
Q1: Outputs | R1: % | S1: 23760000
A2: SV - Flights to Ireland | B2: SV - Flights to Dublin | C2: SV - Flights to Cork | D2: SV - Flights to Belfast | E2: Population | F2: Tourist Departures | G2: Trips(000s) | H2: Spend(m-euro) | J2: Country | K2: Spends Per Trip | L2: Tourist Departures / Population | M2: SV - All | N2: =GDP!D1 -> GDP - Growth | O2: =DPI!B1 -> Disposable Personal Income (USD) | P2: ='Cost of Media'!B1 -> Media Cost | Q2: Weighted Score | S2: Budget Split
A3: 424400 | B3: 263900 | C3: 4580 | D3: 26100 | E3: 334910000 | F3: 80730000 | G3: 1205000 | H3: 1692000000 | J3: United States | K3: =H3/G3 -> 1404.1494 | L3: =F3/E3 -> 0.24104983 | M3: =A3+B3+C3+D3 -> 718980 | N3: =VLOOKUP(J3,GDP!$A$2:$D$13,4,FALSE) -> #N/A | O3: =VLOOKUP(J3,DPI!$A$1:$B$13,2,FALSE) -> #N/A | P3: =VLOOKUP(J3,'Cost of Media'!$A$1:$B$13,2,FALSE) -> #N/A | Q3: 5.0331742 | R3: =Q3/SUM($Q$3:$Q$14) -> 0.11858369 | S3: =R3*$S$1 -> 2817548.5 | T3: United States
A4: 147200 | B4: 791500 | C4: 55200 | D4: 344300 | E4: 68350000 | F4: 71000000 | G4: 3913000 | H4: 1757000000 | J4: United Kingdom | K4: =H4/G4 -> 449.0161 | L4: =F4/E4 -> 1.038771 | M4: =A4+B4+C4+D4 -> 1338200 | N4: =VLOOKUP(J4,GDP!$A$2:$D$13,4,FALSE) -> #N/A | O4: =VLOOKUP(J4,DPI!$A$1:$B$13,2,FALSE) -> #N/A | P4: =VLOOKUP(J4,'Cost of Media'!$A$1:$B$13,2,FALSE) -> #N/A | Q4: 4.0494804 | R4: =Q4/SUM($Q$3:$Q$14) -> 0.095407454 | S4: =R4*$S$1 -> 2266881.1 | T4: United Kingdom
A5: 2790 | B5: 7280 | C5: 490 | D5: 1110 | E5: 84480000 | F5: 86623000 | G5: 463000 | H5: 430000000 | J5: Germany | K5: =H5/G5 -> 928.7257 | L5: =F5/E5 -> 1.025367 | M5: =A5+B5+C5+D5 -> 11670 | N5: =VLOOKUP(J5,GDP!$A$2:$D$13,4,FALSE) -> 0.01846286 | O5: =VLOOKUP(J5,DPI!$A$1:$B$13,2,FALSE) -> 42417 | P5: =VLOOKUP(J5,'Cost of Media'!$A$1:$B$13,2,FALSE) -> #N/A | Q5: 3.4516511 | R5: =Q5/SUM($Q$3:$Q$14) -> 0.081322346 | S5: =R5*$S$1 -> 1932218.9 | T5: Germany
A6: 1120 | B6: 3840 | C6: 380 | D6: 700 | E6: 68170000 | F6: 28085000 | G6: 395000 | H6: 362000000 | J6: France | K6: =H6/G6 -> 916.4557 | L6: =F6/E6 -> 0.41198474 | M6: =A6+B6+C6+D6 -> 6040 | N6: =VLOOKUP(J6,GDP!$A$2:$D$13,4,FALSE) -> 0.015496521 | O6: =VLOOKUP(J6,DPI!$A$1:$B$13,2,FALSE) -> 35001 | P6: =VLOOKUP(J6,'Cost of Media'!$A$1:$B$13,2,FALSE) -> 0.042772724 | Q6: 2.5253236 | R6: =Q6/SUM($Q$3:$Q$14) -> 0.059497682 | S6: =R6*$S$1 -> 1413664.9 | T6: France
A7: 1840 | B7: 6790 | C7: 560 | D7: 1700 | E7: 48370000 | F7: 15755000 | G7: 286000 | H7: 264000000 | J7: Spain | K7: =H7/G7 -> 923.07692 | L7: =F7/E7 -> 0.32571842 | M7: =A7+B7+C7+D7 -> 10890 | N7: =VLOOKUP(J7,GDP!$A$2:$D$13,4,FALSE) -> 0.044715447 | O7: =VLOOKUP(J7,DPI!$A$1:$B$13,2,FALSE) -> 31193 | P7: =VLOOKUP(J7,'Cost of Media'!$A$1:$B$13,2,FALSE) -> #N/A | Q7: 3.4116052 | R7: =Q7/SUM($Q$3:$Q$14) -> 0.080378848 | S7: =R7*$S$1 -> 1909801.4 | T7: Spain
A8: 1550 | B8: 3620 | C8: 310 | D8: 390 | E8: 58760000 | F8: 24970000 | G8: 229000 | H8: 192000000 | J8: Italy | K8: =H8/G8 -> 838.42795 | L8: =F8/E8 -> 0.42494894 | M8: =A8+B8+C8+D8 -> 5870 | N8: =VLOOKUP(J8,GDP!$A$2:$D$13,4,FALSE) -> 0.021079258 | O8: =VLOOKUP(J8,DPI!$A$1:$B$13,2,FALSE) -> 34703 | P8: =VLOOKUP(J8,'Cost of Media'!$A$1:$B$13,2,FALSE) -> 0.15021632 | Q8: 2.7486131 | R8: =Q8/SUM($Q$3:$Q$14) -> 0.064758476 | S8: =R8*$S$1 -> 1538661.4 | T8: Italy
A9: 37700 | B9: 35200 | C9: 680 | D9: 3560 | E9: 40100000 | F9: 21400000 | G9: 180000 | H9: 255000000 | J9: Canada | K9: =H9/G9 -> 1416.6667 | L9: =F9/E9 -> 0.53366584 | M9: =A9+B9+C9+D9 -> 77140 | N9: =VLOOKUP(J9,GDP!$A$2:$D$13,4,FALSE) -> -0.0071396698 | O9: =VLOOKUP(J9,DPI!$A$1:$B$13,2,FALSE) -> 35561 | P9: =VLOOKUP(J9,'Cost of Media'!$A$1:$B$13,2,FALSE) -> #N/A | Q9: 3.454063 | R9: =Q9/SUM($Q$3:$Q$14) -> 0.081379172 | S9: =R9*$S$1 -> 1933569.1 | T9: Canada
A10: 24160 | B10: 20450 | C10: 780 | D10: 2840 | E10: 31860000 | F10: 10629000 | G10: 164000 | H10: 239000000 | J10: AUS / NZ | K10: =H10/G10 -> 1457.3171 | L10: =F10/E10 -> 0.33361582 | M10: =A10+B10+C10+D10 -> 48230 | N10: =VLOOKUP(J10,GDP!$A$2:$D$13,4,FALSE) -> #N/A | O10: =VLOOKUP(J10,DPI!$A$1:$B$13,2,FALSE) -> #N/A | P10: =VLOOKUP(J10,'Cost of Media'!$A$1:$B$13,2,FALSE) -> #N/A | Q10: 3.877353 | R10: =Q10/SUM($Q$3:$Q$14) -> 0.091352062 | S10: =R10*$S$1 -> 2170525 | T10: AUS / NZ
A11: 2180 | B11: 7860 | C11: 740 | D11: 1260 | E11: 30370000 | F11: 41970000 | G11: 264000 | H11: 192000000 | J11: BeNe | K11: =H11/G11 -> 727.27273 | L11: =F11/E11 -> 1.3819559 | M11: =A11+B11+C11+D11 -> 12040 | N11: =VLOOKUP(J11,GDP!$A$2:$D$13,4,FALSE) -> #N/A | O11: =VLOOKUP(J11,DPI!$A$1:$B$13,2,FALSE) -> #N/A | P11: =VLOOKUP(J11,'Cost of Media'!$A$1:$B$13,2,FALSE) -> #N/A | Q11: 3.818982 | R11: =Q11/SUM($Q$3:$Q$14) -> 0.089976816 | S11: =R11*$S$1 -> 2137849.1 | T11: BeNe
A12: 1640 | B12: 4130 | C12: 570 | D12: 780 | E12: 27980000 | F12: 25249000 | G12: 154000 | H12: 107000000 | J12: Nordics | K12: =H12/G12 -> 694.80519 | L12: =F12/E12 -> 0.90239457 | M12: =A12+B12+C12+D12 -> 7120 | N12: =VLOOKUP(J12,GDP!$A$2:$D$13,4,FALSE) -> #N/A | O12: =VLOOKUP(J12,DPI!$A$1:$B$13,2,FALSE) -> #N/A | P12: =VLOOKUP(J12,'Cost of Media'!$A$1:$B$13,2,FALSE) -> #N/A | Q12: 2.3813938 | R12: =Q12/SUM($Q$3:$Q$14) -> 0.056106636 | S12: =R12*$S$1 -> 1333093.7 | T12: Nordics
A13: 590 | B13: 1680 | C13: 170 | D13: 260 | E13: 8850000 | F13: 11275100 | G13: 82000 | H13: 71000000 | J13: Switzerland | K13: =H13/G13 -> 865.85366 | L13: =F13/E13 -> 1.2740226 | M13: =A13+B13+C13+D13 -> 2700 | N13: =VLOOKUP(J13,GDP!$A$2:$D$13,4,FALSE) -> #N/A | O13: =VLOOKUP(J13,DPI!$A$1:$B$13,2,FALSE) -> #N/A | P13: =VLOOKUP(J13,'Cost of Media'!$A$1:$B$13,2,FALSE) -> #N/A | Q13: 4.0180779 | R13: =Q13/SUM($Q$3:$Q$14) -> 0.094667599 | S13: =R13*$S$1 -> 2249302.1 | T13: Switzerland
A14: 300 | B14: 840 | C14: 120 | D14: 140 | E14: 9130000 | F14: 11871000 | G14: 37000 | H14: 39000000 | J14: Austria | K14: =H14/G14 -> 1054.0541 | L14: =F14/E14 -> 1.3002191 | M14: =A14+B14+C14+D14 -> 1400 | N14: =VLOOKUP(J14,GDP!$A$2:$D$13,4,FALSE) -> #N/A | O14: =VLOOKUP(J14,DPI!$A$1:$B$13,2,FALSE) -> #N/A | P14: =VLOOKUP(J14,'Cost of Media'!$A$1:$B$13,2,FALSE) -> #N/A | Q14: 3.6743496 | R14: =Q14/SUM($Q$3:$Q$14) -> 0.086569217 | S14: =R14*$S$1 -> 2056884.6 | T14: Austria
J15: UAE | K15: =H15/G15 -> #DIV/0! | L15: =F15/E15 -> #DIV/0! | M15: =A15+B15+C15+D15 -> 0 | N15: =VLOOKUP(J15,GDP!$A$2:$D$13,4,FALSE) -> #N/A | O15: =VLOOKUP(J15,DPI!$A$1:$B$13,2,FALSE) -> 36020 | P15: =VLOOKUP(J15,'Cost of Media'!$A$1:$B$13,2,FALSE) -> #N/A | Q15: 3.6743496 | R15: =Q15/SUM($Q$3:$Q$14) -> 0.086569217
J16: Avg | K16: =AVERAGE(K3:K14) -> 972.98509 | L16: =AVERAGE(L3:L14) -> 0.76614281 | M16: =AVERAGE(M3:M14) -> 186690 | N16: =AVERAGE(N3:N14) -> #N/A | O16: =AVERAGE(O3:O14) -> #N/A | P16: =AVERAGE(P3:P14) -> #N/A | Q16: =AVERAGE(Q3:Q11) -> 3.5966939 | V16: 29410000
J17: St Dv | K17: =STDEV(K3:K14) -> 312.3861 | L17: =STDEV(L3:L14) -> 0.4301327 | M17: =STDEV(M3:M14) -> 415416.65 | N17: =STDEV(N3:N14) -> #N/A | O17: =STDEV(O3:O14) -> #N/A | P17: =STDEV(P3:P14) -> #N/A | V17: 2300000
J18: Weight | K18: 2 | L18: 1.2 | M18: 1 | N18: 1 | O18: 1.25 | P18: 1 | V18: 3350000
V19: =V16-V17-V18 -> 23760000
J23: Country | K23: =K2 -> Spends Per Trip | L23: =L2 -> Tourist Departures / Population | M23: =M2 -> SV - All | N23: =N2 -> GDP - Growth | O23: =O2 -> Disposable Personal Income (USD) | P23: =P2 -> Media Cost | Q23: Weighted Score
J24: =J3 -> United States | K24: =_xlfn.NORM.DIST(K3,K$16,K$17,TRUE) -> 0.91624189 | L24: =_xlfn.NORM.DIST(L3,L$16,L$17,TRUE) -> 0.11108661 | M24: =_xlfn.NORM.DIST(M3,M$16,M$17,TRUE) -> 0.89996288 | N24: =_xlfn.NORM.DIST(N3,N$16,N$17,TRUE) -> #N/A | O24: =_xlfn.NORM.DIST(O3,O$16,O$17,TRUE) -> #N/A | P24: =_xlfn.NORM.DIST(P3,P$16,P$17,TRUE) -> #N/A | Q24: =SUMPRODUCT($K$18:$P$18,K24:P24) -> #N/A
J25: =J4 -> United Kingdom | K25: =_xlfn.NORM.DIST(K4,K$16,K$17,TRUE) -> 0.04674073 | L25: =_xlfn.NORM.DIST(L4,L$16,L$17,TRUE) -> 0.736902 | M25: =_xlfn.NORM.DIST(M4,M$16,M$17,TRUE) -> 0.99721383 | N25: =_xlfn.NORM.DIST(N4,N$16,N$17,TRUE) -> #N/A | O25: =_xlfn.NORM.DIST(O4,O$16,O$17,TRUE) -> #N/A | P25: =_xlfn.NORM.DIST(P4,P$16,P$17,TRUE) -> #N/A | Q25: =SUMPRODUCT($K$18:$P$18,K25:P25) -> #N/A
J26: =J5 -> Germany | K26: =_xlfn.NORM.DIST(K5,K$16,K$17,TRUE) -> 0.44366572 | L26: =_xlfn.NORM.DIST(L5,L$16,L$17,TRUE) -> 0.72663284 | M26: =_xlfn.NORM.DIST(M5,M$16,M$17,TRUE) -> 0.33676365 | N26: =_xlfn.NORM.DIST(N5,N$16,N$17,TRUE) -> #N/A | O26: =_xlfn.NORM.DIST(O5,O$16,O$17,TRUE) -> #N/A | P26: =_xlfn.NORM.DIST(P5,P$16,P$17,TRUE) -> #N/A | Q26: =SUMPRODUCT($K$18:$P$18,K26:P26) -> #N/A
J27: =J6 -> France | K27: =_xlfn.NORM.DIST(K6,K$16,K$17,TRUE) -> 0.42819948 | L27: =_xlfn.NORM.DIST(L6,L$16,L$17,TRUE) -> 0.205149 | M27: =_xlfn.NORM.DIST(M6,M$16,M$17,TRUE) -> 0.33183035 | N27: =_xlfn.NORM.DIST(N6,N$16,N$17,TRUE) -> #N/A | O27: =_xlfn.NORM.DIST(O6,O$16,O$17,TRUE) -> #N/A | P27: =_xlfn.NORM.DIST(P6,P$16,P$17,TRUE) -> #N/A | Q27: =SUMPRODUCT($K$18:$P$18,K27:P27) -> #N/A
J28: =J7 -> Spain | K28: =_xlfn.NORM.DIST(K7,K$16,K$17,TRUE) -> 0.43653334 | L28: =_xlfn.NORM.DIST(L7,L$16,L$17,TRUE) -> 0.15293493 | M28: =_xlfn.NORM.DIST(M7,M$16,M$17,TRUE) -> 0.33607847 | N28: =_xlfn.NORM.DIST(N7,N$16,N$17,TRUE) -> #N/A | O28: =_xlfn.NORM.DIST(O7,O$16,O$17,TRUE) -> #N/A | P28: =_xlfn.NORM.DIST(P7,P$16,P$17,TRUE) -> #N/A | Q28: =SUMPRODUCT($K$18:$P$18,K28:P28) -> #N/A
J29: =J8 -> Italy | K29: =_xlfn.NORM.DIST(K8,K$16,K$17,TRUE) -> 0.33332876 | L29: =_xlfn.NORM.DIST(L8,L$16,L$17,TRUE) -> 0.21382212 | M29: =_xlfn.NORM.DIST(M8,M$16,M$17,TRUE) -> 0.33168184 | N29: =_xlfn.NORM.DIST(N8,N$16,N$17,TRUE) -> #N/A | O29: =_xlfn.NORM.DIST(O8,O$16,O$17,TRUE) -> #N/A | P29: =_xlfn.NORM.DIST(P8,P$16,P$17,TRUE) -> #N/A | Q29: =SUMPRODUCT($K$18:$P$18,K29:P29) -> #N/A
J30: =J9 -> Canada | K30: =_xlfn.NORM.DIST(K9,K$16,K$17,TRUE) -> 0.92223963 | L30: =_xlfn.NORM.DIST(L9,L$16,L$17,TRUE) -> 0.29443395 | M30: =_xlfn.NORM.DIST(M9,M$16,M$17,TRUE) -> 0.39600125 | N30: =_xlfn.NORM.DIST(N9,N$16,N$17,TRUE) -> #N/A | O30: =_xlfn.NORM.DIST(O9,O$16,O$17,TRUE) -> #N/A | P30: =_xlfn.NORM.DIST(P9,P$16,P$17,TRUE) -> #N/A | Q30: =SUMPRODUCT($K$18:$P$18,K30:P30) -> #N/A
J31: =J10 -> AUS / NZ | K31: =_xlfn.NORM.DIST(K10,K$16,K$17,TRUE) -> 0.93948052 | L31: =_xlfn.NORM.DIST(L10,L$16,L$17,TRUE) -> 0.1573121 | M31: =_xlfn.NORM.DIST(M10,M$16,M$17,TRUE) -> 0.36945244 | N31: =_xlfn.NORM.DIST(N10,N$16,N$17,TRUE) -> #N/A | O31: =_xlfn.NORM.DIST(O10,O$16,O$17,TRUE) -> #N/A | P31: =_xlfn.NORM.DIST(P10,P$16,P$17,TRUE) -> #N/A | Q31: =SUMPRODUCT($K$18:$P$18,K31:P31) -> #N/A
J32: =J11 -> BeNe | K32: =_xlfn.NORM.DIST(K11,K$16,K$17,TRUE) -> 0.21576791 | L32: =_xlfn.NORM.DIST(L11,L$16,L$17,TRUE) -> 0.92388252 | M32: =_xlfn.NORM.DIST(M11,M$16,M$17,TRUE) -> 0.33708886 | N32: =_xlfn.NORM.DIST(N11,N$16,N$17,TRUE) -> #N/A | O32: =_xlfn.NORM.DIST(O11,O$16,O$17,TRUE) -> #N/A | P32: =_xlfn.NORM.DIST(P11,P$16,P$17,TRUE) -> #N/A | Q32: =SUMPRODUCT($K$18:$P$18,K32:P32) -> #N/A
J33: =J12 -> Nordics | K33: =_xlfn.NORM.DIST(K12,K$16,K$17,TRUE) -> 0.18659867 | L33: =_xlfn.NORM.DIST(L12,L$16,L$17,TRUE) -> 0.62428972 | M33: =_xlfn.NORM.DIST(M12,M$16,M$17,TRUE) -> 0.33277448 | N33: =_xlfn.NORM.DIST(N12,N$16,N$17,TRUE) -> #N/A | O33: =_xlfn.NORM.DIST(O12,O$16,O$17,TRUE) -> #N/A | P33: =_xlfn.NORM.DIST(P12,P$16,P$17,TRUE) -> #N/A | Q33: =SUMPRODUCT($K$18:$P$18,K33:P33) -> #N/A
J34: =J13 -> Switzerland | K34: =_xlfn.NORM.DIST(K13,K$16,K$17,TRUE) -> 0.3658197 | L34: =_xlfn.NORM.DIST(L13,L$16,L$17,TRUE) -> 0.88114926 | M34: =_xlfn.NORM.DIST(M13,M$16,M$17,TRUE) -> 0.32891732 | N34: =_xlfn.NORM.DIST(N13,N$16,N$17,TRUE) -> #N/A | O34: =_xlfn.NORM.DIST(O13,O$16,O$17,TRUE) -> #N/A | P34: =_xlfn.NORM.DIST(P13,P$16,P$17,TRUE) -> #N/A | Q34: =SUMPRODUCT($K$18:$P$18,K34:P34) -> #N/A
J35: =J14 -> Austria | K35: =_xlfn.NORM.DIST(K14,K$16,K$17,TRUE) -> 0.60238115 | L35: =_xlfn.NORM.DIST(L14,L$16,L$17,TRUE) -> 0.89281799 | M35: =_xlfn.NORM.DIST(M14,M$16,M$17,TRUE) -> 0.3277863 | N35: =_xlfn.NORM.DIST(N14,N$16,N$17,TRUE) -> #N/A | O35: =_xlfn.NORM.DIST(O14,O$16,O$17,TRUE) -> #N/A | P35: =_xlfn.NORM.DIST(P14,P$16,P$17,TRUE) -> #N/A | Q35: =SUMPRODUCT($K$18:$P$18,K35:P35) -> #N/A

Sheet DPI
A1: Country | B1: Disposable Personal Income (USD)
A2: USA | B2: 60944
A3: Germany | B3: 42417
A4: Netherlands | B4: 40722
A5: Belgium | B5: 37365
A6: South Korea | B6: 36230
A7: UK | B7: 36077
A8: UAE | B8: 36020
A9: Canada | B9: 35561
A10: France | B10: 35001
A11: Italy | B11: 34703
A12: Spain | B12: 31193
A13: Japan | B13: 28040
... A27: Qatar | B27: 17459
A28: Source | B28: https://en.wikipedia.org/wiki/Disposable_household_and_per_capita_income

Sheet Trips
A1: Country | B1: Trips(000s)
A2: UAE
A3: USA | B3: 704.9
A4: France | B4: 433.9
A5: India | B5: 2200.3
A6: UK | B6: 1245.1
A7: Italy | B7: 247
A8: China | B8: 177
A9: Saudi Arabia | B9: 1452.6
A10: Germany | B10: 504.2
A11: Russia | B11: 905.5
A12: Kuwait | B12: 84
A13: Egypt | B13: 170
A14: Khazakstan | B14: 74
A15: Bahrain | B15: 52.4
A16: Qatar
A17: Canada | B17: 59
A18: Romania | B18: 35.1
A19: Oman | B19: 1565.8
A20: Spain | B20: 52.8
A21: Netherlands | B21: 61.4
A22: Japan | B22: 27
A23: Uzbekistan | B23: 104.6
A24: Poland | B24: 40.7
A25: South Korea | B25: 37.7
A26: Armenia | B26: 12
A27: Belgium | B27: 36.6
A28: Source

Sheet Spend
A1: Country | B1: Spend(m-euro)
A2: United States | B2: 1692 | E2: Row Labels | F2: Sum of Grand Total
A3: United Kingdom | B3: 1757 | E3: UM Media Algeria | F3: 377523.38
A4: Germany | B4: 430 | E4: UM Media Angola | F4: 497551.3
A5: France | B5: 362 | E5: UM Media Australia | F5: 6574297
A6: Spain | B6: 264 | E6: UM Media Austria | F6: 1703165.5
A7: Italy | B7: 192 | E7: UM Media Bahrain | F7: 185231.33
A8: Canada | B8: 255 | E8: UM Media Bangladesh | F8: 1142257.6
A9: AUS / NZ | B9: =SUM(B24:B25) -> 239 | E9: UM Media Belgium | F9: 2747352
A10: BeNe | B10: =SUM(B16:B18) -> 192 | E10: UM Media Brazil | F10: 2638362.2
A11: Nordics | B11: 107 | E11: UM Media Canada | F11: 6570298.9
A12: Switzerland | B12: 71 | E12: UM Media China | F12: 17427906
A13: Austria | B13: 39 | E13: UM Media Czech Republic | F13: 1178763.3
E14: UM Media Denmark | F14: 1703822.5
E15: UM Media Egypt | F15: 348670.34
A16: Belgium | B16: 60 | E16: UM Media Ethiopia | F16: 485725.98
A17: Netherlands | B17: 132 | E17: UM Media France | F17: 16228493
A18: Luxembourg | E18: UM Media Germany | F18: 14734717
A19: Denmark | E19: UM Media Ghana | F19: 541163.29
A20: Finland | E20: UM Media Greece | F20: 1648113
A21: Iceland | E21: UM Media Guinea | F21: 114640.76
A22: Norway | E22: UM Media Hong Kong | F22: 1874057.1
A23: Sweden | E23: UM Media Hungary | F23: 792944.29
A24: Australia | B24: 210 | E24: UM Media India | F24: 27833731
A25: New Zealand | B25: 29 | E25: UM Media Indonesia | F25: 1149398.3
E26: UM Media Ireland | F26: 5212681
E27: UM Media Italy | F27: 6905338.9
A28: Source | E28: UM Media Ivory Coast | F28: 191855.54
E29: UM Media Japan | F29: 8686046
E30: UM Media Kenya | F30: 671892.96
E31: UM Media KSA | F31: 6787650.7
E32: UM Media Kuwait | F32: 1737714
E33: UM Media Lebanon | F33: 623680.02
E34: UM Media Malaysia | F34: 1153375.9
E35: UM Media Malta | F35: 257477.09
E36: UM Media Mexico | F36: 2096855.9
E37: UM Media Morocco | F37: 748497.94
E38: UM Media Netherlands | F38: 4553422.1
E39: UM Media New Zealand | F39: 2871932.7
E40: UM Media Norway | F40: 1644311.2
... E68: Grand Total | F68: 1.022477e+09

Sheet Tourist Departures
A1: Country | B1: Tourist Departures
A2: UAE | B2: 18906000
A3: USA | B3: 1.7093009e+08
A4: France | B4: 49276000
A5: India | B5: 26915000
A6: UK | B6: 93086000
A7: Italy | B7: 62207000
A8: China | B8: 154632000
A9: Saudi Arabia | B9: 27196000
A10: Germany | B10: 99533000
A11: Russia | B11: 45330000
A12: Kuwait | B12: 2950000
A13: Egypt | B13: 43066000
... A27: Belgium | B27: 14191000
A28: Source | B28: https://ourworldindata.org/grapher/international-tourist-departures?tab=table&time=2021..latest
B29: https://www.ons.gov.uk/peoplepopulationandcommunity/leisureandtourism/articles/traveltrends/2023
B30: https://camperchamp.com.au/statistics/australia/?

Sheet TD Raw Data
A1: Entity | B1: International tourist departures
A2: Algeria | B2: 2865000
A3: Argentina | B3: 5142000
A4: Armenia | B4: 1139000
A5: Austria | B5: 11871000
A6: Azerbaijan | B6: 1345000
A7: Belarus | B7: 344000
A8: Belgium | B8: 16005000
A9: Bolivia | B9: 821000
A10: Bulgaria | B10: 5664000
A11: Cambodia | B11: 970000
A12: Canada | B12: 21400000
A13: Chile | B13: 2155000
... A71: Zimbabwe | B71: 1610000
A72: Iceland | B72: 219000 | D72: 2021
A73: Sweden | B73: 5767000 | D73: 2021
A74: United States | B74: 80730000 | D74: 2022
A75: United Kingdom | B75: 71000000 | D75: 2022 | E75: https://www.ons.gov.uk/peoplepopulationandcommunity/leisureandtourism/articles/traveltrends/2023
A76: Australia | B76: 9000000 | D76: 2022 | E76: https://camperchamp.com.au/statistics/australia/?

Sheet Minimum Wage
A1: Country | B1: Hourly Minimum Wage
A2: Armenia | B2: 1.08
A3: Bahrain | B3: 7
A4: Belgium | B4: 13.11
A5: Canada | B5: 12.63
A6: China | B6: 2.05
A7: Egypt | B7: 0.73
A8: France | B8: 12.96
A9: Germany | B9: 13.85
A10: India | B10: 0.6
A11: Italy | B11: 10
A12: Japan | B12: 6.69
A13: Khazakstan | B13: 1.09
... A27: Uzbekistan | B27: 0.48
A28: Source | B28: https://www.datapandas.org/ranking/minimum-wage-by-country
B29: https://www.aboutswitzerland.eda.admin.ch/en/labour-market
B30: https://joinhorizons.com/countries/italy/hiring-employees/minimum-wage/
B31: https://www.investopedia.com/articles/investing/080515/5-developed-countries-without-minimum-wages.asp?utm_source=chatgpt.com

Sheet Hourly Minimum Wage Raw Data
A1: Region | B1: Hourly Minimum Wage
A2: Luxembourg | B2: 13.8
A3: Australia | B3: 12.1
A4: France | B4: 11.7
A5: New Zealand | B5: 11.2
A6: Germany | B6: 10.9
A7: Netherlands | B7: 10.4
A8: Belgium | B8: 10.4
A9: United Kingdom | B9: 10.3
A10: Ireland | B10: 9.6
A11: Canada | B11: 9.5
A12: Israel | B12: 7.9
A13: United States | B13: 7.3
... A32: Mexico | B32: 1.1

Sheet NoofMillionaires
A1: Country | B1: NoofMillionaires
A2: UAE | B2: 116500
A3: USA | B3: 24480000
A4: France | B4: 2796000
A5: India | B5: 796000
A6: UK | B6: 2849000
A7: Italy | B7: 1413000
A8: China | B8: 6190000
A9: Saudi Arabia | B9: 313000
A10: Germany | B10: 2683000
A11: Russia | B11: 353000
A12: Kuwait | B12: 217000
A13: Egypt | B13: 87000
... A27: Belgium | B27: 589000
A28: Source | B28: https://www.datapandas.org/ranking/millionaires-by-country

Sheet Inflation Rate
A1: Country | B1: Inflation Rate
A2: Armenia | B2: 0.031
A3: Bahrain | B3: 0.021
A4: Belgium | B4: 0.034
A5: Canada | B5: 0.029
A6: China | B6: 0.01
A7: Egypt | B7: 0.282
A8: France | B8: 0.028
A9: Germany | B9: 0.026
A10: India | B10: 0.046
A11: Italy | B11: 0.021
A12: Japan | B12: 0.022
A13: Khazakstan | B13: 0.087
... A27: Uzbekistan | B27: 0.09
A28: Source | B28: https://www.theglobaleconomy.com/rankings/inflation/
B187: -6.6
B188: 9.7
B189: 26
B190: 42.2
B191: 58.5
B192: Download data from our database

Sheet NoofMillionaires Raw Data
A1: Country | B1: NoOfMillionaires
A2: United States | B2: 24500000
A3: China | B3: 6200000
A4: Japan | B4: 3400000
A5: United Kingdom | B5: 2800000
A6: France | B6: 2800000
A7: Germany | B7: 2700000
A8: Canada | B8: 2300000
A9: Australia | B9: 2200000
A10: Italy | B10: 1400000
A11: South Korea | B11: 1300000
A12: Switzerland | B12: 1200000
A13: Netherlands | B13: 1100000
... A49: Luxembourg | B49: 85786

Sheet Population
A1: Country | B1: Population(m)
A2: UAE | B2: 11350000
A3: USA | B3: 347402264
A4: France | B4: 66658005
A5: India | B5: 1454606724
A6: UK | B6: 69579448
A7: Italy | B7: 58934177
A8: China | B8: 1424381924
A9: Saudi Arabia | B9: 37989969
A10: Germany | B10: 83600000
A11: Russia | B11: 143936258
A12: Kuwait | B12: 4387109
A13: Egypt | B13: 116275465
... A27: Belgium | B27: 11825551
A28: Source | B28: https://www.theglobaleconomy.com/rankings/population_size/

Sheet Search Volume
B1: 2024 | D1: 2023
A2: Country | B2: SV -Abu Dhabi | C2: SV - Flights to Abu Dhabi | D2: 23SV -Abu Dhabi | E2: 23SV - Flights to Abu Dhabi
A3: UAE | B3: 18791890 | C3: 69430 | D3: 9975490 | E3: 85740 | L3: UAE | M3: {=VLOOKUP(L3:L28,A3:E28,2,FALSE)} -> 18791890 | O3: UAE | P3: {=VLOOKUP(O3:O28,A3:E28,3,FALSE)} -> 69430 | R3: UAE | S3: {=VLOOKUP(R3:R28,A3:E28,4,FALSE)} -> 9975490 | U3: UAE | V3: {=VLOOKUP(U3:U28,A3:E28,5,FALSE)} -> 85740 | X3: 18791890 | Y3: 69430 | Z3: 9975490 | AA3: 85740
A4: USA | B4: 3036780 | C4: 70340 | D4: 2947460 | E4: 48810 | L4: USA | M4: 3036780 | O4: USA | P4: 70340 | R4: USA | S4: 2947460 | U4: USA | V4: 48810 | X4: 3036780 | Y4: 70340 | Z4: 2947460 | AA4: 48810
A5: France | B5: 1319680 | C5: 4240 | D5: 1175450 | E5: 2830 | L5: UK | M5: 2248410 | O5: UK | P5: 169080 | R5: UK | S5: 1782130 | U5: UK | V5: 136400 | X5: 2248410 | Y5: 169080 | Z5: 1782130 | AA5: 136400
A6: India | B6: 3792180 | C6: 206010 | D6: 2800880 | E6: 111580 | L6: Germany | M6: 1384090 | O6: Germany | P6: 5530 | R6: Germany | S6: 1351080 | U6: Germany | V6: 3820 | X6: 1384090 | Y6: 5530 | Z6: 1351080 | AA6: 3820
A7: UK | B7: 2248410 | C7: 169080 | D7: 1782130 | E7: 136400 | L7: France | M7: 1319680 | O7: France | P7: 4240 | R7: France | S7: 1175450 | U7: France | V7: 2830 | X7: 1319680 | Y7: 4240 | Z7: 1175450 | AA7: 2830
A8: Italy | B8: 1076490 | C8: 3370 | D8: 1109260 | E8: 3220 | L8: Egypt | M8: 172870 | O8: Egypt | P8: 14650 | R8: Egypt | S8: 149110 | U8: Egypt | V8: 8400 | X8: 172870 | Y8: 14650 | Z8: 149110 | AA8: 8400
A9: China | B9: 32530 | C9: 160 | D9: 21260 | E9: 160 | L9: Khazakstan | M9: 71900 | O9: Khazakstan | P9: 290 | R9: Khazakstan | S9: 47810 | U9: Khazakstan | V9: 190 | X9: 71900 | Y9: 290 | Z9: 47810 | AA9: 190
A10: Saudi Arabia | B10: 390390 | C10: 17520 | D10: 243830 | E10: 13820 | L10: Bahrain | M10: 94410 | O10: Bahrain | P10: 12270 | R10: Bahrain | S10: 87090 | U10: Bahrain | V10: 12260 | X10: 94410 | Y10: 12270 | Z10: 87090 | AA10: 12260
A11: Germany | B11: 1384090 | C11: 5530 | D11: 1351080 | E11: 3820 | L11: Qatar | M11: 139980 | O11: Qatar | P11: 16220 | R11: Qatar | S11: 98020 | U11: Qatar | V11: 14480 | X11: 139980 | Y11: 16220 | Z11: 98020 | AA11: 14480
A12: Russia | B12: 1447698 | C12: 27896 | D12: 994422 | E12: 18822 | L12: Canada | M12: 604940 | O12: Canada | P12: 9120 | R12: Canada | S12: 575590 | U12: Canada | V12: 6950 | X12: 604940 | Y12: 9120 | Z12: 575590 | AA12: 6950
A13: Kuwait | B13: 156750 | C13: 14530 | D13: 136790 | E13: 11620 | L13: Romania | M13: 286520 | O13: Romania | P13: 760 | R13: Romania | S13: 244350 | U13: Romania | V13: 570 | X13: 286520 | Y13: 760 | Z13: 244350 | AA13: 570
A14: Egypt | B14: 172870 | C14: 14650 | D14: 149110 | E14: 8400 | L14: Oman | M14: 139390 | O14: Oman | P14: 1260 | R14: Oman | S14: 98490 | U14: Oman | V14: 1000 | X14: 139390 | Y14: 1260 | Z14: 98490 | AA14: 1000
A15: Khazakstan | B15: 71900 | C15: 290 | D15: 47810 | E15: 190 | L15: Spain | M15: 641800 | O15: Spain | P15: 2170 | R15: Spain | S15: 609940 | U15: Spain | V15: 1750 | X15: 641800 | Y15: 2170 | Z15: 609940 | AA15: 1750
... A28: Belgium | B28: 285990 | C28: 990 | D28: 221500 | E28: 740 | L28: India | M28: 3792180 | O28: India | P28: 206010 | R28: India | S28: 2800880 | U28: India | V28: 111580 | X28: 3792180 | Y28: 206010 | Z28: 2800880 | AA28: 111580
A29: Source | B29: Google Ad Words

Sheet Keyword List
A1: FOR REFERENCE ONLY
A2: Abu Dhabi - Keywords | B2: United States - Flights | C2: United Kingdon - Flights | D2: Germany - Flights | E2: France - Flights | F2: Spain - Flight | G2: Italy - Flight | H2: Canada - Flight | I2: Australia - Flight | J2: New Zealand - Flight | K2: Belgium - Flight | L2: Netherlands - Flight | M2: Luxemburg - Flight | N2: Denmark - Flight | O2: Finland - Flight | P2: Iceland - Flight | Q2: Norway - Flight | R2: Sweden - Flight | S2: India - Flight | T2: UAE - Flight | U2: China - Flight | V2: Saudi Arabia - Flight | W2: Russia - Flight | X2: Kuwait - Flight | Y2: Egypt - flight | Z2: kazakhstan - Flight | AA2: Bahrain - Flight | AB2: Qatar - Flight | AC2: Romania - Flight | AD2: Oman - Flight | AE2: Japan - Flight | AF2: Uzbekistan - Flight | AG2: South Korea - Flight | AH2: Armenia - Flight | AI2: Poland - Flight
A3: sheikh zayed grand mosque | B3: flights from US to uae | C3: flights from london to abu dhabi | D3: flights from germany to abu dhabi | E3: flight from france to uae | F3: flight from spain to uae | G3: flight from italy to uae | H3: flight from canada to uae | I3: flight from australia to uae | J3: flight from new zealand to abu dhabi | K3: flight from belgium to abu dhabi | L3: flight from netherlands to abu dhabi | M3: flight from luxemburg to abu dhabi | N3: flight from denmark to abu dhabi | O3: flight from finland to abu dhabi | P3: flight from iceland to abu dhabi | Q3: flight from norway to abu dhabi | R3: flight from sweden to abu dhabi | S3: flight from india to abu dhabi | T3: flights to abu dhabi | U3: flights to abu dhabi | V3: flights to abu dhabi | W3: flights to abu dhabi | X3: flights to abu dhabi | Y3: flights to abu dhabi | Z3: flights to abu dhabi | AA3: flights to abu dhabi | AB3: flights to abu dhabi | AC3: flights to abu dhabi | AD3: flights to abu dhabi | AE3: flights to abu dhabi | AF3: flights to abu dhabi | AG3: flights to abu dhabi | AH3: flights to abu dhabi | AI3: flights to abu dhabi
A4: abu dhabi mosque | B4: flight from US to abu dhabi | C4: flights from heathrow to abu dhabi | D4: flights from berlin to abu dhabi | E4: flight from france to abu dhabi | F4: flight from spain to abu dhabi | G4: flight from italy to abu dhabi | H4: flight from canada to abu dhabi | I4: flight from australia to abu dhabi | J4: flight from new zealand to uae | K4: flight from belgium to uae | L4: flight from netherlands to uae | M4: flight from luxemburg to uae | N4: flight from denmark to uae | O4: flight from finland to uae | P4: flight from iceland to uae | Q4: flight from norway to uae | R4: flight from sweden to uae | S4: flight from india to uae | T4: abu dhabi flights | U4: abu dhabi flights | V4: abu dhabi flights | W4: abu dhabi flights | X4: abu dhabi flights | Y4: abu dhabi flights | Z4: abu dhabi flights | AA4: abu dhabi flights | AB4: abu dhabi flights | AC4: abu dhabi flights | AD4: abu dhabi flights | AE4: abu dhabi flights | AF4: abu dhabi flights | AG4: abu dhabi flights | AH4: abu dhabi flights | AI4: abu dhabi flights
A5: abu dhabi grand mosque | B5: flight from USA to uae | C5: flights from stansted to abu dhabi | D5: flights from frankfurt to abu dhabi | E5: flight from paris to abu dhabi | F5: flight from barcelona to abu dhabi | G5: flight from rome to abu dhabi | H5: flight from vancouver to abu dhabi | I5: flight from sydney to abu dhabi | J5: flight from nz to abu dhabi | K5: flight from brussels to abu dhabi | L5: flight from amsterdam to abu dhabi | M5: flights to abu dhabi | N5: flight from copenhagen to abu dhabi | O5: flight from helsinki to abu dhabi | P5: flight from reykjavik to abu dhabi | Q5: flight from oslo to abu dhabi | R5: flight from stockholm to abu dhabi | S5: flight from mumbai to abu dhabi | T5: abu dhabi flight | U5: abu dhabi flight | V5: abu dhabi flight | W5: abu dhabi flight | X5: abu dhabi flight | Y5: abu dhabi flight | Z5: abu dhabi flight | AA5: abu dhabi flight | AB5: abu dhabi flight | AC5: abu dhabi flight | AD5: abu dhabi flight | AE5: abu dhabi flight | AF5: abu dhabi flight | AG5: abu dhabi flight | AH5: abu dhabi flight | AI5: abu dhabi flight
A6: palace abu dhabi | B6: flight from USA to abu dhabi | C6: flights from gatwick to abu dhabi | D6: fights from munich to abu dhabi | E6: flights to abu dhabi | F6: flight from madrid to abu dhabi | G6: flight from milan to abu dhabi | H6: flight from montreal to abu dhabi | I6: flight from melbourne to abu dhabi | J6: flight from wellington to abu dhabi | K6: flights to abu dhabi | L6: flights to abu dhabi | M6: abu dhabi flights | N6: flights to abu dhabi | O6: flights to abu dhabi | P6: flights to abu dhabi | Q6: flights to abu dhabi | R6: flights to abu dhabi | S6: flight from hyderabad to abu dhabi | T6: flight abu dhabi | U6: flight abu dhabi | V6: flight abu dhabi | W6: flight abu dhabi | X6: flight abu dhabi | Y6: flight abu dhabi | Z6: flight abu dhabi | AA6: flight abu dhabi | AB6: flight abu dhabi | AC6: flight abu dhabi | AD6: flight abu dhabi | AE6: flight abu dhabi | AF6: flight abu dhabi | AG6: flight abu dhabi | AH6: flight abu dhabi | AI6: flight abu dhabi
A7: qasr al watan | B7: flight from new york to abu dhabi | C7: flights from manchester to abu dhabi | D7: flight from germany to uae | E7: abu dhabi flights | F7: flights to abu dhabi | G7: flight from florence to abu dhabi | H7: flight from toronto to abu dhabi | I7: flight from perth to abu dhabi | J7: flight from auckland to abu dhabi | K7: abu dhabi flights | L7: abu dhabi flights | M7: abu dhabi flight | N7: abu dhabi flights | O7: abu dhabi flights | P7: abu dhabi flights | Q7: abu dhabi flights | R7: abu dhabi flights | S7: flight from pune to abu dhabi | T7: etihad flights to abu dhabi | U7: etihad flights to abu dhabi | V7: etihad flights to abu dhabi | W7: etihad flights to abu dhabi | X7: etihad flights to abu dhabi | Y7: etihad flights to abu dhabi | Z7: etihad flights to abu dhabi | AA7: etihad flights to abu dhabi | AB7: etihad flights to abu dhabi | AC7: etihad flights to abu dhabi | AD7: etihad flights to abu dhabi | AE7: etihad flights to abu dhabi | AF7: etihad flights to abu dhabi | AG7: etihad flights to abu dhabi | AH7: etihad flights to abu dhabi | AI7: etihad flights to abu dhabi
A8: qasr al watan abu dhabi | B8: flight from newark to abu dhabi | C8: flights from uk to abu dhabi | D8: flights to abu dhabi | E8: abu dhabi flight | F8: abu dhabi flights | G8: flights to abu dhabi | H8: flights to abu dhabi | I8: flight from brisbane to abu dhabi | J8: flight from christchurch to abu dhabi | K8: abu dhabi flight | L8: abu dhabi flight | M8: flight abu dhabi | N8: abu dhabi flight | O8: abu dhabi flight | P8: abu dhabi flight | Q8: abu dhabi flight | R8: abu dhabi flight | S8: flight from mumbai to abu dhabi | T8: low cost flights to abu dhabi | U8: low cost flights to abu dhabi | V8: low cost flights to abu dhabi | W8: low cost flights to abu dhabi | X8: low cost flights to abu dhabi | Y8: low cost flights to abu dhabi | Z8: low cost flights to abu dhabi | AA8: low cost flights to abu dhabi | AB8: low cost flights to abu dhabi | AC8: low cost flights to abu dhabi | AD8: low cost flights to abu dhabi | AE8: low cost flights to abu dhabi | AF8: low cost flights to abu dhabi | AG8: low cost flights to abu dhabi | AH8: low cost flights to abu dhabi | AI8: low cost flights to abu dhabi
A9: heritage village abu dhabi | B9: flight from jfk to abu dhabi | C9: flights from glascow to abu dhabi | D9: abu dhabi flights | E9: flight abu dhabi | F9: abu dhabi flight | G9: abu dhabi flights | H9: abu dhabi flights | I9: flights to abu dhabi | J9: flight from queenstown to abu dhabi | K9: flight abu dhabi | L9: flight abu dhabi | M9: etihad flights to abu dhabi | N9: flight abu dhabi | O9: flight abu dhabi | P9: flight abu dhabi | Q9: flight abu dhabi | R9: flight abu dhabi | S9: flight from chennai to abu dhabi | T9: british airways flights to abu dhabi | U9: british airways flights to abu dhabi | V9: british airways flights to abu dhabi | W9: british airways flights to abu dhabi | X9: british airways flights to abu dhabi | Y9: british airways flights to abu dhabi | Z9: british airways flights to abu dhabi | AA9: british airways flights to abu dhabi | AB9: british airways flights to abu dhabi | AC9: british airways flights to abu dhabi | AD9: british airways flights to abu dhabi | AE9: british airways flights to abu dhabi | AF9: british airways flights to abu dhabi | AG9: british airways flights to abu dhabi | AH9: british airways flights to abu dhabi | AI9: british airways flights to abu dhabi
A10: al jahili fort | B10: flight from atlanta to abu dhabi | C10: flights from edinburgh to abu dhabi | D10: abu dhabi flight | E10: etihad flights to abu dhabi | F10: flight abu dhabi | G10: abu dhabi flight | H10: abu dhabi flight | I10: abu dhabi flights | J10: flights to abu dhabi | K10: etihad flights to abu dhabi | L10: etihad flights to abu dhabi | M10: low cost flights to abu dhabi | N10: etihad flights to abu dhabi | O10: etihad flights to abu dhabi | P10: etihad flights to abu dhabi | Q10: etihad flights to abu dhabi | R10: etihad flights to abu dhabi | S10: flight from jaipur to abu dhabi | T10: turkish airlines flight to abu dhabi | U10: turkish airlines flight to abu dhabi | V10: turkish airlines flight to abu dhabi | W10: turkish airlines flight to abu dhabi | X10: turkish airlines flight to abu dhabi | Y10: turkish airlines flight to abu dhabi | Z10: turkish airlines flight to abu dhabi | AA10: turkish airlines flight to abu dhabi | AB10: turkish airlines flight to abu dhabi | AC10: turkish airlines flight to abu dhabi | AD10: turkish airlines flight to abu dhabi | AE10: turkish airlines flight to abu dhabi | AF10: turkish airlines flight to abu dhabi | AG10: turkish airlines flight to abu dhabi | AH10: turkish airlines flight to abu dhabi | AI10: turkish airlines flight to abu dhabi
A11: al jahili fort abu dhabi | B11: flight from la to abu dhabi | C11: flight from uk to uae | D11: flight abu dhabi | E11: low cost flights to abu dhabi | F11: etihad flights to abu dhabi | G11: flight abu dhabi | H11: flight abu dhabi | I11: abu dhabi flight | J11: abu dhabi flights | K11: low cost flights to abu dhabi | L11: low cost flights to abu dhabi | M11: british airways flights to abu dhabi | N11: low cost flights to abu dhabi | O11: low cost flights to abu dhabi | P11: low cost flights to abu dhabi | Q11: low cost flights to abu dhabi | R11: low cost flights to abu dhabi | S11: flight from kolakata to abu dhabi | T11: air arabia flights to abu dhabi | U11: air arabia flights to abu dhabi | V11: air arabia flights to abu dhabi | W11: air arabia flights to abu dhabi | X11: air arabia flights to abu dhabi | Y11: air arabia flights to abu dhabi | Z11: air arabia flights to abu dhabi | AA11: air arabia flights to abu dhabi | AB11: air arabia flights to abu dhabi | AC11: air arabia flights to abu dhabi | AD11: air arabia flights to abu dhabi | AE11: air arabia flights to abu dhabi | AF11: air arabia flights to abu dhabi | AG11: air arabia flights to abu dhabi | AH11: air arabia flights to abu dhabi | AI11: air arabia flights to abu dhabi
A12: ferrari world abu dhabi | B12: flight from los angeles to abu dhabi | C12: flights to abu dhabi | D12: etihad flights to abu dhabi | E12: british airways flights to abu dhabi | F12: low cost flights to abu dhabi | G12: etihad flights to abu dhabi | H12: etihad flights to abu dhabi | I12: flight abu dhabi | J12: abu dhabi flight | K12: british airways flights to abu dhabi | L12: british airways flights to abu dhabi | M12: turkish airlines flight to abu dhabi | N12: british airways flights to abu dhabi | O12: british airways flights to abu dhabi | P12: british airways flights to abu dhabi | Q12: british airways flights to abu dhabi | R12: british airways flights to abu dhabi | S12: flights to abu dhabi | T12: qatar airways flights to abu dhabi | U12: qatar airways flights to abu dhabi | V12: qatar airways flights to abu dhabi | W12: qatar airways flights to abu dhabi | X12: qatar airways flights to abu dhabi | Y12: qatar airways flights to abu dhabi | Z12: qatar airways flights to abu dhabi | AA12: qatar airways flights to abu dhabi | AB12: qatar airways flights to abu dhabi | AC12: qatar airways flights to abu dhabi | AD12: qatar airways flights to abu dhabi | AE12: qatar airways flights to abu dhabi | AF12: qatar airways flights to abu dhabi | AG12: qatar airways flights to abu dhabi | AH12: qatar airways flights to abu dhabi | AI12: qatar airways flights to abu dhabi
A13: warner bros world abu dhabi | B13: flight from miami to abu dhabi | C13: abu dhabi flights | D13: low cost flights to abu dhabi | E13: turkish airlines flight to abu dhabi | F13: british airways flights to abu dhabi | G13: low cost flights to abu dhabi | H13: low cost flights to abu dhabi | I13: etihad flights to abu dhabi | J13: flight abu dhabi | K13: turkish airlines flight to abu dhabi | L13: turkish airlines flight to abu dhabi | M13: air arabia flights to abu dhabi | N13: turkish airlines flight to abu dhabi | O13: turkish airlines flight to abu dhabi | P13: turkish airlines flight to abu dhabi | Q13: turkish airlines flight to abu dhabi | R13: turkish airlines flight to abu dhabi | S13: abu dhabi flights | T13: singapore airlines flight to abu dhabi | U13: singapore airlines flight to abu dhabi | V13: singapore airlines flight to abu dhabi | W13: singapore airlines flight to abu dhabi | X13: singapore airlines flight to abu dhabi | Y13: singapore airlines flight to abu dhabi | Z13: singapore airlines flight to abu dhabi | AA13: singapore airlines flight to abu dhabi | AB13: singapore airlines flight to abu dhabi | AC13: singapore airlines flight to abu dhabi | AD13: singapore airlines flight to abu dhabi | AE13: singapore airlines flight to abu dhabi | AF13: singapore airlines flight to abu dhabi | AG13: singapore airlines flight to abu dhabi | AH13: singapore airlines flight to abu dhabi | AI13: singapore airlines flight to abu dhabi
... A21: corniche beach | B21: etihad flights to abu dhabi | C21: qatar airways flights to abu dhabi | D21: air baltic flight to abu dhabi | E21: klm flight to abu dhabi | F21: saudia flight to abu dhabi | G21: air baltic flight to abu dhabi | H21: air baltic flight to abu dhabi | I21: finnair flight to abu dhabi | J21: japan airlines flight to abu dhabi | K21: klm flight to abu dhabi | L21: klm flight to abu dhabi | M21: swiss air flight to abu dhabi | N21: klm flight to abu dhabi | O21: klm flight to abu dhabi | P21: klm flight to abu dhabi | Q21: klm flight to abu dhabi | R21: klm flight to abu dhabi | S21: qatar airways flights to abu dhabi | T21: air india flight to abu dhabi | U21: air india flight to abu dhabi | V21: air india flight to abu dhabi | W21: air india flight to abu dhabi | X21: air india flight to abu dhabi | Y21: air india flight to abu dhabi | Z21: air india flight to abu dhabi | AA21: air india flight to abu dhabi | AB21: air india flight to abu dhabi | AC21: air india flight to abu dhabi | AD21: air india flight to abu dhabi | AE21: air india flight to abu dhabi | AF21: air india flight to abu dhabi | AG21: flight from south korea to uae | AH21: air india flight to abu dhabi | AI21: air india flight to abu dhabi
A22: corniche beach abu dhabi | B22: low cost flights to abu dhabi | C22: singapore airlines flight to abu dhabi | D22: saudia flight to abu dhabi | E22: swiss air flight to abu dhabi | F22: klm flight to abu dhabi | G22: saudia flight to abu dhabi | H22: saudia flight to abu dhabi | I22: air baltic flight to abu dhabi | J22: finnair flight to abu dhabi | K22: swiss air flight to abu dhabi | L22: swiss air flight to abu dhabi | M22: air france flight to abu dhabi | N22: swiss air flight to abu dhabi | O22: swiss air flight to abu dhabi | P22: swiss air flight to abu dhabi | Q22: swiss air flight to abu dhabi | R22: swiss air flight to abu dhabi | S22: singapore airlines flight to abu dhabi | U22: china flight to uae | V22: flight from saudi to uae | W22: flight from russia to abu dhabi | X22: flight from kuwait to uae | Y22: flight from egypt to uae | Z22: flight from kazakhstan to abu dhabi | AA22: flight from bahrain to uae | AB22: flight from qatar to uae | AC22: flight from romania to uae | AD22: flight from oman to uae | AE22: flight from japan to uae | AF22: flight from uzbekistan to uae | AG22: flight from south korea to abu dhabi | AH22: flight from armenia to abu dhabi | AI22: flights from poland to uae
A23: jebel hafeet | B23: british airways flights to abu dhabi | C23: japan airlines flight to abu dhabi | D23: klm flight to abu dhabi | E23: air france flight to abu dhabi | F23: swiss air flight to abu dhabi | G23: klm flight to abu dhabi | H23: klm flight to abu dhabi | I23: saudia flight to abu dhabi | J23: air baltic flight to abu dhabi | K23: air france flight to abu dhabi | L23: air france flight to abu dhabi | N23: air france flight to abu dhabi | O23: air france flight to abu dhabi | P23: air france flight to abu dhabi | Q23: air france flight to abu dhabi | R23: air france flight to abu dhabi | S23: japan airlines flight to abu dhabi | U23: flight from china to uae | V23: flight from saudi to abu dhabi | W23: flight from russia to uae | X23: flight from kuwait to abu dhabi | Y23: flight from egypt to abu dhabi | Z23: flight from kazakhstan to uae | AA23: flight from bahrain to abu dhabi | AB23: flight from qatar to abu dhabi | AC23: flight from romania to abu dhabi | AD23: flight from oman to abu dhabi | AE23: flight from japan to abu dhabi | AF23: flight from uzbekistan to abu dhabi | AG23: flight from seoul to abu dhabi | AH23: flight from armenia to uae | AI23: flights from poland to abu dhabi
A24: jebel hafeet abu dhabi | B24: turkish airlines flight to abu dhabi | C24: finnair flight to abu dhabi | D24: swiss air flight to abu dhabi | F24: air france flight to abu dhabi | G24: swiss air flight to abu dhabi | H24: swiss air flight to abu dhabi | I24: klm flight to abu dhabi | J24: saudia flight to abu dhabi | S24: finnair flight to abu dhabi | U24: flight from china to abu dhabi | V24: flight from saudi arabia to abu dhabi | W24: flight from moscow to abu dhabi | Y24: flight from cairo to abu dhabi | Z24: flight from astana to abu dhabi | AB24: flight from doha to abu dhabi | AC24: flight from bucharest to abu dhabi | AE24: flight from tokyo to abu dhabi | AF24: flight from tashkent to abu dhabi | AG24: flight from busan to abu dhabi | AH24: flight from yerevan to abu dhabi | AI24: flights from warsaw to abu dhabi
A25: saadiyat island | B25: air arabia flights to abu dhabi | C25: air baltic flight to abu dhabi | D25: air france flight to abu dhabi | G25: air france flight to abu dhabi | H25: air france flight to abu dhabi | I25: swiss air flight to abu dhabi | J25: klm flight to abu dhabi | S25: air baltic flight to abu dhabi | U25: flight from beijing to abu dhabi | V25: flight from riyadh to abu dhabi | Y25: flight from Sharm El Sheikh to abu dhabi | AE25: flight from osaka to abu dhabi
A26: saadiyat island abu dhabi | B26: qatar airways flights to abu dhabi | C26: saudia flight to abu dhabi | I26: air france flight to abu dhabi | J26: swiss air flight to abu dhabi | S26: saudia flight to abu dhabi | U26: flight from shanghai to abu dhabi | V26: flight from jeddah to abu dhabi
A27: desert safari abu dhabi | B27: singapore airlines flight to abu dhabi | C27: klm flight to abu dhabi | J27: air france flight to abu dhabi | S27: klm flight to abu dhabi | U27: flight from shenzen to abu dhabi
A28: souks abu dhabi | B28: japan airlines flight to abu dhabi | C28: swiss air flight to abu dhabi | S28: swiss air flight to abu dhabi
A29: abu dhabi shopping | B29: finnair flight to abu dhabi | C29: air france flight to abu dhabi | P29: UAE | S29: air france flight to abu dhabi
A30: louvre abu dhabi museum | B30: air baltic flight to abu dhabi | P30: USA | S30: air india flight to abu dhabi
A31: louvre abu dhabi museum | B31: saudia flight to abu dhabi | P31: France
A32: things to do in abu dhabi | B32: klm flight to abu dhabi | P32: India
A33: abu dhabi itinerary | B33: swiss air flight to abu dhabi | P33: UK
A34: day tour abu dhabi | B34: air france flight to abu dhabi | P34: Italy
A35: top sights in abu dhabi | P35: China
A36: activities abu dhabi | P36: Saudi Arabia
A37: abu dhabi tours | P37: Germany
A38: private abu dhabi tour | P38: Russia
A39: qasr al hosn | P39: Kuwait
A40: wasr al hosn abu dhabi | P40: Egypt
A41: yas marina circuit | P41: Khazakstan
A42: desert adventures abu dhabi | P42: Bahrain
A43: what to do in abu dhabi | P43: Qatar
A44: visit abu dhabi | P44: Canada
A45: abu dhabi | P45: Romania
A46: abu dhabi travel | P46: Oman
... A49: trip to abu dhabi | P49: Japan
P50: Uzbekistan
P51: Poland
P52: South Korea
P53: Armenia
P54: Belgium

Sheet StandardofLiving
A1: Country | B1: HDI
A2: UAE | B2: 0.94
A3: USA | B3: 0.938
A4: France | B4: 0.92
A5: India | B5: 0.685
A6: UK | B6: 0.946
A7: Italy | B7: 0.915
A8: China | B8: 0.797
A9: Saudi Arabia | B9: 0.9
A10: Germany | B10: 0.959
A11: Russia | B11: 0.832
A12: Kuwait | B12: 0.852
A13: Egypt | B13: 0.754
... A27: Belgium | B27: 0.951
A28: Source | B28: https://www.datapandas.org/ranking/hdi-by-country?

Sheet GDP Per Capita
A1: Country | B1: GDP Per Capita
A2: UAE | B2: 49377.564
A3: USA | B3: 85809.9
A4: France | B4: 46150.488
A5: India | B5: 2696.6639
A6: UK | B6: 52636.787
A7: Italy | B7: 40226.047
A8: China | B8: 13303.148
A9: Saudi Arabia | B9: 35057.225
A10: Germany | B10: 55800.219
A11: Russia | B11: 14889.019
A12: Kuwait | B12: 32213.862
A13: Egypt | B13: 3338.4737
... A27: Belgium | B27: 55954.611
A28: Source | B28: https://www.datapandas.org/ranking/gdp-per-capita-by-country

Sheet MAS
A1: Country | B1: Median Annual Salary (USD)
A2: UAE | B2: 22037
A3: USA | B3: 67468
A4: France | B4: 48072
A5: India | B5: 10475
A6: UK | B6: 45486
A7: Italy | B7: 43390
A8: China | B8: 11434
A9: Saudi Arabia | B9: 18257
A10: Germany | B10: 55055
A11: Russia | B11: 15400
A12: Kuwait | B12: 35600
A13: Egypt | B13: 12500
... A27: Belgium | B27: 49749

Sheet Population Raw Data
A1: Countries | B1: Population size, 2023
A2: India | B2: 1428.63 | D2: Source | E2: https://www.theglobaleconomy.com/rankings/population_size/
A3: China | B3: 1410.71
A4: United States | B4: 334.91
A5: Indonesia | B5: 277.53
A6: Pakistan | B6: 240.49
A7: Nigeria | B7: 223.8
A8: Brazil | B8: 216.42
A9: Bangladesh | B9: 172.95
A10: Russia | B10: 143.83
A11: Mexico | B11: 128.46
A12: Ethiopia | B12: 126.53
A13: Japan | B13: 124.52
A14: Philippines | B14: 117.34
... A197: Tuvalu | B197: 0.01

Sheet GDP
B1: GDP - 2024 | C1: GDP - 2025 | D1: GDP - Growth
A2: USA | B2: 29184 | C2: 30507 | D2: =C2/B2-1 -> 0.045333059
A3: UK | B3: 3644 | C3: 3839 | D3: =C3/B3-1 -> 0.053512623
A4: Germany | B4: 4658 | C4: 4744 | D4: =C4/B4-1 -> 0.01846286
A5: France | B5: 3162 | C5: 3211 | D5: =C5/B5-1 -> 0.015496521
A6: Spain | B6: 1722 | C6: 1799 | D6: =C6/B6-1 -> 0.044715447
A7: Italy | B7: 2372 | C7: 2422 | D7: =C7/B7-1 -> 0.021079258
A8: Japan | B8: 4026 | C8: 4186 | D8: =C8/B8-1 -> 0.039741679
A9: Netherlands | B9: 1227 | C9: 1272 | D9: =C9/B9-1 -> 0.036674817
A10: China | B10: 18748 | C10: 19231 | D10: =C10/B10-1 -> 0.025762748
A11: South Korea | B11: 1869 | C11: 1790 | D11: =C11/B11-1 -> -0.042268593
A12: Canada | B12: 2241 | C12: 2225 | D12: =C12/B12-1 -> -0.0071396698
A13: India | B13: 3909 | C13: 4187 | D13: =C13/B13-1 -> 0.071117933
... A27: Russia | B27: 2161 | C27: 2076 | D27: =C27/B27-1 -> -0.039333642

Sheet Cost of Media
A1: Country | B1: Media Cost
A2: UAE | B2: =1/VLOOKUP(A2,'Magna Cost of Media'!$A$5:$K$56,11,FALSE) -> #N/A
A3: USA | B3: =1/VLOOKUP(A3,'Magna Cost of Media'!$A$5:$K$56,11,FALSE) -> #N/A
A4: France | B4: =1/VLOOKUP(A4,'Magna Cost of Media'!$A$5:$K$56,11,FALSE) -> 0.042772724
A5: India | B5: =1/VLOOKUP(A5,'Magna Cost of Media'!$A$5:$K$56,11,FALSE) -> 0.21913073
A6: UK | B6: =1/VLOOKUP(A6,'Magna Cost of Media'!$A$5:$K$56,11,FALSE) -> #N/A
A7: Italy | B7: =1/VLOOKUP(A7,'Magna Cost of Media'!$A$5:$K$56,11,FALSE) -> 0.15021632
A8: China | B8: =1/VLOOKUP(A8,'Magna Cost of Media'!$A$5:$K$56,11,FALSE) -> 0.041092957
A9: Saudi Arabia | B9: =AVERAGE(B24:B25) -> 0.044300189
A10: Germany | B10: =AVERAGE(B16:B18) -> #N/A
A11: Russia | B11: =AVERAGE(B19:B23) -> #N/A
A12: Kuwait | B12: =1/VLOOKUP(A12,'Magna Cost of Media'!$A$5:$K$56,11,FALSE) -> #N/A
A13: Egypt | B13: =1/VLOOKUP(A13,'Magna Cost of Media'!$A$5:$K$56,11,FALSE) -> #N/A
A14: Khazakstan
A15: Bahrain
A16: Qatar | B16: =1/VLOOKUP(A16,'Magna Cost of Media'!$A$5:$K$56,11,FALSE) -> #N/A
A17: Canada | B17: =1/VLOOKUP(A17,'Magna Cost of Media'!$A$5:$K$56,11,FALSE) -> 0.031657955
A18: Romania
A19: Oman | B19: =1/VLOOKUP(A19,'Magna Cost of Media'!$A$5:$K$56,11,FALSE) -> #N/A
A20: Spain | B20: =1/VLOOKUP(A20,'Magna Cost of Media'!$A$5:$K$56,11,FALSE) -> 0.096328877
A21: Netherlands
A22: Japan | B22: =1/VLOOKUP(A22,'Magna Cost of Media'!$A$5:$K$56,11,FALSE) -> 0.048190819
A23: Uzbekistan | B23: =1/VLOOKUP(A23,'Magna Cost of Media'!$A$5:$K$56,11,FALSE) -> #N/A
A24: Poland | B24: =1/VLOOKUP(A24,'Magna Cost of Media'!$A$5:$K$56,11,FALSE) -> 0.056841129
A25: South Korea | B25: =1/VLOOKUP(A25,'Magna Cost of Media'!$A$5:$K$56,11,FALSE) -> 0.031759249
A26: Armenia
A27: Belgium
A28: Source | B28: https://www.datapandas.org/ranking/median-income-by-country?

Sheet Magna Cost of Media
A4: Title | B4: CPM by Market
A5: MARKET | B5: Free TV | C5: Pay TV | D5: Video | E5: Display | F5: News. | G5: Mags. | H5: Radio | I5: OOH | J5: Total Traditional | K5: All Media Average
A6: World | B6: 54.053017 | C6: 28.92331 | D6: - | E6: 7.8042848 | F6: 79.915909 | G6: 30.815871 | H6: 5.6713173 | I6: - | J6: 41.490259 | K6: 36.005446
A7: APAC | B7: 19.312819 | C7: 31.32084 | D7: - | E7: 6.1285057 | F7: 42.259308 | G7: 45.038301 | H7: 3.7056351 | I7: - | J7: 22.428817 | K7: 21.359846
A8: EMEA | B8: 26.089496 | C8: 16.703079 | D8: - | E8: 8.8891081 | F8: 56.974118 | G8: 23.104166 | H8: 6.2935168 | I8: - | J8: 27.415334 | K8: 25.49801
A9: Latin America | B9: 7.6345834 | C9: 18.314488 | D9: - | E9: 0.8419234 | F9: 43.202452 | G9: 45.040086 | H9: 5.1197142 | I9: - | J9: 9.7288796 | K9: 8.2100519
A10: North America | B10: 110.32174 | C10: 30.16035 | D10: - | E10: 8.9279738 | F10: 126.74417 | G10: 34.130025 | H10: 5.7288352 | I10: - | J10: 59.968564 | K10: 52.312025
A11: Western Europe | B11: 28.807053 | C11: 17.836112 | D11: - | E11: 9.0702786 | F11: 58.476312 | G11: 23.250215 | H11: 6.931666 | I11: - | J11: 29.565247 | K11: 27.220892
A12: Central & Eastern Europe | B12: 6.9783568 | C12: 33.182539 | D12: - | E12: 5.5326927 | F12: 23.474048 | G12: 22.027703 | H12: 4.2910034 | I12: - | J12: 11.677412 | K12: 11.022245
A14: Australia | B14: 49.654922 | C14: 71.266259 | D14: - | E14: 3.3165035 | F14: 74.995085 | G14: 21.373177 | H14: 3.2976625 | I14: - | J14: 39.68934 | K14: 33.250017
A15: Austria | B15: 72.373348 | C15: - | D15: - | E15: 12.914603 | F15: 86.080232 | G15: 56.656301 | H15: 6.2941941 | I15: - | J15: 67.020746 | K15: 62.628173
A16: Belgium | B16: 10.807536 | C16: - | D16: - | E16: 10.383852 | F16: 17.343902 | G16: 17.313515 | H16: 4.2789355 | I16: - | J16: 10.292966 | K16: 14.047538
A17: Brazil | B17: 5.0576016 | C17: 16.987463 | D17: - | E17: 0.61937626 | F17: 50.062097 | G17: 47.596705 | H17: 7.263028 | I17: - | J17: 8.4665669 | K17: 6.781275
A18: Bulgaria | B18: 12.513994 | C18: 9.7075486 | D18: - | E18: 5.9048801 | F18: 80.463342 | G18: 106.95767 | H18: 4.2832506 | I18: - | J18: 13.57521 | K18: 12.39659
A19: Canada | B19: 36.297165 | C19: 33.879606 | D19: - | E19: 9.7917981 | F19: 73.381506 | G19: 17.841653 | H19: 7.2103774 | I19: - | J19: 30.906179 | K19: 31.587637
A20: China | B20: 37.77868 | C20: - | D20: - | E20: 8.0039624 | F20: - | G20: - | H20: - | I20: - | J20: 28.909698 | K20: 24.33507
A21: Colombia | B21: 3.8132599 | C21: 3.4512573 | D21: - | E21: - | F21: - | G21: - | H21: - | I21: - | J21: 3.6824238 | K21: 3.6824238
A22: Croatia | B22: 12.743192 | C22: 11.496699 | D22: - | E22: 3.9510142 | F22: 16.000696 | G22: 29.8207 | H22: 7.4627615 | I22: - | J22: 12.59068 | K22: 11.959554
A23: Czech | B23: 9.728609 | C23: 233.60155 | D23: - | E23: 7.3322775 | F23: 29.678092 | G23: 18.766976 | H23: 4.7922645 | I23: - | J23: 14.561393 | K23: 12.59993
A24: Denmark | B24: 22.670385 | C24: - | D24: - | E24: 5.710437 | F24: 15.718246 | G24: 20.221638 | H24: 5.6510032 | I24: - | J24: 17.025159 | K24: 16.847843
A25: Finland | B25: 26.024138 | C25: - | D25: - | E25: 26.448738 | F25: 43.857989 | G25: 68.597967 | H25: 7.2830973 | I25: - | J25: 31.927266 | K25: 32.935902
A26: France | B26: 36.002335 | C26: 260.22487 | D26: - | E26: 6.4166781 | F26: 19.637808 | G26: 15.657436 | H26: 9.2242275 | I26: - | J26: 26.187232 | K26: 23.379386
A27: Germany | B27: 37.576187 | C27: 45.703669 | D27: - | E27: 12.469444 | F27: 91.398731 | G27: 24.752859 | H27: 6.1647014 | I27: - | J27: 48.47188 | K27: 42.193897
A28: Greece | B28: 8.9339366 | C28: - | D28: - | E28: 0.515 | F28: 28.837512 | G28: 22.85467 | H28: 28.889149 | I28: - | J28: 13.741056 | K28: 11.06458
A29: Hungary | B29: 2.6781086 | C29: - | D29: - | E29: 3.6976007 | F29: 27.80785 | G29: 26.222692 | H29: 8.7311471 | I29: - | J29: 9.2914403 | K29: 8.5861948
A30: India | B30: 1.5340051 | C30: - | D30: - | E30: 2.0443091 | F30: 11.235016 | G30: 3.2924071 | H30: 1.4814447 | I30: - | J30: 4.6403451 | K30: 4.5634858
A31: Indonesia | B31: 4.7871566 | C31: 65.484329 | D31: - | E31: 0.54 | F31: 120.13963 | G31: 318.72215 | H31: 0.82517705 | I31: - | J31: 22.318799 | K31: 18.468883
A32: Ireland | B32: 84.437434 | C32: 36.824816 | D32: - | E32: 9.8567823 | F32: 125.63912 | G32: 40.660568 | H32: 2.5993691 | I32: - | J32: 77.10003 | K32: 56.415856
A33: Italy | B33: 3.6226985 | C33: 14.096264 | D33: - | E33: - | F33: 6.2544753 | G33: 3.5565201 | H33: 1.3911677 | I33: - | J33: 4.1786605 | K33: 6.6570664
A34: Japan | B34: 5.0517886 | C34: - | D34: - | E34: - | F34: 52.555478 | G34: 48.90049 | H34: 2.4974201 | I34: - | J34: 20.589649 | K34: 20.750841
A35: Malaysia | B35: 6.9443321 | C35: 16.56589 | D35: - | E35: 8.4629857 | F35: 10.516196 | G35: 6.2071659 | H35: 2.3389021 | I35: - | J35: 13.757982 | K35: 13.398275
A36: Mexico | B36: 12.889247 | C36: 36.519039 | D36: - | E36: 1.0156938 | F36: 13.2149 | G36: 33.604887 | H36: 2.4606947 | I36: - | J36: 13.026143 | K36: 11.085339
A37: Morocco | B37: 0.94080462 | C37: - | D37: - | E37: 0.5 | F37: - | G37: - | H37: 4.105604 | I37: - | J37: 2.2009241 | K37: 1.9455997
A38: Netherlands | B38: 36.387803 | C38: - | D38: - | E38: - | F38: - | G38: - | H38: 6.0737171 | I38: - | J38: 29.172508 | K38: 28.591309
A39: New Zealand | B39: 7.997782 | C39: 4.9454373 | D39: - | E39: 11.854083 | F39: 24.345585 | G39: 10.387699 | H39: 6.9531235 | I39: - | J39: 9.7840765 | K39: 10.617103
A40: Norway | B40: 17.577524 | C40: - | D40: - | E40: 19.218214 | F40: 30.858466 | G40: 12.154063 | H40: 6.7529647 | I40: - | J40: 17.147185 | K40: 19.285296
A41: Peru | B41: 11.454718 | C41: 30.494412 | D41: - | E41: - | F41: 45.871242 | G41: 29.052013 | H41: 2.9932734 | I41: - | J41: 12.350223 | K41: 12.34709
A42: Poland | B42: 5.9650461 | C42: 36.860968 | D42: - | E42: - | F42: - | G42: - | H42: - | I42: - | J42: 17.627151 | K42: 17.592895
A43: Portugal | B43: 3.3937991 | C43: 4.9278588 | D43: - | E43: 2.1247709 | F43: 8.7147512 | G43: 10.499204 | H43: 0.98494257 | I43: - | J43: 3.7525245 | K43: 3.8769435
A44: Romania | B44: 9.1220773 | C44: - | D44: - | E44: 0.575 | F44: 16.052272 | G44: 11.192633 | H44: 0.535 | I44: - | J44: 8.2159645 | K44: 7.5190444
A45: Serbia | B45: 1.2978112 | C45: 0.94974246 | D45: - | E45: 0.32975815 | F45: 20.469299 | G45: 72.477979 | H45: 1.3660045 | I45: - | J45: 4.891367 | K45: 4.4913328
A46: Singapore | B46: 16.879086 | C46: - | D46: - | E46: 12.76249 | F46: 9.6816915 | G46: 27.15895 | H46: 4.7329605 | I46: - | J46: 12.206186 | K46: 12.364404
A47: South Africa | B47: 2.4564466 | C47: 4.4471631 | D47: - | E47: 16.481828 | F47: 9.795601 | G47: 4.3558349 | H47: 1.547198 | I47: - | J47: 3.9272818 | K47: 4.0922992
A48: South Korea | B48: 39.545494 | C48: 36.763642 | D48: - | E48: 1.4733307 | F48: 48.48755 | G48: 28.997418 | H48: 16.170046 | I48: - | J48: 39.075706 | K48: 31.48689
A49: Spain | B49: 5.299714 | C49: 4.8760333 | D49: - | E49: 8.9017451 | F49: 18.707895 | G49: 9.8306405 | H49: 14.548762 | I49: - | J49: 9.8103251 | K49: 10.381103
A50: Sweden | B50: 13.383982 | C50: - | D50: - | E50: - | F50: - | G50: 16.941519 | H50: 0.525 | I50: - | J50: 11.27427 | K50: 11.118477
A51: Switzerland | B51: 184.04614 | C51: - | D51: - | E51: 27.448979 | F51: 56.121163 | G51: 49.06403 | H51: 26.283797 | I51: - | J51: 85.351241 | K51: 75.048354
A52: Taiwan | B52: 8.3165119 | C52: 9.5109671 | D52: - | E52: - | F52: 16.197512 | G52: 6.7822298 | H52: - | I52: - | J52: 9.893971 | K52: 9.893971
A53: Thailand | B53: 3.0012995 | C53: - | D53: - | E53: 3.6231381 | F53: 16.749216 | G53: 47.476994 | H53: 1.5597981 | I53: - | J53: 6.6875177 | K53: 6.4523684
A54: United Kingdom | B54: 11.005177 | C54: 6.8790176 | D54: - | E54: 2.3428252 | F54: 0.49 | G54: 0.49 | H54: 2.7006124 | I54: - | J54: 7.4173888 | K54: 12.144432
A55: United States | B55: 112.49481 | C55: 30.060972 | D55: - | E55: - | F55: 129.53398 | G55: 34.264291 | H55: 5.6549395 | I55: - | J55: 61.070829 | K55: 53.033424
A56: Uruguay | B56: 24.044759 | C56: - | D56: - | E56: - | F56: 57.499128 | G56: 41.980794 | H56: 1.472708 | I56: - | J56: 23.312772 | K56: 23.312772

Sheet Perception Scores
B1: SENTIMENT | C1: EXPLANATION | E1: PERCEPTION | F1: EXPLANATION
A2: What is it? | B2: Warmth, safety perception, brand trust SIGNALS - Safety rankings, regional ties, media tone, social/ cultural alignment | E2: Awareness, familiarit, clarity SIGNALS - Global indices, brand distinctiveness, country rankings
A3: Country
A4: UAE | B4: 100 | C4: High emotional connection and brand pride as the home market. | E4: 100 | F4: Complete awareness and clarity of positioning as the capital.
A5: KSA | B5: 96 | C5: Strong cultural and lifestyle alignment drives emotional warmth. | E5: 92 | F5: Abu Dhabi is well understood and clearly positioned vs. Dubai.
A6: Kuwait | B6: 96 | C6: Regional familiarity and repeat travel build strong emotional affinity. | E6: 88 | F6: Frequent visitation builds high familiarity and brand understanding.
A7: India | B7: 88 | C7: Positive sentiment fueled by safety perception and diaspora links. | E7: 80 | F7: General awareness is strong but full brand image still forming.
A8: UK | B8: 84 | C8: Strong emotional response due to perceived safety and cultural appeal. | E8: 84 | F8: Brand is growing with high-profile assets like Louvre and F1.
A9: Germany | B9: 84 | C9: Trust and cultural appreciation drive solid emotional sentiment. | E9: 80 | F9: Moderate familiarity, with a clear image among culture-seekers.
A10: China | B10: 80 | C10: Prestige and innovation appeal support positive associations. | E10: 72 | F10: Recognized by affluent segments but broader familiarity is limited.
A11: France | B11: 80 | C11: Cultural partnership helps sentiment among affluent travelers. | E11: 72 | F11: Awareness exists but brand meaning still developing beyond Louvre.
A12: Russia | B12: 76 | C12: Historical interest supports residual positive emotion. | E12: 76 | F12: Perception is slightly fading due to decreased visibility.
A13: Italy | B13: 76 | C13: Luxury and cultural appeal evoke moderate sentiment in niches. | E13: 68 | F13: Limited brand distinction from Dubai; low general awareness.
A14: USA | B14: 72 | C14: Positive among exposed audiences, but limited emotional connection overall. | E14: 68 | F14: Recognition remains low despite event exposure and media efforts.
A15: Egypt
A16: Khazakstan
A17: Bahrain
A18: Qatar
A19: Canada
A20: Romania
A21: Oman
A22: Spain
A23: Netherlands
A24: Japan
A25: Uzbekistan
A26: Poland
... A30: Source

Sheet Sheet1

Sheet Inflation Rate Raw Data
A1: Countries | B1: Inflation, 2023
A2: Lebanon | B2: 221.3
A3: Turkey | B3: 53.9
A4: Suriname | B4: 51.6
A5: Sierra Leone | B5: 47.6
A6: Iran | B6: 44.6
A7: Ghana | B7: 38.1
A8: Haiti | B8: 36.8
A9: Egypt | B9: 33.9
A10: Laos | B10: 31.2
A11: Pakistan | B11: 30.8
A12: Ethiopia | B12: 30.2
A13: Malawi | B13: 28.8
... A161: Seychelles | B161: -1
